Workbook

Sheet Executive_Summary
A1: Phase 3 Data Quality Audit — Executive Summary for Tom Nguyen
A2: Five exports audited: Outpatients (PAS), Inpatients (EHR), ED (EDIS), Theatres (TMS), Workforce (WRS). 4,523 rows, 63 issues logged. All counts are live formulas — see DQ_Issue_Log and Task_Workings.
A4: 1. What is wrong — the errors that change performance figures
A5: ED 4-hour | D5: 35 missing departure times + 9 duplicates + 4 negative times produce three figures: 79.9%, 83.2%, 83.9%. Validated figure: 83.1%.
A6: DNA rate | D6: Status miscoding is small (2 rows). The bigger problem is method and timing: the PAS 14.1% = DNA ÷ (ATT+DNA); DNA outcomes are recorded late (Jan 25.8% → Mar 3.7%). Validated Q1 figure: 13.9% — well above the 8% target.
A7: LWBS | D7: 'LEFT' code (120 rows) is undefined: LWBS is 2.4% or 14.7% depending on its meaning.
A8: ED mortality | D8: 'DIED' on 14.6% of attendances is not credible — likely miscoding. Do not quote any ED mortality figure.
A9: HRG income | D9: 28 blank HRG codes = £51,800 — but over six months, not per month. The brief's £621k/yr figure is overstated ~6×.
A10: Readmissions | D10: 44 blank flags: rate is 9.0%–12.3%, either side of the 10% target.
A11: Theatres | D11: Utilisation_Pct column wrong in 7 rows; 4 rows exceed 100%. The 64% vs 72% dispute is definitional (T4 + overruns).
A12: Agency spend | D12: 15 blank flags + 24 test records. February range: £49,280–£53,515 (narrow — blanks are only 1.4%).
A13: Linkage | D13: No outpatient or ED NHS Number appears in the inpatient file — PAS, EDIS and EHR cannot currently be joined.
A14: NHS Numbers | D14: 188 NHS Numbers start with 0 — opening the CSV in Excel drops the zero. This is the 'truncation' issue.
A16: 2. What you can trust today
A17: KPI | B17: Validated figure | C17: Can we quote it? | D17: Caveat
A18: ED 4-hour | B18: =Task_Workings!B52 -> 0.83135135 | C18: Amber | D18: Quote 83.1% with range 80.1%–83.8% (35 missing departures). Differs from the 81.3% in the brief — reconcile with Sarah's manual count.
A19: DNA rate (Q1, quarterly) | B19: =Task_Workings!B16 -> 0.13919414 | C19: Amber | D19: Quarterly only — monthly figures are distorted by late outcome recording.
A20: HRG coding completeness | B20: =1-Task_Workings!B25 -> 0.97666667 | C20: Green | D20: 97.7% coded vs 98% target; 28 episodes to code.
A21: Theatre utilisation (elective) | B21: =Task_Workings!B60 -> 0.65698479 | C21: Amber | D21: Sessions-based, T1–T3. Definition to be ratified.
A22: Agency spend (Feb) | B22: £49k–£54k | C22: Amber | D22: Range, not a point estimate; reconcile to ledger.
A23: 30-day readmissions | B23: 9.0%–12.3% | C23: Red | D23: 44 blank flags — back-fill before quoting.
A24: LWBS rate | B24: 2.4% or 14.7% | C24: Red | D24: Depends on definition of 'LEFT'.
A25: RTT 18-week | B25: Not from this extract | C25: Red | D25: Outpatient extract holds only 131 open pathways; only 41% of those are within 18 weeks — inconsistent with the 74.8% headline. Needs the full waiting list.
A26: ED mortality / DIED | B26: Do not use | C26: Red | D26: 141 'DIED' codes are not credible.
A28: 3. Priority order for fixing
A29: 1. ED departures and 'DIED'/'LEFT' codes — ED 4-hour is the headline NHS England will test; mortality miscoding is a governance risk.
A30: 2. DNA definition and outcome recording — adopt DNA ÷ (ATT+DNA+REF), report quarterly, 48-hour outcome standard.
A31: 3. HRG blanks (28 episodes) — £51,800 recoverable before the SUS deadline.
A32: 4. NHS Number import as text + PDS back-fill — fixes linkage for readmissions and duplicates.
A33: 5. Readmission flag back-fill — moves RA30 from Unknown to known.
A34: 6. Theatre definition (GIRFT, T1–T3, capped) and TMS session fix.
A35: 7. Workforce: make Agency_Flag mandatory, remove ST-99 test data, escalate 8 shifts over 13 hours to HR.

Sheet DQ_Issue_Log
A1: Issue_ID | B1: Task | C1: 1. Sheet / dataset | D1: Source | E1: 2. Column | F1: 3. Issue type | G1: Issue found | H1: 4. Rows affected | I1: % of rows | J1: 5. Severity | K1: 6. Recommended action | L1: Example record(s) | M1: KPI(s) affected | N1: Impact on the KPI | O1: Root cause (likely) | P1: Owner | Q1: Status
A2: OP-01 | B2: T1 | C2: Outpatients | D2: PAS | E2: Attendance_Status | F2: Non-standard value | G2: Non-standard status values: 'attended' (1) and 'N/A' (1). Valid codes are ATT, DNA, CAN, REF. | H2: =SUMPRODUCT(--(OP_Raw!J2:J581<>""),--ISERROR(MATCH(OP_Raw!J2:J581,{"ATT","DNA","CAN","REF"},0))) -> 2 | I2: =H2/(COUNTA(OP_Raw!A:A)-1) -> 0.0034482759 | J2: Major | K2: Map 'attended' → ATT; exclude 'N/A' (APT-100199 also has CL-DEP, GEN, blank consultant — likely a legacy/test record). Add PAS drop-down validation. | L2: APT-100154 ('attended'); APT-100199 ('N/A') | M2: DNA rate | N2: A COUNTIF on 'ATT' misses 'attended'; 'N/A' inflates any COUNTA denominator. Small here (0.03 pts) but the same pattern at scale drives the DNA dispute. | O2: Free-text entry allowed in PAS status field | P2: PAS team / Sarah Okafor | Q2: Fixed in analysis
A3: OP-02 | B3: T6 | C3: Outpatients | D3: PAS | E3: Waiting_Days | F3: Format error | G3: Text value 'ATT' in a numeric field (column-shift / entry error). | H3: =SUMPRODUCT(--ISTEXT(OP_Raw!K2:K581)) -> 28 | I3: =H3/(COUNTA(OP_Raw!A:A)-1) -> 0.048275862 | J3: Major | K3: Recover from RTT_Weeks × 7 (RTT_Weeks is populated and consistent for every other row). | L3: APT-100362, APT-100369, APT-100375 | M3: RTT, waiting times | N3: Rows drop out of any AVERAGE/SUM of waiting time; Excel may error or silently ignore them. | O3: Status value written into the wrong field on export | P3: Daniel Walsh (pipeline) | Q3: Fixed in analysis
A4: OP-03 | B4: T6 | C4: Outpatients | D4: PAS | E4: Waiting_Days | F4: Impossible value | G4: Negative waiting time. | H4: =COUNTIF(OP_Raw!K2:K581,"<0") -> 1 | I4: =H4/(COUNTA(OP_Raw!A:A)-1) -> 0.0017241379 | J4: Major | K4: Exclude from RTT calculations; validate referral date with PAS team. | L4: APT-100200 (−3 days) | M4: RTT | N4: Impossible value — appointment before referral. Handover notes said 4 rows; this extract has 1. | O4: Referral date entered after appointment date, or transferred-in patient clock | P4: Sarah Okafor | Q4: Open — validate
A5: OP-04 | B5: T2 | C5: Outpatients | D5: PAS | E5: NHS_Number | F5: Blank | G5: NHS Number blank. | H5: =COUNTBLANK(OP_Raw!B2:B581) -> 3 | I5: =H5/(COUNTA(OP_Raw!A:A)-1) -> 0.0051724138 | J5: Major | K5: Trace via PDS (Spine) and back-fill. | L5: 3 rows | M5: Patient matching, RTT | N5: Cannot link to admissions / readmissions; possible duplicate patients on the waiting list. | O5: Not captured at registration | P5: PAS team | Q5: Open
A6: OP-05 | B6: T2 | C6: Outpatients | D6: PAS | E6: NHS_Number | F6: Format error | G6: NHS Numbers starting with 0 — will be truncated to 9 digits if the CSV is opened directly in Excel or cast as INT. | H6: =SUMPRODUCT(--(LEFT(OP_Raw!B2:B581,1)="0")) -> 26 | I6: =H6/(COUNTA(OP_Raw!A:A)-1) -> 0.044827586 | J6: Major | K6: Import NHS_Number as TEXT (Power Query: set type to Text); fix the export query to VARCHAR(10). | L6: APT-100362 (0721302594) | M6: All patient-level KPIs | N6: Root cause of the known 'NHS Number truncation' issue: numeric casting drops the leading zero. | O6: Export casts NHS_Number as INT; Excel auto-converts to number | P6: Daniel Walsh | Q6: Fixed in analysis
A7: OP-06 | B7: T7 | C7: Outpatients | D7: PAS | E7: Specialty_Code | F7: Non-standard value | G7: Retired code GEN (replaced by GM in June 2023). | H7: =COUNTIF(OP_Raw!E2:E581,"GEN") -> 3 | I7: =H7/(COUNTA(OP_Raw!A:A)-1) -> 0.0051724138 | J7: Major | K7: Map GEN → GM using Specialty_Code_Mapping.csv. | L7: 3 rows | M7: Specialty activity, RTT by specialty | N7: General Medicine activity split across two codes and under-reported. | O7: Specialty code migration not completed | P7: Daniel Walsh | Q7: Fixed in analysis
A8: OP-07 | B8: — | C8: Outpatients | D8: PAS | E8: Clinic_Code | F8: Non-standard value | G8: Retired / decommissioned clinic codes CL-OLD and CL-DEP. | H8: =COUNTIF(OP_Raw!G2:G581,"CL-OLD")+COUNTIF(OP_Raw!G2:G581,"CL-DEP") -> 2 | I8: =H8/(COUNTA(OP_Raw!A:A)-1) -> 0.0034482759 | J8: Minor | K8: Exclude from clinic reporting; confirm origin (pre-merger / closed dermatology) with PAS team. | L8: APT-100186 (CL-OLD); APT-100199 (CL-DEP) | M8: Clinic activity, DNA | N8: Activity booked to clinics that no longer exist. | O8: Legacy codes still selectable in PAS | P8: PAS team | Q8: Open — confirm
A9: OP-08 | B9: — | C9: Outpatients | D9: PAS | E9: Consultant_Code | F9: Blank | G9: Consultant code blank. | H9: =COUNTBLANK(OP_Raw!F2:F581) -> 5 | I9: =H9/(COUNTA(OP_Raw!A:A)-1) -> 0.0086206897 | J9: Minor | K9: Report as 'Unknown'; register locums. | L9: APT-100156, APT-100169, APT-100191, APT-100199, APT-100201 | M9: Consultant-level reporting | N9: Cannot attribute activity; possible unregistered locums. | O9: Locum consultants not registered in PAS | P9: Medical Staffing | Q9: Open
A10: OP-09 | B10: T6 | C10: Outpatients | D10: PAS | E10: RTT_Status / RTT_Weeks | F10: Blank | G10: RTT status blank. | H10: =COUNTBLANK(OP_Raw!L2:L581) -> 1 | I10: =H10/(COUNTA(OP_Raw!A:A)-1) -> 0.0017241379 | J10: Major | K10: Validate pathway status. | L10: 1 row | M10: RTT compliance | N10: Pathway cannot be counted as open or closed. | O10: Pathway not validated | P10: Sarah Okafor | Q10: Open
A11: OP-10 | B11: — | C11: Outpatients | D11: PAS | E11: Referral_Source | F11: Non-standard value | G11: Non-standard value 'Other'. | H11: =COUNTIF(OP_Raw!N2:N581,"Other") -> 1 | I11: =H11/(COUNTA(OP_Raw!A:A)-1) -> 0.0017241379 | J11: Minor | K11: Map to reference list. | L11: 1 row | M11: Referral analysis | N11: Minor — not in reference list. | O11: Free text | P11: PAS team | Q11: Open
A12: OP-11 | B12: — | C12: Outpatients | D12: PAS | E12: Postcode | F12: Blank | G12: Postcode blank. | H12: =COUNTBLANK(OP_Raw!O2:O581) -> 2 | I12: =H12/(COUNTA(OP_Raw!A:A)-1) -> 0.0034482759 | J12: Minor | K12: Back-fill from PDS. | L12: 2 rows | M12: Population / health-inequality analysis | N12: Minor. | O12: Not captured | P12: PAS team | Q12: Open
A13: OP-12 | B13: T1 | C13: Outpatients | D13: PAS | E13: Attendance_Status (by month) | F13: Impossible value (implausible pattern) | G13: DNA rate swings from 25.8% (Jan) to 10.9% (Feb) to 3.7% (Mar) — DNA outcomes appear to be recorded late or bulk-updated. | H13: =COUNTIFS(OP_Raw!J2:J581,"DNA",OP_Raw!H2:H581,">="&DATE(2025,1,1),OP_Raw!H2:H581,"<"&DATE(2025,2,1)) -> 49 | I13: =H13/(COUNTA(OP_Raw!A:A)-1) -> 0.084482759 | J13: Major | K13: Report DNA quarterly; set a 48-hour outcome-recording standard for clinics; re-run once March outcomes are complete. | L13: 49 of 76 DNAs fall in January | M13: DNA rate | N13: A calendar-month DNA rate (PAS report method) is unreliable; a quarterly figure is more stable. Explains part of the 3-figure dispute. | O13: Outcome recording lag in clinics | P13: Outpatient Manager / Sarah Okafor | Q13: Open — investigate
A14: OP-13 | B14: T4 | C14: Outpatients | D14: PAS | E14: Appointment_Time | F14: Format error | G14: Placeholder 'TBC' instead of a time. | H14: =COUNTIF(OP_Raw!I2:I581,"TBC") -> 1 | I14: =H14/(COUNTA(OP_Raw!A:A)-1) -> 0.0017241379 | J14: Minor | K14: Confirm slot or exclude. | L14: 1 row | M14: Clinic utilisation | N14: Time arithmetic fails for this row. | O14: Booking without a confirmed slot | P14: PAS team | Q14: Open
A15: OP-14 | B15: T5 | C15: Outpatients | D15: PAS | E15: Appointment_ID | F15: Duplicate | G15: Duplicate check: no exact duplicate IDs and no near-duplicates (tested NHS Number + date; + clinic; + time; Surname + DOB + date). All IDs are valid APT-XXXXXX (no 5-digit truncation). | H15: =ROWS(OP_Raw!A2:A581)-SUMPRODUCT(1/COUNTIF(OP_Raw!A2:A581,OP_Raw!A2:A581)) -> 0 | I15: =H15/(COUNTA(OP_Raw!A:A)-1) -> 0 | J15: None found | K15: No action; keep the check in the weekly pipeline. | L15: None | M15: Activity counts, DNA | N15: None — appointment counts are not inflated by duplicates. | O15: n/a | P15: Analyst | Q15: Closed — none found
A16: IP-01 | B16: — | C16: Inpatients | D16: EHR | E16: Episode_ID | F16: Duplicate | G16: Duplicate Episode_IDs (6 IDs appear twice; 2 exact copies, 4 differ only by Ward_Code). | H16: =ROWS(IP_Raw!A2:A1207)-SUMPRODUCT(1/COUNTIF(IP_Raw!A2:A1207,IP_Raw!A2:A1207)) -> 6 | I16: =H16/(COUNTA(IP_Raw!A:A)-1) -> 0.0049751244 | J16: Major | K16: Keep one row per Episode_ID (first ward); record transfers separately. | L16: EP-10000057, EP-10000091, EP-10000198, EP-10000254, EP-10000264, EP-10000553 | M16: Activity, ALOS, HRG income, bed days | N16: Activity and income double-counted; ward transfers recorded as new episodes. | O16: Ward transfer creates a second record in the EHR export | P16: Daniel Walsh | Q16: Fixed in analysis
A17: IP-02 | B17: T3 | C17: Inpatients | D17: EHR | E17: HRG_Code | F17: Blank | G17: HRG code blank — episode cannot be grouped or paid. | H17: =COUNTBLANK(IP_Raw!M2:M1207) -> 28 | I17: =H17/(COUNTA(IP_Raw!A:A)-1) -> 0.023217247 | J17: Critical | K17: Send Episode_ID list to Clinical Coding before SUS deadline. | L17: 28 episodes (all discharged) | M17: HRG coding completeness, income | N17: £51,800 income at risk (28 × £1,850). NB: across 6 months, not per month as the company brief assumed. | O17: Clinical coding backlog | P17: Marcus Reid (Clinical Coding) | Q17: Open
A18: IP-03 | B18: — | C18: Inpatients | D18: EHR | E18: Readmission_Flag | F18: Blank | G18: Readmission flag blank (handover notes said 41; extract has 44). | H18: =COUNTBLANK(IP_Raw!L2:L1207) -> 44 | I18: =H18/(COUNTA(IP_Raw!A:A)-1) -> 0.036484245 | J18: Major | K18: Back-fill using admission-date logic (NHS Number + admission within 30 days of a previous discharge). | L18: 44 rows | M18: 30-day readmission rate | N18: Rate ranges 9.0% (blanks excluded) to 12.3% (blanks = Y) — straddles the 10% target. | O18: EHR not populating flag; ownership disputed | P18: Analyst (per Nov governance decision) | Q18: Open
A19: IP-04 | B19: T4 | C19: Inpatients | D19: EHR | E19: Discharge_Date / Method / LOS | F19: Blank | G19: Open episodes — no discharge date, method, LOS or bed days. Some admitted in October 2024. | H19: =COUNTBLANK(IP_Raw!I2:I1207) -> 31 | I19: =H19/(COUNTA(IP_Raw!A:A)-1) -> 0.025704809 | J19: Major | K19: Validate each open episode >30 days with ward clerks. | L19: 31 rows (admitted 01/10/2024–08/03/2025) | M19: ALOS, bed occupancy | N19: Excluded from ALOS; very old open episodes are almost certainly missing discharges, which understates bed availability. | O19: Discharge not recorded in EHR | P19: Ward administration | Q19: Open
A20: IP-05 | B20: T4 | C20: Inpatients | D20: EHR | E20: Discharge_Date | F20: Format error | G20: Dates stored as text ('October 9 2024'). | H20: =SUMPRODUCT(--ISTEXT(IP_Raw!I2:I1207)) -> 3 | I20: =H20/(COUNTA(IP_Raw!A:A)-1) -> 0.0024875622 | J20: Major | K20: Convert with Power Query (Date.FromText, locale en-GB). | L20: October 9 2024; November 20 2024; December 19 2024 | M20: ALOS, readmissions | N20: Date arithmetic fails; rows silently drop out. | O20: Manual entry / different source format | P20: Daniel Walsh | Q20: Fixed in analysis
A21: IP-06 | B21: — | C21: Inpatients | D21: EHR | E21: Admission_Type | F21: Non-standard value | G21: Non-standard values 'Elective' (9) and 'emergency' (4). Valid: ELEC, EMER, TRANSFER. | H21: =COUNTIF(IP_Raw!F2:F1207,"Elective")+COUNTIF(IP_Raw!F2:F1207,"emergency") -> 13 | I21: =H21/(COUNTA(IP_Raw!A:A)-1) -> 0.010779436 | J21: Major | K21: Map Elective → ELEC; emergency → EMER. | L21: 13 rows | M21: Elective activity, readmissions, cancelled ops | N21: Elective/emergency counts understated when filtering on code. | O21: Free text entry | P21: Daniel Walsh | Q21: Fixed in analysis
A22: IP-07 | B22: — | C22: Inpatients | D22: EHR | E22: Discharge_Method | F22: Non-standard value | G22: Non-standard value 'Discharged'. | H22: =COUNTIF(IP_Raw!J2:J1207,"Discharged") -> 15 | I22: =H22/(COUNTA(IP_Raw!A:A)-1) -> 0.012437811 | J22: Minor | K22: Map to HOME after validation. | L22: 15 rows | M22: Discharge destination | N22: Cannot tell home vs transfer. | O22: Free text | P22: Ward administration | Q22: Open
A23: IP-08 | B23: — | C23: Inpatients | D23: EHR | E23: Ward_Code | F23: Non-standard value | G23: Decommissioned ward W-08 (closed Feb 2024). | H23: =COUNTIF(IP_Raw!G2:G1207,"W-08") -> 3 | I23: =H23/(COUNTA(IP_Raw!A:A)-1) -> 0.0024875622 | J23: Major | K23: Reassign to correct ward; disable code. | L23: 3 rows | M23: Bed occupancy | N23: Activity on a ward with no beds inflates occupancy. | O23: Legacy code still selectable | P23: Daniel Walsh | Q23: Open
A24: IP-09 | B24: T7 | C24: Inpatients | D24: EHR | E24: Specialty_Code | F24: Non-standard value | G24: Retired code GEN. | H24: =COUNTIF(IP_Raw!H2:H1207,"GEN") -> 10 | I24: =H24/(COUNTA(IP_Raw!A:A)-1) -> 0.008291874 | J24: Major | K24: Map GEN → GM. | L24: 10 rows | M24: Specialty activity | N24: General Medicine under-reported. | O24: Specialty code migration | P24: Daniel Walsh | Q24: Fixed in analysis
A25: IP-10 | B25: — | C25: Inpatients | D25: EHR | E25: Length_of_Stay | F25: Impossible value | G25: Negative length of stay (dates show positive stays). | H25: =COUNTIF(IP_Raw!K2:K1207,"<0") -> 6 | I25: =H25/(COUNTA(IP_Raw!A:A)-1) -> 0.0049751244 | J25: Major | K25: Recalculate LOS = Discharge_Date − Admission_Date. | L25: EP-10000154 (−3 vs 6 days) | M25: ALOS | N25: Pulls ALOS down. | O25: Calculated field error | P25: Daniel Walsh | Q25: Fixed in analysis
A26: IP-11 | B26: — | C26: Inpatients | D26: EHR | E26: Bed_Days | F26: Impossible value | G26: Bed_Days differs from Length_of_Stay. | H26: =SUMPRODUCT(--(IP_Raw!K2:K1207<>""),--(IP_Raw!K2:K1207<>IP_Raw!N2:N1207)) -> 34 | I26: =H26/(COUNTA(IP_Raw!A:A)-1) -> 0.028192371 | J26: Minor | K26: Agree one definition (midnight census). | L26: 34 rows | M26: Bed occupancy, cost per episode | N26: Two 'stay' measures disagree; definition undocumented. | O26: Different counting rules (midnights vs days) | P26: Daniel Walsh | Q26: Open — define
A27: IP-12 | B27: T2 | C27: Inpatients | D27: EHR | E27: NHS_Number | F27: Blank | G27: NHS Number blank. | H27: =COUNTBLANK(IP_Raw!B2:B1207) -> 20 | I27: =H27/(COUNTA(IP_Raw!A:A)-1) -> 0.016583748 | J27: Major | K27: Trace via PDS. | L27: 20 rows | M27: Readmissions, linkage | N27: Readmissions cannot be detected for these patients. | O27: Not captured / unidentified patients | P27: Ward administration | Q27: Open
A28: IP-13 | B28: T2 | C28: Inpatients | D28: EHR | E28: NHS_Number | F28: Format error | G28: NHS Numbers starting with 0 — truncation risk on import. | H28: =SUMPRODUCT(--(LEFT(IP_Raw!B2:B1207,1)="0")) -> 95 | I28: =H28/(COUNTA(IP_Raw!A:A)-1) -> 0.078772803 | J28: Major | K28: Import as Text. | L28: EP rows with 0-leading NHS Number | M28: Readmissions, linkage | N28: Truncated numbers break patient matching. | O28: INT casting | P28: Daniel Walsh | Q28: Fixed in analysis
A29: IP-14 | B29: T3 | C29: Inpatients | D29: EHR | E29: Consultant / ICD10 / OPCS4 | F29: Blank | G29: Consultant (28), ICD-10 (27) and OPCS-4 (27) blank. | H29: =COUNTBLANK(IP_Raw!P2:P1207) -> 27 | I29: =H29/(COUNTA(IP_Raw!A:A)-1) -> 0.02238806 | J29: Critical | K29: Include in Clinical Coding work list. | L29: 25 episodes have an HRG but no ICD-10 code | M29: HRG income, SUS | N29: Episodes with missing diagnosis/procedure codes may group incorrectly. | O29: Coding incomplete | P29: Marcus Reid | Q29: Open
A30: ED-01 | B30: — | C30: ED | D30: EDIS | E30: Attendance_ID | F30: Duplicate | G30: Duplicate attendance IDs (9 duplicated records). | H30: =ROWS(ED_Raw!A2:A970)-SUMPRODUCT(1/COUNTIF(ED_Raw!A2:A970,ED_Raw!A2:A970)) -> 9 | I30: =H30/(COUNTA(ED_Raw!A:A)-1) -> 0.0092879257 | J30: Critical | K30: De-duplicate on Attendance_ID. | L30: ED-7000110, ED-7000114, ED-7000213 … | M30: ED 4-hour, attendances | N30: Attendances double-counted. | O30: Export duplication | P30: Daniel Walsh | Q30: Fixed in analysis
A31: ED-02 | B31: T4 | C31: ED | D31: EDIS | E31: Departure_Time | F31: Blank | G31: Departure time missing — so Total_ED_Time and Four_Hour_Breach are also blank. | H31: =COUNTBLANK(ED_Raw!I2:I970) -> 35 | I31: =H31/(COUNTA(ED_Raw!A:A)-1) -> 0.036119711 | J31: Critical | K31: Report validated figure with blanks excluded and show the range; chase departures with ED. | L31: 35 rows | M31: ED 4-hour | N31: The root cause of the three ED figures: 79.9% (blanks = breach), 83.2% (blanks excluded), 83.9% (blanks = pass). | O31: Departure not recorded (incl. EDIS downtime) | P31: ED Manager | Q31: Open
A32: ED-03 | B32: — | C32: ED | D32: EDIS | E32: Four_Hour_Breach | F32: Blank | G32: Breach flag blank (35 missing departures + 4 negative times). | H32: =COUNTBLANK(ED_Raw!K2:K970) -> 39 | I32: =H32/(COUNTA(ED_Raw!A:A)-1) -> 0.040247678 | J32: Critical | K32: Recalculate breach from times (helper column Q). | L32: 39 rows | M32: ED 4-hour | N32: As above. | O32: Flag derived from a missing/invalid time | P32: Analyst | Q32: Fixed in analysis
A33: ED-04 | B33: — | C33: ED | D33: EDIS | E33: Total_ED_Time_Minutes | F33: Impossible value | G33: Negative ED time — midnight / calculation error. | H33: =COUNTIF(ED_Raw!L2:L970,"<0") -> 4 | I33: =H33/(COUNTA(ED_Raw!A:A)-1) -> 0.004127967 | J33: Major | K33: Recalculate from Arrival/Departure times. | L33: ED-7000256 (−57; times give 166 min) | M33: ED 4-hour | N33: 4 attendances missing from the breach count; recalculation shows 1 is a breach (369 min). | O33: Derived field error | P33: Daniel Walsh | Q33: Fixed in analysis
A34: ED-05 | B34: T4 | C34: ED | D34: EDIS | E34: Arrival_Time | F34: Format error | G34: 12-hour AM/PM format ('3:53 PM') instead of 24-hour HH:MM. | H34: =SUMPRODUCT(--ISNUMBER(SEARCH("M",ED_Raw!F2:F970))) -> 17 | I34: =H34/(COUNTA(ED_Raw!A:A)-1) -> 0.01754386 | J34: Major | K34: Convert with TIMEVALUE / Power Query. | L34: 17 rows | M34: ED 4-hour | N34: Time arithmetic fails unless converted. | O34: Manual entry (EDIS downtime pattern) | P34: Daniel Walsh | Q34: Fixed in analysis
A35: ED-06 | B35: — | C35: ED | D35: EDIS | E35: Triage_Category | F35: Impossible value | G35: Invalid triage values 0 and 6 (valid 1–5). | H35: =COUNTIF(ED_Raw!G2:G970,0)+COUNTIF(ED_Raw!G2:G970,6) -> 9 | I35: =H35/(COUNTA(ED_Raw!A:A)-1) -> 0.0092879257 | J35: Major | K35: Review with ED; add 1–5 validation. | L35: ED-7000206, ED-7000228, ED-7000358 … | M35: Acuity / casemix | N35: Clinical prioritisation unknown for these patients. | O35: No validation in EDIS | P35: ED Manager | Q35: Open
A36: ED-07 | B36: — | C36: ED | D36: EDIS | E36: Seen_by_Clinician_Time | F36: Blank | G36: Time seen by clinician blank. | H36: =COUNTBLANK(ED_Raw!H2:H970) -> 28 | I36: =H36/(COUNTA(ED_Raw!A:A)-1) -> 0.028895769 | J36: Minor | K36: Chase with ED. | L36: 28 rows | M36: Time to clinician, LWBS | N36: Cannot measure wait to be seen. | O36: Not recorded | P36: ED Manager | Q36: Open
A37: ED-08 | B37: T2 | C37: ED | D37: EDIS | E37: NHS_Number | F37: Blank | G37: NHS Number blank (12.5% of attendances). | H37: =COUNTBLANK(ED_Raw!B2:B970) -> 121 | I37: =H37/(COUNTA(ED_Raw!A:A)-1) -> 0.124871 | J37: Major | K37: Back-fill post-attendance via PDS. | L37: 121 rows | M37: Linkage to admissions / readmissions | N37: Cannot link ED attendances to inpatient episodes. | O37: Unidentified patients at arrival | P37: ED reception | Q37: Open
A38: ED-09 | B38: — | C38: ED | D38: EDIS | E38: Departure_Code | F38: Non-standard value | G38: Code 'LEFT' (120 rows) not in the glossary — ambiguous vs LWBS (23). | H38: =COUNTIF(ED_Raw!J2:J970,"LEFT") -> 120 | I38: =H38/(COUNTA(ED_Raw!A:A)-1) -> 0.12383901 | J38: Major | K38: Define LEFT with ED (left before or after being seen?) and map. | L38: 120 rows | M38: LWBS rate | N38: LWBS is 2.4% (LWBS only) or 14.7% (LWBS + LEFT) — the difference between meeting and badly breaching the 5% standard. | O38: Code list not controlled | P38: ED Manager / Daniel Walsh | Q38: Open — define
A39: ED-10 | B39: — | C39: ED | D39: EDIS | E39: Departure_Code | F39: Impossible value | G39: 'DIED' recorded for 14.6% of attendances — clinically implausible for an ED. | H39: =COUNTIF(ED_Raw!J2:J970,"DIED") -> 141 | I39: =H39/(COUNTA(ED_Raw!A:A)-1) -> 0.14551084 | J39: Critical | K39: Urgent validation with ED and Medical Director before any mortality reporting. | L39: 141 rows | M39: Mortality, quality reporting | N39: Must not be quoted; likely miscoding. | O39: Wrong code mapping in EDIS export | P39: Medical Director / Daniel Walsh | Q39: Open — urgent
A40: ED-11 | B40: — | C40: ED | D40: EDIS | E40: Chief_Complaint | F40: Non-standard value | G40: Inconsistent case ('STROKE', 'Chest Pain', 'laceration') — 48 variants of 21 complaints. | H40: =SUMPRODUCT(--NOT(EXACT(ED_Raw!M2:M970,UPPER(ED_Raw!M2:M970)))) -> 698 | I40: =H40/(COUNTA(ED_Raw!A:A)-1) -> 0.72033024 | J40: Minor | K40: Standardise with UPPER/TRIM in Power Query. | L40: 'abdominal pain' vs 'ABDOMINAL PAIN' | M40: Casemix analysis | N40: Grouping splits the same complaint. | O40: Free text | P40: Analyst | Q40: Fixed in analysis
A41: ED-12 | B41: — | C41: ED | D41: EDIS | E41: Specialty_Referred | F41: Non-standard value | G41: 'N/A' used alongside 'NONE'. | H41: =COUNTIF(ED_Raw!N2:N970,"N/A") -> 13 | I41: =H41/(COUNTA(ED_Raw!A:A)-1) -> 0.013415893 | J41: Minor | K41: Map N/A → NONE. | L41: 13 rows | M41: Referral analysis | N41: Minor. | O41: Free text | P41: Analyst | Q41: Fixed in analysis
A42: TH-01 | B42: — | C42: Theatres | D42: TMS | E42: Sessions_Used | F42: Impossible value | G42: Sessions used exceed sessions available (impossible). | H42: =SUMPRODUCT(--(TH_Raw!D2:D209>TH_Raw!C2:C209)) -> 4 | I42: =H42/(COUNTA(TH_Raw!A:A)-1) -> 0.019230769 | J42: Major | K42: Cap at Sessions_Available for reporting; fix TMS update at source. | L42: T2 09/06/2024 (11 of 10); T3 10/11/2024 (10 of 8) | M42: Theatre utilisation | N42: Utilisation over 100%; the existing 'fudge' rule hides it. | O42: TMS not updating cancelled sessions (pipeline issue 5) | P42: Daniel Walsh / Theatres | Q42: Open
A43: TH-02 | B43: — | C43: Theatres | D43: TMS | E43: Utilisation_Pct | F43: Impossible value | G43: Pre-calculated % does not equal Sessions_Used ÷ Sessions_Available. | H43: =SUMPRODUCT(--(ABS(ROUND(TH_Raw!D2:D209/(TH_Raw!C2:C209+(TH_Raw!C2:C209=0))*100,1)-TH_Raw!E2:E209)>0.1)) -> 7 | I43: =H43/(COUNTA(TH_Raw!A:A)-1) -> 0.033653846 | J43: Major | K43: Never use Utilisation_Pct; calculate from sessions. | L43: T2 23/06/2024 shows 41.5% (should be 50.0%) | M43: Theatre utilisation | N43: Averages of this column are wrong; always recalculate. | O43: Manual overwrite of a calculated field | P43: Analyst | Q43: Fixed in analysis
A44: TH-03 | B44: — | C44: Theatres | D44: TMS | E44: Theatre_ID | F44: Non-standard value | G44: 'Theatre One' — non-standard ID. 8 sessions = T3's pattern, and T3 is missing that week. | H44: =COUNTIF(TH_Raw!B2:B209,"Theatre One") -> 1 | I44: =H44/(COUNTA(TH_Raw!A:A)-1) -> 0.0048076923 | J44: Minor | K44: Map to T3 (confirm with Theatres). | L44: 12/05/2024 | M44: Theatre utilisation by theatre | N44: T3 under-counted, phantom theatre created. | O44: Free text | P44: Theatres Manager | Q44: Fixed in analysis
A45: TH-04 | B45: — | C45: Theatres | D45: TMS | E45: Sessions_Available | F45: Impossible value | G45: Zero sessions available (T2 30/06/2024). | H45: =COUNTIF(TH_Raw!C2:C209,0) -> 1 | I45: =H45/(COUNTA(TH_Raw!A:A)-1) -> 0.0048076923 | J45: Minor | K45: Exclude from denominators; confirm closure. | L45: T2 30/06/2024 | M45: Theatre utilisation | N45: Division by zero; likely planned closure. | O45: Theatre closed | P45: Theatres Manager | Q45: Fixed in analysis
A46: TH-05 | B46: T4 | C46: Theatres | D46: TMS | E46: Week_Ending | F46: Format error | G46: Week ending not a Sunday. | H46: =SUMPRODUCT(--(WEEKDAY(TH_Raw!A2:A209,2)<>7)) -> 2 | I46: =H46/(COUNTA(TH_Raw!A:A)-1) -> 0.0096153846 | J46: Minor | K46: Correct to 16/06/2024 and 30/03/2025. | L46: 17/06/2024 (T1); 31/03/2025 (T4) | M46: Weekly trend | N46: Rows fall into the wrong week. | O46: Entry error | P46: Analyst | Q46: Fixed in analysis
A47: TH-06 | B47: — | C47: Theatres | D47: TMS | E47: Cancellations_Trust | F47: Blank | G47: Trust cancellations blank. | H47: =COUNTBLANK(TH_Raw!H2:H209) -> 30 | I47: =H47/(COUNTA(TH_Raw!A:A)-1) -> 0.14423077 | J47: Critical | K47: Report blanks separately; chase with Theatres. | L47: 30 rows | M47: Cancelled operations rate | N47: Cancellation rate understated if blanks treated as zero. | O47: Not recorded | P47: Theatres Manager | Q47: Open
A48: TH-07 | B48: — | C48: Theatres | D48: TMS | E48: Cancellations_Patient | F48: Blank | G48: Patient cancellations blank. | H48: =COUNTBLANK(TH_Raw!I2:I209) -> 23 | I48: =H48/(COUNTA(TH_Raw!A:A)-1) -> 0.11057692 | J48: Minor | K48: As above. | L48: 23 rows | M48: Cancelled operations rate | N48: As above. | O48: Not recorded | P48: Theatres Manager | Q48: Open
A49: TH-08 | B49: — | C49: Theatres | D49: TMS | E49: Overrun_Minutes | F49: Impossible value | G49: Negative overrun minutes — undefined (early finish?). | H49: =COUNTIF(TH_Raw!J2:J209,"<0") -> 14 | I49: =H49/(COUNTA(TH_Raw!A:A)-1) -> 0.067307692 | J49: Minor | K49: Define field (early finish = negative). | L49: 14 rows | M49: Time-based utilisation | N49: Hours-based figures shift depending on interpretation. | O49: Definition not documented | P49: Theatres Manager | Q49: Open — define
A50: TH-09 | B50: — | C50: Theatres | D50: TMS | E50: Cases_Completed | F50: Impossible value | G50: More cases completed than planned. | H50: =SUMPRODUCT(--(TH_Raw!G2:G209>TH_Raw!F2:F209)) -> 15 | I50: =H50/(COUNTA(TH_Raw!A:A)-1) -> 0.072115385 | J50: Minor | K50: Record add-ons separately. | L50: 15 rows | M50: Cases-based utilisation | N50: Add-on cases not planned; the TMS cases method exceeds 100% in places. | O50: Add-on / emergency cases | P50: Theatres Manager | Q50: Open
A51: TH-10 | B51: T7 | C51: Theatres | D51: TMS | E51: Specialty_Code | F51: Non-standard value | G51: Retired code GEN. | H51: =COUNTIF(TH_Raw!K2:K209,"GEN") -> 2 | I51: =H51/(COUNTA(TH_Raw!A:A)-1) -> 0.0096153846 | J51: Minor | K51: Map GEN → GM. | L51: 2 rows | M51: Specialty utilisation | N51: Minor. | O51: Code migration | P51: Daniel Walsh | Q51: Fixed in analysis
A52: WF-01 | B52: T8 | C52: Workforce | D52: WRS | E52: Agency_Flag | F52: Blank | G52: Agency flag blank. | H52: =COUNTBLANK(WF_Raw!I2:I1561) -> 15 | I52: =H52/(COUNTA(WF_Raw!A:A)-1) -> 0.0096153846 | J52: Major | K52: Classify with ward managers; make flag mandatory. | L52: 15 rows (11 in Feb) | M52: Agency spend % | N52: Agency spend can only be given as a range (Task 8). | O52: Bank shifts booked outside agency module | P52: Adaeze Obi / Priya Chakrabarti | Q52: Open
A53: WF-02 | B53: — | C53: Workforce | D53: WRS | E53: Staff_ID | F53: Non-standard value | G53: Training-environment test records (ST-99xxx). | H53: =COUNTIF(WF_Raw!B2:B1561,"ST-99*") -> 24 | I53: =H53/(COUNTA(WF_Raw!A:A)-1) -> 0.015384615 | J53: Major | K53: Filter out; stop at source. | L53: 24 rows (4 flagged agency) | M53: All workforce KPIs | N53: Inflates shifts and agency counts. | O53: Test data leaking from WRS training environment | P53: Daniel Walsh | Q53: Fixed in analysis
A54: WF-03 | B54: — | C54: Workforce | D54: WRS | E54: Staff_ID | F54: Blank | G54: Staff ID blank. | H54: =COUNTBLANK(WF_Raw!B2:B1561) -> 18 | I54: =H54/(COUNTA(WF_Raw!A:A)-1) -> 0.011538462 | J54: Minor | K54: Validate with rostering. | L54: 18 rows | M54: Vacancy, sickness | N54: Shifts cannot be attributed to a person. | O54: Unfilled / placeholder shifts | P54: Adaeze Obi | Q54: Open
A55: WF-04 | B55: — | C55: Workforce | D55: WRS | E55: Staff_Grade | F55: Non-standard value | G55: Non-standard grade 'Doctor'. | H55: =COUNTIF(WF_Raw!C2:C1561,"Doctor") -> 9 | I55: =H55/(COUNTA(WF_Raw!A:A)-1) -> 0.0057692308 | J55: Minor | K55: Map via ESR. | L55: 9 rows | M55: Workforce by staff group | N55: Cannot split CONS/REG/SHO. | O55: Free text | P55: Adaeze Obi | Q55: Open
A56: WF-05 | B56: — | C56: Workforce | D56: WRS | E56: Shift_Type | F56: Non-standard value | G56: Abbreviated shift types D / N / L. | H56: =SUMPRODUCT(--(LEN(WF_Raw!F2:F1561)=1)) -> 5 | I56: =H56/(COUNTA(WF_Raw!A:A)-1) -> 0.0032051282 | J56: Minor | K56: Map D→DAY, N→NIGHT, L→LONG. | L56: 5 rows | M56: Shift analysis | N56: Minor. | O56: Free text | P56: Analyst | Q56: Fixed in analysis
A57: WF-06 | B57: — | C57: Workforce | D57: WRS | E57: Hours_Rostered | F57: Impossible value | G57: Zero rostered hours but hours worked recorded. | H57: =COUNTIF(WF_Raw!G2:G1561,0) -> 3 | I57: =H57/(COUNTA(WF_Raw!A:A)-1) -> 0.0019230769 | J57: Minor | K57: Validate with ward managers. | L57: 3 rows | M57: Overtime, cost | N57: Unrostered work — cost not planned. | O57: Ad hoc shifts not rostered | P57: Adaeze Obi | Q57: Open
A58: WF-07 | B58: — | C58: Workforce | D58: WRS | E58: Hours_Worked | F58: Impossible value (WTR breach) | G58: Shifts over 13 hours — breach of Working Time Regulations rest rules. | H58: =COUNTIF(WF_Raw!H2:H1561,">13") -> 8 | I58: =H58/(COUNTA(WF_Raw!A:A)-1) -> 0.0051282051 | J58: Major | K58: Report to Workforce and HR immediately. | L58: 8 shifts (max 15.2 h) | M58: Staff safety, compliance | N58: A real operational risk, not just a data error — escalate. | O58: Over-runs / double shifts | P58: Adaeze Obi / HR | Q58: Open — escalate
A59: WF-08 | B59: — | C59: Workforce | D59: WRS | E59: Ward_Code | F59: Non-standard value | G59: Decommissioned ward W-08. | H59: =COUNTIF(WF_Raw!D2:D1561,"W-08") -> 3 | I59: =H59/(COUNTA(WF_Raw!A:A)-1) -> 0.0019230769 | J59: Minor | K59: Reassign. | L59: 3 rows | M59: Ward staffing | N59: Shifts on a closed ward. | O59: Legacy code | P59: Adaeze Obi | Q59: Open
A60: WF-09 | B60: — | C60: Workforce | D60: WRS | E60: Absence_Flag | F60: Blank | G60: Absence flag blank. | H60: =COUNTBLANK(WF_Raw!J2:J1561) -> 9 | I60: =H60/(COUNTA(WF_Raw!A:A)-1) -> 0.0057692308 | J60: Minor | K60: Validate. | L60: 9 rows | M60: Sickness absence | N60: Minor understatement. | O60: Not recorded | P60: Adaeze Obi | Q60: Open
A61: WF-10 | B61: T7 | C61: Workforce | D61: WRS | E61: Specialty_Code | F61: Non-standard value | G61: Retired code GEN. | H61: =COUNTIF(WF_Raw!L2:L1561,"GEN") -> 9 | I61: =H61/(COUNTA(WF_Raw!A:A)-1) -> 0.0057692308 | J61: Minor | K61: Map GEN → GM. | L61: 9 rows | M61: Workforce by specialty | N61: Minor. | O61: Code migration | P61: Daniel Walsh | Q61: Fixed in analysis
A62: WF-11 | B62: — | C62: Workforce | D62: WRS | E62: Shift_Date | F62: Blank (missing period) | G62: Export covers 06/01/2025–02/03/2025 only — March is almost empty. | H62: =COUNTIF(WF_Raw!E2:E1561,">="&DATE(2025,3,1)) -> 33 | I62: =H62/(COUNTA(WF_Raw!A:A)-1) -> 0.021153846 | J62: Major | K62: Re-run export after quarter end. | L62: 33 shifts in March | M62: Quarterly workforce KPIs | N62: Q1 workforce figures are incomplete; use February as the latest full month. | O62: Export run on 3 March | P62: Daniel Walsh | Q62: Open
A63: XS-01 | B63: T2 | C63: Cross-sheet | D63: PAS/EHR | E63: NHS_Number (Outpatients vs Inpatients) | F63: Blank / cross-sheet mismatch | G63: Outpatient NHS Numbers not found in the inpatient file — zero of 384 unique outpatient patients match an inpatient record. | H63: =SUMPRODUCT(--(OP_Raw!B2:B581<>""),--(COUNTIF(IP_Raw!B2:B1207,OP_Raw!B2:B581)=0)) -> 577 | I63: =H63/(COUNTA(OP_Raw!A:A)-1) -> 0.99482759 | J63: Critical | K63: Confirm with Daniel Walsh whether the extracts cover the same patients; if so, investigate number format / PDS tracing. | L63: 577 of 577 non-blank rows | M63: Patient pathway linkage, RTT → admission, readmissions | N63: PAS and EHR cannot be joined on NHS Number, so no cross-setting KPI (e.g. outpatient-to-admission conversion) can be calculated. | O63: Separate extracts / different patient cohorts, or NHS Number not consistently recorded across systems | P63: Daniel Walsh | Q63: Open — urgent
A64: XS-02 | B64: T2 | C64: Cross-sheet | D64: PAS/EHR | E64: NHS_Number (ED vs Inpatients) | F64: Blank / cross-sheet mismatch | G64: ED NHS Numbers not found in the inpatient file. | H64: =SUMPRODUCT(--(ED_Raw!B2:B970<>""),--(COUNTIF(IP_Raw!B2:B1207,ED_Raw!B2:B970)=0)) -> 848 | I64: =H64/(COUNTA(OP_Raw!A:A)-1) -> 1.462069 | J64: Major | K64: As above. | L64: All 848 non-blank rows | M64: ED conversion, readmissions | N64: 121 ADM departures cannot be matched to an admission episode. | O64: As above | P64: Daniel Walsh | Q64: Open

Sheet DQ_Scores
A1: Data Quality Scores by dataset
A2: DQ score = share of rows with no issue from the DQ_Issue_Log. Rows with ≥1 issue counted by the Python audit (each row counted once, even with several issues).
A4: Dataset | B4: Source | C4: Raw sheet | D4: Total rows | E4: Rows with ≥1 issue | F4: DQ score | G4: Issues logged | H4: Critical / Major issues | I4: RAG | J4: Headline problem
A5: Outpatients | B5: PAS | C5: OP_Raw | D5: =COUNTA(OP_Raw!A:A)-1 -> 580 | E5: 40 | F5: =1-E5/D5 -> 0.93103448 | G5: =COUNTIF(DQ_Issue_Log!$C$2:$C$64,A5) -> 14 | H5: =COUNTIFS(DQ_Issue_Log!$C$2:$C$64,A5,DQ_Issue_Log!$J$2:$J$64,"Critical")+COUNTIFS(DQ_Issue_Log!$C$2:$C$64,A5,DQ_Issue_Log!$J$2:$J$64,"Major") -> 8 | I5: =IF(F5>=0.95,"Green",IF(F5>=0.85,"Amber","Red")) -> Amber | J5: Small number of status/ID errors, but DNA outcomes recorded late (monthly DNA swings 25.8% → 3.7%).
A6: Inpatients | B6: EHR | C6: IP_Raw | D6: =COUNTA(IP_Raw!A:A)-1 -> 1206 | E6: 270 | F6: =1-E6/D6 -> 0.7761194 | G6: =COUNTIF(DQ_Issue_Log!$C$2:$C$64,A6) -> 14 | H6: =COUNTIFS(DQ_Issue_Log!$C$2:$C$64,A6,DQ_Issue_Log!$J$2:$J$64,"Critical")+COUNTIFS(DQ_Issue_Log!$C$2:$C$64,A6,DQ_Issue_Log!$J$2:$J$64,"Major") -> 12 | I6: =IF(F6>=0.95,"Green",IF(F6>=0.85,"Amber","Red")) -> Red | J6: 28 blank HRG codes (£51,800), 44 blank readmission flags, duplicates and 31 open episodes.
A7: ED | B7: EDIS | C7: ED_Raw | D7: =COUNTA(ED_Raw!A:A)-1 -> 969 | E7: 431 | F7: =1-E7/D7 -> 0.55521156 | G7: =COUNTIF(DQ_Issue_Log!$C$2:$C$64,A7) -> 12 | H7: =COUNTIFS(DQ_Issue_Log!$C$2:$C$64,A7,DQ_Issue_Log!$J$2:$J$64,"Critical")+COUNTIFS(DQ_Issue_Log!$C$2:$C$64,A7,DQ_Issue_Log!$J$2:$J$64,"Major") -> 9 | I7: =IF(F7>=0.95,"Green",IF(F7>=0.85,"Amber","Red")) -> Red | J7: 35 missing departures cause the 3 ED figures; 'DIED' and 'LEFT' codes are not credible.
A8: Theatres | B8: TMS | C8: TH_Raw | D8: =COUNTA(TH_Raw!A:A)-1 -> 208 | E8: 87 | F8: =1-E8/D8 -> 0.58173077 | G8: =COUNTIF(DQ_Issue_Log!$C$2:$C$64,A8) -> 10 | H8: =COUNTIFS(DQ_Issue_Log!$C$2:$C$64,A8,DQ_Issue_Log!$J$2:$J$64,"Critical")+COUNTIFS(DQ_Issue_Log!$C$2:$C$64,A8,DQ_Issue_Log!$J$2:$J$64,"Major") -> 3 | I8: =IF(F8>=0.95,"Green",IF(F8>=0.85,"Amber","Red")) -> Red | J8: 7 wrong Utilisation_Pct values, 4 rows over 100%, no agreed definition.
A9: Workforce | B9: WRS | C9: WF_Raw | D9: =COUNTA(WF_Raw!A:A)-1 -> 1560 | E9: 102 | F9: =1-E9/D9 -> 0.93461538 | G9: =COUNTIF(DQ_Issue_Log!$C$2:$C$64,A9) -> 11 | H9: =COUNTIFS(DQ_Issue_Log!$C$2:$C$64,A9,DQ_Issue_Log!$J$2:$J$64,"Critical")+COUNTIFS(DQ_Issue_Log!$C$2:$C$64,A9,DQ_Issue_Log!$J$2:$J$64,"Major") -> 4 | I9: =IF(F9>=0.95,"Green",IF(F9>=0.85,"Amber","Red")) -> Amber | J9: 15 blank agency flags, 24 test records, 8 shifts breaching 13 hours.
A10: Overall | D10: =SUM(D5:D9) -> 4523 | E10: =SUM(E5:E9) -> 930 | F10: =1-E10/D10 -> 0.79438426 | G10: =SUM(G5:G9) -> 61 | H10: =SUM(H5:H9) -> 36 | I10: =IF(F10>=0.95,"Green",IF(F10>=0.85,"Amber","Red")) -> Red
A12: RAG thresholds (Task 14 / IG standard): Green ≥95% · Amber 85–94% · Red <85% of rows valid. Cross-sheet linkage issues (XS) are not counted in any one dataset. Note: NHS Numbers in this test extract do not pass the Modulus 11 check digit, so that check is excluded here — apply it to live data.

Sheet Date_Format_Audit
A1: Task 4 — Date and time format audit (Sheets 1–3)
A2: Standard: dates dd/mm/yyyy (stored as real Excel dates); times HH:MM (24-hour). Dates that Excel could not read are stored as text, so ISTEXT finds them.
A4: Sheet | B4: Column | C4: Expected format | D4: Non-standard values | E4: Examples | F4: Issue type | G4: Severity | H4: Recommended action
A5: Outpatients | B5: Patient_DOB | C5: dd/mm/yyyy | D5: =SUMPRODUCT(--ISTEXT(OP_Raw!D2:D581)) -> 0 | E5: None | F5: — | G5: None found | H5: No action.
A6: Outpatients | B6: Appointment_Date | C6: dd/mm/yyyy | D6: =SUMPRODUCT(--ISTEXT(OP_Raw!H2:H581)) -> 0 | E6: None | F6: — | G6: None found | H6: No action.
A7: Outpatients | B7: Appointment_Time | C7: HH:MM | D7: =SUMPRODUCT(--(OP_Raw!I2:I581<>""),--((LEN(OP_Raw!I2:I581)<>5)+(MID(OP_Raw!I2:I581,3,1)<>":")>0)) -> 1 | E7: 'TBC' | F7: Format error | G7: Minor | H7: Confirm the slot or exclude from clinic-time analysis.
A8: Inpatients | B8: Patient_DOB | C8: dd/mm/yyyy | D8: =SUMPRODUCT(--ISTEXT(IP_Raw!D2:D1207)) -> 0 | E8: None | F8: — | G8: None found | H8: No action.
A9: Inpatients | B9: Admission_Date | C9: dd/mm/yyyy | D9: =SUMPRODUCT(--ISTEXT(IP_Raw!E2:E1207)) -> 0 | E9: None | F9: — | G9: None found | H9: No action.
A10: Inpatients | B10: Discharge_Date | C10: dd/mm/yyyy | D10: =SUMPRODUCT(--ISTEXT(IP_Raw!I2:I1207)) -> 3 | E10: 'October 9 2024', 'November 20 2024', 'December 19 2024' | F10: Format error | G10: Major | H10: Convert in Power Query (Date.FromText, en-GB); recalculate LOS; stop free-text entry.
A11: ED | B11: Patient_DOB | C11: dd/mm/yyyy | D11: =SUMPRODUCT(--ISTEXT(ED_Raw!D2:D970)) -> 0 | E11: None | F11: — | G11: None found | H11: No action.
A12: ED | B12: Arrival_Date | C12: dd/mm/yyyy | D12: =SUMPRODUCT(--ISTEXT(ED_Raw!E2:E970)) -> 0 | E12: None | F12: — | G12: None found | H12: No action.
A13: ED | B13: Arrival_Time | C13: HH:MM | D13: =SUMPRODUCT(--(ED_Raw!F2:F970<>""),--((LEN(ED_Raw!F2:F970)<>5)+(MID(ED_Raw!F2:F970,3,1)<>":")>0)) -> 17 | E13: '3:53 PM', '12:13 AM', '2:43 PM' | F13: Format error | G13: Major | H13: Convert 12-hour to 24-hour (TIMEVALUE / Power Query Time.FromText); then recalculate ED minutes and breach flag.
A14: ED | B14: Seen_by_Clinician_Time | C14: HH:MM | D14: =SUMPRODUCT(--(ED_Raw!H2:H970<>""),--((LEN(ED_Raw!H2:H970)<>5)+(MID(ED_Raw!H2:H970,3,1)<>":")>0)) -> 0 | E14: None | F14: — | G14: None found | H14: No action (28 blanks logged separately).
A15: ED | B15: Departure_Time | C15: HH:MM | D15: =SUMPRODUCT(--(ED_Raw!I2:I970<>""),--((LEN(ED_Raw!I2:I970)<>5)+(MID(ED_Raw!I2:I970,3,1)<>":")>0)) -> 0 | E15: None | F15: — | G15: None found | H15: No action (35 blanks logged separately).
A17: Also checked: no impossible dates (e.g. 31/02), no future dates beyond 31/03/2025, all DOBs between 1935 and 2007. Theatre Week_Ending has 2 non-Sunday dates (logged as TH issue).

Sheet GEN_Audit
A1: Task 7 — GEN → GM replacement audit trail
A2: Original columns are untouched; replacement is done in a Specialty_Code_Clean helper column on each raw sheet so every change is traceable.
A4: Sheet | B4: Column | C4: GEN before | D4: GM before | E4: GEN after | F4: GM after | G4: Check: GM after = GM before + GEN before | H4: Change date | I4: Changed by | J4: Authority
A5: Outpatients (OP_Raw) | B5: Specialty_Code | C5: =COUNTIF(OP_Raw!E2:E581,"GEN") -> 3 | D5: =COUNTIF(OP_Raw!E2:E581,"GM") -> 55 | E5: =COUNTIF(OP_Raw!R2:R581,"GEN") -> 0 | F5: =COUNTIF(OP_Raw!R2:R581,"GM") -> 58 | G5: =IF(AND(E5=0,F5=D5+C5),"PASS","FAIL") -> PASS | H5: Week 1 | I5: L. Ukeni | J5: Specialty_Code_Mapping.csv (Daniel Walsh)
A6: Inpatients (IP_Raw) | B6: Specialty_Code | C6: =COUNTIF(IP_Raw!H2:H1207,"GEN") -> 10 | D6: =COUNTIF(IP_Raw!H2:H1207,"GM") -> 98 | E6: =COUNTIF(IP_Raw!R2:R1207,"GEN") -> 0 | F6: =COUNTIF(IP_Raw!R2:R1207,"GM") -> 108 | G6: =IF(AND(E6=0,F6=D6+C6),"PASS","FAIL") -> PASS | H6: Week 1 | I6: L. Ukeni | J6: Specialty_Code_Mapping.csv (Daniel Walsh)
A7: ED (ED_Raw) | B7: Specialty_Referred | C7: =COUNTIF(ED_Raw!N2:N970,"GEN") -> 0 | D7: =COUNTIF(ED_Raw!N2:N970,"GM") -> 15 | E7: =C7 -> 0 | F7: =D7 -> 15 | G7: =IF(AND(E7=0,F7=D7+C7),"PASS","FAIL") -> PASS | H7: Week 1 | I7: L. Ukeni | J7: Specialty_Code_Mapping.csv (Daniel Walsh)
A8: Theatres (TH_Raw) | B8: Specialty_Code | C8: =COUNTIF(TH_Raw!K2:K209,"GEN") -> 2 | D8: =COUNTIF(TH_Raw!K2:K209,"GM") -> 0 | E8: =COUNTIF(TH_Raw!L2:L209,"GEN") -> 0 | F8: =COUNTIF(TH_Raw!L2:L209,"GM") -> 2 | G8: =IF(AND(E8=0,F8=D8+C8),"PASS","FAIL") -> PASS | H8: Week 1 | I8: L. Ukeni | J8: Specialty_Code_Mapping.csv (Daniel Walsh)
A9: Workforce (WF_Raw) | B9: Specialty_Code | C9: =COUNTIF(WF_Raw!L2:L1561,"GEN") -> 9 | D9: =COUNTIF(WF_Raw!L2:L1561,"GM") -> 281 | E9: =COUNTIF(WF_Raw!M2:M1561,"GEN") -> 0 | F9: =COUNTIF(WF_Raw!M2:M1561,"GM") -> 290 | G9: =IF(AND(E9=0,F9=D9+C9),"PASS","FAIL") -> PASS | H9: Week 1 | I9: L. Ukeni | J9: Specialty_Code_Mapping.csv (Daniel Walsh)
A10: Total | C10: =SUM(C5:C9) -> 24 | D10: =SUM(D5:D9) -> 449 | E10: =SUM(E5:E9) -> 0 | F10: =SUM(F5:F9) -> 473

Sheet Task_Workings
A1: Task workings — every figure is a live formula on the raw sheets
A3: TASK 1 — Attendance status check (Sarah Okafor)
A4: ATT (exact match) | B4: =SUMPRODUCT(--EXACT(OP_Raw!J2:J581,"ATT")) -> 463
A5: DNA (exact match) | B5: =SUMPRODUCT(--EXACT(OP_Raw!J2:J581,"DNA")) -> 76
A6: CAN (exact match) | B6: =SUMPRODUCT(--EXACT(OP_Raw!J2:J581,"CAN")) -> 33
A7: REF (exact match) | B7: =SUMPRODUCT(--EXACT(OP_Raw!J2:J581,"REF")) -> 6
A8: 'attended' — should be ATT | B8: =SUMPRODUCT(--EXACT(OP_Raw!J2:J581,"attended")) -> 1 | C8: APT-100154
A9: 'N/A' — exclude | B9: =SUMPRODUCT(--EXACT(OP_Raw!J2:J581,"N/A")) -> 1 | C9: APT-100199 — also CL-DEP clinic, GEN specialty, blank consultant: likely legacy/test record
A10: Total rows | B10: =COUNTA(OP_Raw!J2:J581) -> 580
A12: DNA rate reconciliation (for the Board conflict — Sarah vs Priya)
A13: Version A logic: COUNTIF(DNA) ÷ COUNTA(column incl. header) | B13: =B5/(COUNTA(OP_Raw!J2:J581)+1) -> 0.13080895 | C13: Header row and CAN rows in the denominator
A14: DNA ÷ all appointments (raw) | B14: =B5/COUNTA(OP_Raw!J2:J581) -> 0.13103448 | C14: Includes cancellations
A15: PAS-style: DNA ÷ (ATT + DNA) | B15: =B5/(B4+B5) -> 0.14100186 | C15: Reproduces the 14.1% PAS figure — but uncorrected statuses and excludes REF
A16: VALIDATED (recommended): DNA ÷ (ATT + 'attended' + DNA + REF) | B16: =B5/(B4+B8+B5+B7) -> 0.13919414 | C16: NHS England definition: denominator excludes cancellations; 'attended' corrected; 'N/A' excluded
A17: Trust target | B17: 0.08 | C17: Company brief
A18: DNA rate — January 2025 | B18: =COUNTIFS(OP_Raw!J2:J581,"DNA",OP_Raw!H2:H581,">="&DATE(2025,1,1),OP_Raw!H2:H581,"<"&DATE(2025,2,1))/(COUNTIFS(OP_Raw!J2:J581,"ATT",OP_Raw!H2:H581,">="&DATE(2025,1,1),OP_Raw!H2:H581,"<"&DATE(2025,2,1))+COUNTIFS(OP_Raw!J2:J581,"attended",OP_Raw!H2:H581,">="&DATE(2025,1,1),OP_Raw!H2:H581,"<"&DATE(2025,2,1))+COUNTIFS(OP_Raw!J2:J581,"DNA",OP_Raw!H2:H581,">="&DATE(2025,1,1),OP_Raw!H2:H581,"<"&DATE(2025,2,1))+COUNTIFS(OP_Raw!J2:J581,"REF",OP_Raw!H2:H581,">="&DATE(2025,1,1),OP_Raw!H2:H581,"<"&DATE(2025,2,1))) -> 0.25789474 | C18: Monthly swing 25.8% → 3.7% indicates late outcome recording — report quarterly
A19: DNA rate — February 2025 | B19: =COUNTIFS(OP_Raw!J2:J581,"DNA",OP_Raw!H2:H581,">="&DATE(2025,2,1),OP_Raw!H2:H581,"<"&DATE(2025,3,1))/(COUNTIFS(OP_Raw!J2:J581,"ATT",OP_Raw!H2:H581,">="&DATE(2025,2,1),OP_Raw!H2:H581,"<"&DATE(2025,3,1))+COUNTIFS(OP_Raw!J2:J581,"attended",OP_Raw!H2:H581,">="&DATE(2025,2,1),OP_Raw!H2:H581,"<"&DATE(2025,3,1))+COUNTIFS(OP_Raw!J2:J581,"DNA",OP_Raw!H2:H581,">="&DATE(2025,2,1),OP_Raw!H2:H581,"<"&DATE(2025,3,1))+COUNTIFS(OP_Raw!J2:J581,"REF",OP_Raw!H2:H581,">="&DATE(2025,2,1),OP_Raw!H2:H581,"<"&DATE(2025,3,1))) -> 0.10880829
A20: DNA rate — March 2025 | B20: =COUNTIFS(OP_Raw!J2:J581,"DNA",OP_Raw!H2:H581,">="&DATE(2025,3,1),OP_Raw!H2:H581,"<"&DATE(2025,4,1))/(COUNTIFS(OP_Raw!J2:J581,"ATT",OP_Raw!H2:H581,">="&DATE(2025,3,1),OP_Raw!H2:H581,"<"&DATE(2025,4,1))+COUNTIFS(OP_Raw!J2:J581,"attended",OP_Raw!H2:H581,">="&DATE(2025,3,1),OP_Raw!H2:H581,"<"&DATE(2025,4,1))+COUNTIFS(OP_Raw!J2:J581,"DNA",OP_Raw!H2:H581,">="&DATE(2025,3,1),OP_Raw!H2:H581,"<"&DATE(2025,4,1))+COUNTIFS(OP_Raw!J2:J581,"REF",OP_Raw!H2:H581,">="&DATE(2025,3,1),OP_Raw!H2:H581,"<"&DATE(2025,4,1))) -> 0.036809816
A22: TASK 3 — HRG blanks (Priya Chakrabarti)
A23: Blank HRG_Code (rows) | B23: =COUNTBLANK(IP_Raw!M2:M1207) -> 28 | C23: All 28 are on unique, discharged episodes — none sit in duplicate rows
A24: Unique episodes (duplicates removed) | B24: =SUMPRODUCT(1/COUNTIF(IP_Raw!A2:A1207,IP_Raw!A2:A1207)) -> 1200 | C24: 1,206 rows − 6 duplicate Episode_IDs
A25: % of episodes uncoded | B25: =B23/B24 -> 0.023333333 | C25: Target 98% coded → actual 97.7%
A26: Tariff per episode (£) | B26: 1850 | C26: Supplied by Priya
A27: Of which admitted in March 2025 (may still be in coding window) | B27: =COUNTIFS(IP_Raw!M2:M1207,"",IP_Raw!E2:E1207,">="&DATE(2025,3,1)) -> 4
A28: Best case — exclude March (coding backlog, recoverable) | B28: =(B23-B27)*B26 -> 44400
A29: Central — all blanks unpaid | B29: =B23*B26 -> 51800
A30: Worst case — plus 25 episodes with HRG but no ICD-10 (may group wrongly) | B30: =(B23+SUMPRODUCT(--(IP_Raw!M2:M1207<>""),--(IP_Raw!P2:P1207="")))*B26 -> 98050 | C30: Upper bound; these may be paid at the wrong HRG rather than not at all
A31: Months covered by the extract | B31: 6 | C31: Oct 2024 – Mar 2025
A32: Average per month (central) | B32: =B23*B26/B31 -> 8633.3333 | C32: Brief assumed £51,800 PER MONTH — the extract shows £51,800 over SIX months (≈£8.6k/month)
A34: TASK 8 — Agency spend range, February 2025 (Priya Chakrabarti)
A35: Period start | B35: 45689 | C35: Latest complete month (export ends 02/03/2025)
A36: Period end | B36: 45716
A37: Valid shifts (ST-99 test records excluded) | B37: =COUNTIFS(WF_Raw!B2:B1561,"<>ST-99*",WF_Raw!E2:E1561,">="&B35,WF_Raw!E2:E1561,"<="&B36) -> 782
A38: Agency_Flag = Y | B38: =COUNTIFS(WF_Raw!B2:B1561,"<>ST-99*",WF_Raw!E2:E1561,">="&B35,WF_Raw!E2:E1561,"<="&B36,WF_Raw!I2:I1561,"Y") -> 128
A39: Agency_Flag = N | B39: =COUNTIFS(WF_Raw!B2:B1561,"<>ST-99*",WF_Raw!E2:E1561,">="&B35,WF_Raw!E2:E1561,"<="&B36,WF_Raw!I2:I1561,"N") -> 643
A40: Agency_Flag blank | B40: =COUNTIFS(WF_Raw!B2:B1561,"<>ST-99*",WF_Raw!E2:E1561,">="&B35,WF_Raw!E2:E1561,"<="&B36,WF_Raw!I2:I1561,"") -> 11
A41: Blank as % of shifts | B41: =B40/B37 -> 0.014066496
A42: Cost per agency shift (£) | B42: 385 | C42: Supplied by Priya
A43: BEST case — all blanks are bank | B43: =B38*B42 -> 49280 | C43: Most likely: blanks arise from bank shifts booked outside the agency module
A44: CENTRAL — blanks agency at the flagged rate | B44: =(B38+B40*B38/(B38+B39))*B42 -> 49983.087
A45: WORST case — all blanks are agency | B45: =(B38+B40)*B42 -> 53515
A46: Cost of the data gap (worst − best) | B46: =B40*B42 -> 4235 | C46: Reconcile against the Finance ledger agency cost centre — it should fall in this range
A48: ED 4-hour — why there are three figures
A49: Raw: N ÷ all rows (blanks = breach) | B49: =COUNTIF(ED_Raw!K2:K970,"N")/COUNTA(ED_Raw!A2:A970) -> 0.79876161
A50: Raw: N ÷ (Y + N) (blanks excluded) | B50: =COUNTIF(ED_Raw!K2:K970,"N")/(COUNTIF(ED_Raw!K2:K970,"Y")+COUNTIF(ED_Raw!K2:K970,"N")) -> 0.83225806
A51: Raw: (N + blanks) ÷ all rows (blanks = pass) | B51: =(COUNTIF(ED_Raw!K2:K970,"N")+COUNTBLANK(ED_Raw!K2:K970))/COUNTA(ED_Raw!A2:A970) -> 0.83900929
A52: VALIDATED: duplicates removed, times recalculated, missing departures excluded | B52: =COUNTIFS(ED_Raw!Q2:Q970,"N",ED_Raw!P2:P970,"")/(COUNTIFS(ED_Raw!Q2:Q970,"N",ED_Raw!P2:P970,"")+COUNTIFS(ED_Raw!Q2:Q970,"Y",ED_Raw!P2:P970,"")) -> 0.83135135 | C52: Helper columns O–Q on ED_Raw
A53: Range if all 35 missing departures were breaches | B53: =COUNTIFS(ED_Raw!Q2:Q970,"N",ED_Raw!P2:P970,"")/COUNTIFS(ED_Raw!P2:P970,"") -> 0.80104167
A54: Range if all 35 missing departures were within 4 hours | B54: =(COUNTIFS(ED_Raw!Q2:Q970,"N",ED_Raw!P2:P970,"")+COUNTIFS(ED_Raw!Q2:Q970,"",ED_Raw!P2:P970,""))/COUNTIFS(ED_Raw!P2:P970,"") -> 0.8375
A55: NHS standard / interim target | B55: 95% / 78%
A57: Theatre utilisation — Finance vs Operations
A58: Session length (hours) | B58: 4 | C58: Assumption: standard 4-hour session
A59: Sessions-based, all theatres incl. T4 | B59: =SUM(TH_Raw!D2:D209)/SUM(TH_Raw!C2:C209) -> 0.7074517
A60: Sessions-based, elective T1–T3 only (Operations method) | B60: =(SUM(TH_Raw!D2:D209)-SUMIF(TH_Raw!B2:B209,"T4",TH_Raw!D2:D209))/(SUM(TH_Raw!C2:C209)-SUMIF(TH_Raw!B2:B209,"T4",TH_Raw!C2:C209)) -> 0.65698479 | C60: Closest to Operations' 64.2%
A61: Hours-based incl. overruns, all theatres (Finance method) | B61: =(SUM(TH_Raw!D2:D209)*B58*60+SUM(TH_Raw!J2:J209))/(SUM(TH_Raw!C2:C209)*B58*60) -> 0.72381746 | C61: Closest to Finance's 71.6% — overrun time is credited as 'used'
A62: Average of pre-calculated Utilisation_Pct (do not use) | B62: =AVERAGE(TH_Raw!E2:E209)/100 -> 0.69304808 | C62: Contains 7 wrong values and averages percentages
A63: Gap explained by: including emergency theatre T4 | B63: =SUM(TH_Raw!D2:D209)/SUM(TH_Raw!C2:C209)-B60 -> 0.050466916
A64: Gap explained by: crediting overrun minutes | B64: =B61-SUM(TH_Raw!D2:D209)/SUM(TH_Raw!C2:C209) -> 0.016365762

Sheet OP_Raw
A1: Appointment_ID | B1: NHS_Number | C1: Patient_Surname | D1: Patient_DOB | E1: Specialty_Code | F1: Consultant_Code | G1: Clinic_Code | H1: Appointment_Date | I1: Appointment_Time | J1: Attendance_Status | K1: Waiting_Days | L1: RTT_Status | M1: RTT_Weeks | N1: Referral_Source | O1: Postcode | P1: Waiting_Days_Validated | Q1: Waiting_Days_Check | R1: Specialty_Code_Clean
A2: APT-100001 | B2: 4823719056 | C2: AHMED | D2: 28564 | E2: GM | F2: C-1042 | G2: CL-101 | H2: 45663 | I2: 09:00 | J2: ATT | K2: 34 | L2: CLOSED | M2: 4.9 | N2: GP | O2: NG1 2AB | P2: =IF(AND(ISNUMBER(K2),K2>=0),K2,IF(ISNUMBER(M2),ROUND(M2*7,0),"")) -> 34 | Q2: =IF(ISTEXT(K2),"TEXT - recovered",IF(K2<0,"NEGATIVE",IF(K2>728,">104 WEEKS","OK"))) -> OK | R2: =IF(E2="GEN","GM",E2) -> GM
A3: APT-100002 | B3: 7612384905 | C3: PATEL | D3: 23945 | E3: CS | F3: C-1017 | G3: CL-102 | H3: 45663 | I3: 09:30 | J3: ATT | K3: 67 | L3: CLOSED | M3: 9.6 | N3: GP | O3: LE1 1AA | P3: =IF(AND(ISNUMBER(K3),K3>=0),K3,IF(ISNUMBER(M3),ROUND(M3*7,0),"")) -> 67 | Q3: =IF(ISTEXT(K3),"TEXT - recovered",IF(K3<0,"NEGATIVE",IF(K3>728,">104 WEEKS","OK"))) -> OK | R3: =IF(E3="GEN","GM",E3) -> CS
A4: APT-100003 | B4: 3394820174 | C4: WILSON | D4: 32820 | E4: OR | F4: C-1033 | G4: CL-103 | H4: 45663 | I4: 10:00 | J4: DNA | K4: 145 | L4: OPEN | M4: 20.7 | N4: GP | O4: NG5 3CD | P4: =IF(AND(ISNUMBER(K4),K4>=0),K4,IF(ISNUMBER(M4),ROUND(M4*7,0),"")) -> 145 | Q4: =IF(ISTEXT(K4),"TEXT - recovered",IF(K4<0,"NEGATIVE",IF(K4>728,">104 WEEKS","OK"))) -> OK | R4: =IF(E4="GEN","GM",E4) -> OR
A5: APT-100004 | B5: 9182746350 | C5: OKAFOR | D5: 26329 | E5: GS | F5: C-1028 | G5: CL-104 | H5: 45663 | I5: 10:30 | J5: ATT | K5: 28 | L5: CLOSED | M5: 4 | N5: CONS | O5: LE2 7GH | P5: =IF(AND(ISNUMBER(K5),K5>=0),K5,IF(ISNUMBER(M5),ROUND(M5*7,0),"")) -> 28 | Q5: =IF(ISTEXT(K5),"TEXT - recovered",IF(K5<0,"NEGATIVE",IF(K5>728,">104 WEEKS","OK"))) -> OK | R5: =IF(E5="GEN","GM",E5) -> GS
A6: APT-100005 | B6: 6547832901 | C6: KHAN | D6: 20620 | E6: RS | F6: C-1051 | G6: CL-105 | H6: 45663 | I6: 11:00 | J6: ATT | K6: 89 | L6: CLOSED | M6: 12.7 | N6: GP | O6: NG7 4EF | P6: =IF(AND(ISNUMBER(K6),K6>=0),K6,IF(ISNUMBER(M6),ROUND(M6*7,0),"")) -> 89 | Q6: =IF(ISTEXT(K6),"TEXT - recovered",IF(K6<0,"NEGATIVE",IF(K6>728,">104 WEEKS","OK"))) -> OK | R6: =IF(E6="GEN","GM",E6) -> RS
A7: APT-100006 | B7: 2938475610 | C7: SMITH | D7: 15952 | E7: EM | F7: C-1009 | G7: CL-106 | H7: 45663 | I7: 11:30 | J7: CAN | K7: 12 | L7: OPEN | M7: 1.7 | N7: ED | O7: NG1 5KL | P7: =IF(AND(ISNUMBER(K7),K7>=0),K7,IF(ISNUMBER(M7),ROUND(M7*7,0),"")) -> 12 | Q7: =IF(ISTEXT(K7),"TEXT - recovered",IF(K7<0,"NEGATIVE",IF(K7>728,">104 WEEKS","OK"))) -> OK | R7: =IF(E7="GEN","GM",E7) -> EM
A8: APT-100007 | B8: 8174629305 | C8: JONES | D8: 29703 | E8: GYN | F8: C-1044 | G8: CL-107 | H8: 45663 | I8: 13:00 | J8: ATT | K8: 56 | L8: CLOSED | M8: 8 | N8: GP | O8: LE4 2MN | P8: =IF(AND(ISNUMBER(K8),K8>=0),K8,IF(ISNUMBER(M8),ROUND(M8*7,0),"")) -> 56 | Q8: =IF(ISTEXT(K8),"TEXT - recovered",IF(K8<0,"NEGATIVE",IF(K8>728,">104 WEEKS","OK"))) -> OK | R8: =IF(E8="GEN","GM",E8) -> GYN
A9: APT-100008 | B9: 5063821749 | C9: WILLIAMS | D9: 34687 | E9: URO | F9: C-1022 | G9: CL-108 | H9: 45663 | I9: 13:30 | J9: DNA | K9: 178 | L9: OPEN | M9: 25.4 | N9: GP | O9: NG8 6PQ | P9: =IF(AND(ISNUMBER(K9),K9>=0),K9,IF(ISNUMBER(M9),ROUND(M9*7,0),"")) -> 178 | Q9: =IF(ISTEXT(K9),"TEXT - recovered",IF(K9<0,"NEGATIVE",IF(K9>728,">104 WEEKS","OK"))) -> OK | R9: =IF(E9="GEN","GM",E9) -> URO
A10: APT-100009 | B10: 1847362905 | C10: BROWN | D10: 24691 | E10: OPH | F10: C-1037 | G10: CL-109 | H10: 45663 | I10: 14:00 | J10: ATT | K10: 45 | L10: CLOSED | M10: 6.4 | N10: GP | O10: LE5 0RS | P10: =IF(AND(ISNUMBER(K10),K10>=0),K10,IF(ISNUMBER(M10),ROUND(M10*7,0),"")) -> 45 | Q10: =IF(ISTEXT(K10),"TEXT - recovered",IF(K10<0,"NEGATIVE",IF(K10>728,">104 WEEKS","OK"))) -> OK | R10: =IF(E10="GEN","GM",E10) -> OPH
A11: APT-100010 | B11: 4729183650 | C11: TAYLOR | D11: 19049 | E11: RHE | F11: C-1015 | G11: CL-110 | H11: 45663 | I11: 14:30 | J11: ATT | K11: 112 | L11: CLOSED | M11: 16 | N11: GP | O11: NG2 1TU | P11: =IF(AND(ISNUMBER(K11),K11>=0),K11,IF(ISNUMBER(M11),ROUND(M11*7,0),"")) -> 112 | Q11: =IF(ISTEXT(K11),"TEXT - recovered",IF(K11<0,"NEGATIVE",IF(K11>728,">104 WEEKS","OK"))) -> OK | R11: =IF(E11="GEN","GM",E11) -> RHE
A12: APT-100011 | B12: 3816294750 | C12: DAVIES | D12: 32427 | E12: GM | F12: C-1042 | G12: CL-101 | H12: 45664 | I12: 09:00 | J12: ATT | K12: 23 | L12: CLOSED | M12: 3.3 | N12: GP | O12: NG3 2VW | P12: =IF(AND(ISNUMBER(K12),K12>=0),K12,IF(ISNUMBER(M12),ROUND(M12*7,0),"")) -> 23 | Q12: =IF(ISTEXT(K12),"TEXT - recovered",IF(K12<0,"NEGATIVE",IF(K12>728,">104 WEEKS","OK"))) -> OK | R12: =IF(E12="GEN","GM",E12) -> GM
A13: APT-100012 | B13: 7294618305 | C13: EVANS | D13: 26814 | E13: CS | F13: C-1017 | G13: CL-102 | H13: 45664 | I13: 09:30 | J13: DNA | K13: 134 | L13: OPEN | M13: 19.1 | N13: GP | O13: LE6 1XY | P13: =IF(AND(ISNUMBER(K13),K13>=0),K13,IF(ISNUMBER(M13),ROUND(M13*7,0),"")) -> 134 | Q13: =IF(ISTEXT(K13),"TEXT - recovered",IF(K13<0,"NEGATIVE",IF(K13>728,">104 WEEKS","OK"))) -> OK | R13: =IF(E13="GEN","GM",E13) -> CS
... A153: APT-100152 | B153: 6291374056 | C153: RICE | D153: 27766 | E153: GYN | F153: C-1044 | G153: CL-107 | H153: 45684 | I153: 09:30 | J153: ATT | K153: 57 | L153: CLOSED | M153: 8.1 | N153: GP | O153: LE3 1NO | P153: =IF(AND(ISNUMBER(K153),K153>=0),K153,IF(ISNUMBER(M153),ROUND(M153*7,0),"")) -> 57 | Q153: =IF(ISTEXT(K153),"TEXT - recovered",IF(K153<0,"NEGATIVE",IF(K153>728,">104 WEEKS","OK"))) -> OK | R153: =IF(E153="GEN","GM",E153) -> GYN
A154: APT-100153 | C154: HASSAN | D154: 29329 | E154: GEN | F154: C-1033 | G154: CL-103 | H154: 45684 | I154: 10:00 | J154: ATT | K154: 78 | M154: 11.1 | N154: GP | O154: NG5 3CD | P154: =IF(AND(ISNUMBER(K154),K154>=0),K154,IF(ISNUMBER(M154),ROUND(M154*7,0),"")) -> 78 | Q154: =IF(ISTEXT(K154),"TEXT - recovered",IF(K154<0,"NEGATIVE",IF(K154>728,">104 WEEKS","OK"))) -> OK | R154: =IF(E154="GEN","GM",E154) -> GM
A155: APT-100154 | B155: 7184926350 | C155: NGUYEN | D155: 21492 | E155: CS | F155: C-1017 | G155: CL-102 | H155: 45684 | I155: 10:30 | J155: attended | K155: 34 | L155: CLOSED | M155: 4.9 | N155: GP | O155: LE1 1AA | P155: =IF(AND(ISNUMBER(K155),K155>=0),K155,IF(ISNUMBER(M155),ROUND(M155*7,0),"")) -> 34 | Q155: =IF(ISTEXT(K155),"TEXT - recovered",IF(K155<0,"NEGATIVE",IF(K155>728,">104 WEEKS","OK"))) -> OK | R155: =IF(E155="GEN","GM",E155) -> CS
A156: APT-100155 | B156: 3829174605 | C156: BROOKS | D156: 30112 | E156: GM | F156: C-1042 | G156: CL-101 | H156: 45684 | I156: 11:00 | J156: ATT | K156: 45 | L156: CLOSED | M156: 6.4 | N156: GP | O156: LE6 3LM | P156: =IF(AND(ISNUMBER(K156),K156>=0),K156,IF(ISNUMBER(M156),ROUND(M156*7,0),"")) -> 45 | Q156: =IF(ISTEXT(K156),"TEXT - recovered",IF(K156<0,"NEGATIVE",IF(K156>728,">104 WEEKS","OK"))) -> OK | R156: =IF(E156="GEN","GM",E156) -> GM
A157: APT-100156 | B157: 4819273650 | C157: OSEI | D157: 33444 | E157: OR | G157: CL-103 | H157: 45684 | I157: 11:30 | J157: DNA | K157: 145 | L157: OPEN | M157: 20.7 | N157: GP | P157: =IF(AND(ISNUMBER(K157),K157>=0),K157,IF(ISNUMBER(M157),ROUND(M157*7,0),"")) -> 145 | Q157: =IF(ISTEXT(K157),"TEXT - recovered",IF(K157<0,"NEGATIVE",IF(K157>728,">104 WEEKS","OK"))) -> OK | R157: =IF(E157="GEN","GM",E157) -> OR
A158: APT-100157 | B158: 2947163850 | C158: JACKSON | D158: 29102 | E158: GS | F158: C-1028 | G158: CL-104 | H158: 45684 | I158: 13:00 | J158: ATT | K158: 42 | L158: CLOSED | M158: 6 | N158: GP | O158: LE7 2BC | P158: =IF(AND(ISNUMBER(K158),K158>=0),K158,IF(ISNUMBER(M158),ROUND(M158*7,0),"")) -> 42 | Q158: =IF(ISTEXT(K158),"TEXT - recovered",IF(K158<0,"NEGATIVE",IF(K158>728,">104 WEEKS","OK"))) -> OK | R158: =IF(E158="GEN","GM",E158) -> GS
A159: APT-100158 | B159: 8163924750 | C159: MENSAH | D159: 23813 | E159: RS | F159: C-1051 | G159: CL-105 | H159: 45684 | I159: 13:30 | J159: DNA | K159: 189 | L159: OPEN | M159: 27 | N159: GP | O159: NG7 5CD | P159: =IF(AND(ISNUMBER(K159),K159>=0),K159,IF(ISNUMBER(M159),ROUND(M159*7,0),"")) -> 189 | Q159: =IF(ISTEXT(K159),"TEXT - recovered",IF(K159<0,"NEGATIVE",IF(K159>728,">104 WEEKS","OK"))) -> OK | R159: =IF(E159="GEN","GM",E159) -> RS
A160: APT-100159 | B160: 5948271630 | C160: ROBINSON | D160: 28087 | E160: RHE | F160: C-1015 | G160: CL-110 | H160: 45684 | I160: 14:00 | J160: DNA | K160: 168 | L160: OPEN | M160: 24 | N160: GP | O160: NG7 6NO | P160: =IF(AND(ISNUMBER(K160),K160>=0),K160,IF(ISNUMBER(M160),ROUND(M160*7,0),"")) -> 168 | Q160: =IF(ISTEXT(K160),"TEXT - recovered",IF(K160<0,"NEGATIVE",IF(K160>728,">104 WEEKS","OK"))) -> OK | R160: =IF(E160="GEN","GM",E160) -> RHE
A161: APT-100160 | B161: 6183924750 | C161: WHITE | D161: 16639 | E161: GEN | F161: C-1051 | G161: CL-105 | H161: 45684 | I161: 14:30 | J161: ATT | K161: 56 | L161: CLOSED | M161: 8 | N161: GP | O161: NG5 4DE | P161: =IF(AND(ISNUMBER(K161),K161>=0),K161,IF(ISNUMBER(M161),ROUND(M161*7,0),"")) -> 56 | Q161: =IF(ISTEXT(K161),"TEXT - recovered",IF(K161<0,"NEGATIVE",IF(K161>728,">104 WEEKS","OK"))) -> OK | R161: =IF(E161="GEN","GM",E161) -> GM
A162: APT-100161 | B162: 4273819605 | C162: WRIGHT | D162: 30898 | E162: GM | F162: C-1042 | G162: CL-101 | H162: 45685 | I162: 09:00 | J162: ATT | K162: 35 | L162: CLOSED | M162: 5 | N162: GP | O162: LE5 7JK | P162: =IF(AND(ISNUMBER(K162),K162>=0),K162,IF(ISNUMBER(M162),ROUND(M162*7,0),"")) -> 35 | Q162: =IF(ISTEXT(K162),"TEXT - recovered",IF(K162<0,"NEGATIVE",IF(K162>728,">104 WEEKS","OK"))) -> OK | R162: =IF(E162="GEN","GM",E162) -> GM
A163: APT-100162 | B163: 8149273650 | C163: SCOTT | D163: 24949 | E163: CS | F163: C-1017 | G163: CL-102 | H163: 45685 | I163: 09:30 | J163: DNA | K163: 202 | L163: OPEN | M163: 28.9 | N163: GP | O163: NG6 4LM | P163: =IF(AND(ISNUMBER(K163),K163>=0),K163,IF(ISNUMBER(M163),ROUND(M163*7,0),"")) -> 202 | Q163: =IF(ISTEXT(K163),"TEXT - recovered",IF(K163<0,"NEGATIVE",IF(K163>728,">104 WEEKS","OK"))) -> OK | R163: =IF(E163="GEN","GM",E163) -> CS
A164: APT-100163 | B164: 1847362905 | C164: DAVIES | D164: 32427 | E164: GM | F164: C-1042 | G164: CL-101 | H164: 45685 | I164: 10:00 | J164: ATT | K164: 24 | L164: CLOSED | M164: 3.4 | N164: GP | O164: NG3 2VW | P164: =IF(AND(ISNUMBER(K164),K164>=0),K164,IF(ISNUMBER(M164),ROUND(M164*7,0),"")) -> 24 | Q164: =IF(ISTEXT(K164),"TEXT - recovered",IF(K164<0,"NEGATIVE",IF(K164>728,">104 WEEKS","OK"))) -> OK | R164: =IF(E164="GEN","GM",E164) -> GM
A165: APT-100164 | C165: CHIRWA | D165: 25728 | E165: OR | F165: C-1033 | G165: CL-103 | H165: 45685 | I165: 10:30 | J165: DNA | K165: 267 | L165: OPEN | M165: 38.1 | N165: GP | O165: NG2 4TU | P165: =IF(AND(ISNUMBER(K165),K165>=0),K165,IF(ISNUMBER(M165),ROUND(M165*7,0),"")) -> 267 | Q165: =IF(ISTEXT(K165),"TEXT - recovered",IF(K165<0,"NEGATIVE",IF(K165>728,">104 WEEKS","OK"))) -> OK | R165: =IF(E165="GEN","GM",E165) -> OR
A166: APT-100165 | B166: 7294618305 | C166: EVANS | D166: 26814 | E166: CS | F166: C-1017 | G166: CL-102 | H166: 45685 | I166: 11:00 | J166: ATT | K166: 56 | L166: CLOSED | M166: 8 | N166: CONS | O166: LE6 1XY | P166: =IF(AND(ISNUMBER(K166),K166>=0),K166,IF(ISNUMBER(M166),ROUND(M166*7,0),"")) -> 56 | Q166: =IF(ISTEXT(K166),"TEXT - recovered",IF(K166<0,"NEGATIVE",IF(K166>728,">104 WEEKS","OK"))) -> OK | R166: =IF(E166="GEN","GM",E166) -> CS
A167: APT-100166 | B167: 3947821605 | C167: ADEYEMI | D167: 31460 | E167: GYN | F167: C-1044 | G167: CL-107 | H167: 45685 | I167: 11:30 | J167: ATT | K167: 34 | L167: CLOSED | M167: 4.9 | N167: GP | O167: LE4 2MN | P167: =IF(AND(ISNUMBER(K167),K167>=0),K167,IF(ISNUMBER(M167),ROUND(M167*7,0),"")) -> 34 | Q167: =IF(ISTEXT(K167),"TEXT - recovered",IF(K167<0,"NEGATIVE",IF(K167>728,">104 WEEKS","OK"))) -> OK | R167: =IF(E167="GEN","GM",E167) -> GYN
A168: APT-100167 | B168: 6374829105 | C168: NELSON | D168: 27168 | E168: GYN | F168: C-1044 | G168: CL-107 | H168: 45685 | I168: 13:00 | J168: ATT | K168: 46 | L168: CLOSED | M168: 6.6 | N168: GP | O168: LE8 4VW | P168: =IF(AND(ISNUMBER(K168),K168>=0),K168,IF(ISNUMBER(M168),ROUND(M168*7,0),"")) -> 46 | Q168: =IF(ISTEXT(K168),"TEXT - recovered",IF(K168<0,"NEGATIVE",IF(K168>728,">104 WEEKS","OK"))) -> OK | R168: =IF(E168="GEN","GM",E168) -> GYN
A169: APT-100168 | B169: 5183924760 | C169: WOOD | D169: 23329 | E169: EM | F169: C-1009 | G169: CL-106 | H169: 45685 | I169: 13:30 | J169: ATT | K169: 26 | L169: OPEN | M169: 3.7 | N169: ED | O169: NG5 5VW | P169: =IF(AND(ISNUMBER(K169),K169>=0),K169,IF(ISNUMBER(M169),ROUND(M169*7,0),"")) -> 26 | Q169: =IF(ISTEXT(K169),"TEXT - recovered",IF(K169<0,"NEGATIVE",IF(K169>728,">104 WEEKS","OK"))) -> OK | R169: =IF(E169="GEN","GM",E169) -> EM
A170: APT-100169 | B170: 8291736450 | C170: OKONKWO | D170: 29089 | E170: GS | G170: CL-104 | H170: 45685 | I170: 14:00 | J170: ATT | K170: 67 | L170: CLOSED | M170: 9.6 | N170: GP | O170: LE9 3NO | P170: =IF(AND(ISNUMBER(K170),K170>=0),K170,IF(ISNUMBER(M170),ROUND(M170*7,0),"")) -> 67 | Q170: =IF(ISTEXT(K170),"TEXT - recovered",IF(K170<0,"NEGATIVE",IF(K170>728,">104 WEEKS","OK"))) -> OK | R170: =IF(E170="GEN","GM",E170) -> GS
A171: APT-100170 | B171: 3748291605 | C171: PEREZ | D171: 26003 | E171: RHE | F171: C-1015 | G171: CL-110 | H171: 45685 | I171: 14:30 | J171: ATT | K171: 68 | L171: CLOSED | M171: 9.7 | N171: GP | O171: NG2 3BC | P171: =IF(AND(ISNUMBER(K171),K171>=0),K171,IF(ISNUMBER(M171),ROUND(M171*7,0),"")) -> 68 | Q171: =IF(ISTEXT(K171),"TEXT - recovered",IF(K171<0,"NEGATIVE",IF(K171>728,">104 WEEKS","OK"))) -> OK | R171: =IF(E171="GEN","GM",E171) -> RHE
A172: APT-100171 | B172: 5847291360 | C172: PATTERSON | D172: 32195 | E172: RS | F172: C-1051 | G172: CL-105 | H172: 45686 | I172: 09:00 | J172: ATT | K172: 46 | L172: CLOSED | M172: 6.6 | N172: GP | O172: LE4 5NO | P172: =IF(AND(ISNUMBER(K172),K172>=0),K172,IF(ISNUMBER(M172),ROUND(M172*7,0),"")) -> 46 | Q172: =IF(ISTEXT(K172),"TEXT - recovered",IF(K172<0,"NEGATIVE",IF(K172>728,">104 WEEKS","OK"))) -> OK | R172: =IF(E172="GEN","GM",E172) -> RS
A173: APT-100172 | B173: 2947163850 | C173: JACKSON | D173: 29102 | E173: GS | F173: C-1028 | G173: CL-104 | H173: 45686 | I173: 09:30 | J173: DNA | K173: 179 | L173: OPEN | M173: 25.6 | N173: GP | O173: LE7 2BC | P173: =IF(AND(ISNUMBER(K173),K173>=0),K173,IF(ISNUMBER(M173),ROUND(M173*7,0),"")) -> 179 | Q173: =IF(ISTEXT(K173),"TEXT - recovered",IF(K173<0,"NEGATIVE",IF(K173>728,">104 WEEKS","OK"))) -> OK | R173: =IF(E173="GEN","GM",E173) -> GS
A174: APT-100173 | B174: 4817293605 | C174: KELLY | D174: 28343 | E174: GYN | F174: C-1044 | G174: CL-107 | H174: 45686 | I174: 10:00 | J174: ATT | K174: 46 | L174: CLOSED | M174: 6.6 | N174: GP | O174: LE8 1JK | P174: =IF(AND(ISNUMBER(K174),K174>=0),K174,IF(ISNUMBER(M174),ROUND(M174*7,0),"")) -> 46 | Q174: =IF(ISTEXT(K174),"TEXT - recovered",IF(K174<0,"NEGATIVE",IF(K174>728,">104 WEEKS","OK"))) -> OK | R174: =IF(E174="GEN","GM",E174) -> GYN
A175: APT-100174 | B175: 9374821605 | C175: WATSON | D175: 25840 | E175: RHE | F175: C-1015 | G175: CL-110 | H175: 45686 | I175: 10:30 | J175: ATT | K175: 46 | L175: CLOSED | M175: 6.6 | N175: GP | O175: NG2 6JK | P175: =IF(AND(ISNUMBER(K175),K175>=0),K175,IF(ISNUMBER(M175),ROUND(M175*7,0),"")) -> 46 | Q175: =IF(ISTEXT(K175),"TEXT - recovered",IF(K175<0,"NEGATIVE",IF(K175>728,">104 WEEKS","OK"))) -> OK | R175: =IF(E175="GEN","GM",E175) -> RHE
A176: APT-100175 | C176: IHEJIRIKA | D176: 23206 | E176: GM | F176: C-1042 | G176: CL-101 | H176: 45686 | I176: 11:00 | J176: DNA | K176: 312 | L176: OPEN | M176: 44.6 | N176: GP | O176: NG1 2AB | P176: =IF(AND(ISNUMBER(K176),K176>=0),K176,IF(ISNUMBER(M176),ROUND(M176*7,0),"")) -> 312 | Q176: =IF(ISTEXT(K176),"TEXT - recovered",IF(K176<0,"NEGATIVE",IF(K176>728,">104 WEEKS","OK"))) -> OK | R176: =IF(E176="GEN","GM",E176) -> GM
A177: APT-100176 | B177: 6193847205 | C177: ALEXANDER | D177: 22432 | E177: GS | F177: C-1028 | G177: CL-104 | H177: 45686 | I177: 11:30 | J177: ATT | K177: 35 | L177: CLOSED | M177: 5 | N177: GP | O177: NG6 5FG | P177: =IF(AND(ISNUMBER(K177),K177>=0),K177,IF(ISNUMBER(M177),ROUND(M177*7,0),"")) -> 35 | Q177: =IF(ISTEXT(K177),"TEXT - recovered",IF(K177<0,"NEGATIVE",IF(K177>728,">104 WEEKS","OK"))) -> OK | R177: =IF(E177="GEN","GM",E177) -> GS
A178: APT-100177 | B178: 7491836250 | C178: ADAMS | D178: 29063 | E178: GS | F178: C-1028 | G178: CL-104 | H178: 45686 | I178: 13:00 | J178: ATT | K178: 57 | L178: CLOSED | M178: 8.1 | N178: GP | O178: NG7 5PQ | P178: =IF(AND(ISNUMBER(K178),K178>=0),K178,IF(ISNUMBER(M178),ROUND(M178*7,0),"")) -> 57 | Q178: =IF(ISTEXT(K178),"TEXT - recovered",IF(K178<0,"NEGATIVE",IF(K178>728,">104 WEEKS","OK"))) -> OK | R178: =IF(E178="GEN","GM",E178) -> GS
A179: APT-100178 | B179: 4938271560 | C179: HENRY | D179: 22681 | E179: RHE | F179: C-1015 | G179: CL-110 | H179: 45686 | I179: 13:30 | J179: ATT | K179: 113 | L179: CLOSED | M179: 16.1 | N179: GP | O179: NG2 9ZA | P179: =IF(AND(ISNUMBER(K179),K179>=0),K179,IF(ISNUMBER(M179),ROUND(M179*7,0),"")) -> 113 | Q179: =IF(ISTEXT(K179),"TEXT - recovered",IF(K179<0,"NEGATIVE",IF(K179>728,">104 WEEKS","OK"))) -> OK | R179: =IF(E179="GEN","GM",E179) -> RHE
A180: APT-100179 | B180: 8374291605 | C180: HARRIS | D180: 30293 | E180: EM | F180: C-1009 | G180: CL-106 | H180: 45686 | I180: 14:00 | J180: ATT | K180: 16 | L180: OPEN | M180: 2.3 | N180: ED | O180: NG1 5FG | P180: =IF(AND(ISNUMBER(K180),K180>=0),K180,IF(ISNUMBER(M180),ROUND(M180*7,0),"")) -> 16 | Q180: =IF(ISTEXT(K180),"TEXT - recovered",IF(K180<0,"NEGATIVE",IF(K180>728,">104 WEEKS","OK"))) -> OK | R180: =IF(E180="GEN","GM",E180) -> EM
A181: APT-100180 | B181: 1938274605 | C181: BAILEY | D181: 31626 | E181: URO | F181: C-1022 | G181: CL-108 | H181: 45686 | I181: 14:30 | J181: DNA | K181: 213 | L181: OPEN | M181: 30.4 | N181: GP | O181: NG3 8LM | P181: =IF(AND(ISNUMBER(K181),K181>=0),K181,IF(ISNUMBER(M181),ROUND(M181*7,0),"")) -> 213 | Q181: =IF(ISTEXT(K181),"TEXT - recovered",IF(K181<0,"NEGATIVE",IF(K181>728,">104 WEEKS","OK"))) -> OK | R181: =IF(E181="GEN","GM",E181) -> URO
A182: APT-100181 | B182: 4823719056 | C182: AHMED | D182: 28564 | E182: GM | F182: C-1042 | G182: CL-101 | H182: 45687 | I182: 09:00 | J182: ATT | K182: 35 | L182: CLOSED | M182: 5 | N182: GP | O182: NG1 2AB | P182: =IF(AND(ISNUMBER(K182),K182>=0),K182,IF(ISNUMBER(M182),ROUND(M182*7,0),"")) -> 35 | Q182: =IF(ISTEXT(K182),"TEXT - recovered",IF(K182<0,"NEGATIVE",IF(K182>728,">104 WEEKS","OK"))) -> OK | R182: =IF(E182="GEN","GM",E182) -> GM
A183: APT-100182 | B183: 7612384905 | C183: PATEL | D183: 23945 | E183: CS | F183: C-1017 | G183: CL-102 | H183: 45687 | I183: 09:30 | J183: ATT | K183: 68 | L183: CLOSED | M183: 9.7 | N183: GP | O183: LE1 1AA | P183: =IF(AND(ISNUMBER(K183),K183>=0),K183,IF(ISNUMBER(M183),ROUND(M183*7,0),"")) -> 68 | Q183: =IF(ISTEXT(K183),"TEXT - recovered",IF(K183<0,"NEGATIVE",IF(K183>728,">104 WEEKS","OK"))) -> OK | R183: =IF(E183="GEN","GM",E183) -> CS
A184: APT-100183 | B184: 5063821749 | C184: WILLIAMS | D184: 34687 | E184: URO | F184: C-1022 | G184: CL-108 | H184: 45687 | I184: 10:00 | J184: ATT | K184: 35 | L184: CLOSED | M184: 5 | N184: GP | O184: NG8 6PQ | P184: =IF(AND(ISNUMBER(K184),K184>=0),K184,IF(ISNUMBER(M184),ROUND(M184*7,0),"")) -> 35 | Q184: =IF(ISTEXT(K184),"TEXT - recovered",IF(K184<0,"NEGATIVE",IF(K184>728,">104 WEEKS","OK"))) -> OK | R184: =IF(E184="GEN","GM",E184) -> URO
A185: APT-100184 | B185: 2738491605 | C185: PRICE | D185: 18453 | E185: GS | F185: C-1028 | G185: CL-104 | H185: 45687 | I185: 10:30 | J185: ATT | K185: 90 | L185: CLOSED | M185: 12.9 | N185: GP | O185: NG4 8RS | P185: =IF(AND(ISNUMBER(K185),K185>=0),K185,IF(ISNUMBER(M185),ROUND(M185*7,0),"")) -> 90 | Q185: =IF(ISTEXT(K185),"TEXT - recovered",IF(K185<0,"NEGATIVE",IF(K185>728,">104 WEEKS","OK"))) -> OK | R185: =IF(E185="GEN","GM",E185) -> GS
A186: APT-100185 | B186: 6491837250 | C186: REED | D186: 26998 | E186: OR | F186: C-1033 | G186: CL-103 | H186: 45687 | I186: 11:00 | J186: DNA | K186: 312 | L186: OPEN | M186: 44.6 | N186: GP | O186: LE6 5BC | P186: =IF(AND(ISNUMBER(K186),K186>=0),K186,IF(ISNUMBER(M186),ROUND(M186*7,0),"")) -> 312 | Q186: =IF(ISTEXT(K186),"TEXT - recovered",IF(K186<0,"NEGATIVE",IF(K186>728,">104 WEEKS","OK"))) -> OK | R186: =IF(E186="GEN","GM",E186) -> OR
A187: APT-100186 | B187: 9182746350 | C187: OKAFOR | D187: 26329 | E187: GS | F187: C-1028 | G187: CL-OLD | H187: 45687 | I187: 11:30 | J187: ATT | K187: 28 | L187: CLOSED | M187: 4 | N187: CONS | O187: LE2 7GH | P187: =IF(AND(ISNUMBER(K187),K187>=0),K187,IF(ISNUMBER(M187),ROUND(M187*7,0),"")) -> 28 | Q187: =IF(ISTEXT(K187),"TEXT - recovered",IF(K187<0,"NEGATIVE",IF(K187>728,">104 WEEKS","OK"))) -> OK | R187: =IF(E187="GEN","GM",E187) -> GS
A188: APT-100187 | B188: 3628194705 | C188: MORGAN | D188: 32633 | E188: RS | F188: C-1051 | G188: CL-105 | H188: 45687 | I188: 13:00 | J188: ATT | K188: 35 | L188: CLOSED | M188: 5 | N188: GP | O188: LE7 6FG | P188: =IF(AND(ISNUMBER(K188),K188>=0),K188,IF(ISNUMBER(M188),ROUND(M188*7,0),"")) -> 35 | Q188: =IF(ISTEXT(K188),"TEXT - recovered",IF(K188<0,"NEGATIVE",IF(K188>728,">104 WEEKS","OK"))) -> OK | R188: =IF(E188="GEN","GM",E188) -> RS
... A191: APT-100190 | B191: 9182637450 | C191: COOPER | D191: 27305 | E191: RHE | F191: C-1015 | G191: CL-110 | H191: 45687 | I191: 14:30 | J191: ATT | K191: 90 | L191: CLOSED | M191: 12.9 | N191: GP | O191: NG4 5PQ | P191: =IF(AND(ISNUMBER(K191),K191>=0),K191,IF(ISNUMBER(M191),ROUND(M191*7,0),"")) -> 90 | Q191: =IF(ISTEXT(K191),"TEXT - recovered",IF(K191<0,"NEGATIVE",IF(K191>728,">104 WEEKS","OK"))) -> OK | R191: =IF(E191="GEN","GM",E191) -> RHE
A192: APT-100191 | B192: 4819273650 | C192: OSEI | D192: 33444 | E192: OR | G192: CL-103 | H192: 45688 | I192: 09:00 | J192: DNA | K192: 146 | L192: OPEN | M192: 20.9 | N192: GP | P192: =IF(AND(ISNUMBER(K192),K192>=0),K192,IF(ISNUMBER(M192),ROUND(M192*7,0),"")) -> 146 | Q192: =IF(ISTEXT(K192),"TEXT - recovered",IF(K192<0,"NEGATIVE",IF(K192>728,">104 WEEKS","OK"))) -> OK | R192: =IF(E192="GEN","GM",E192) -> OR
A193: APT-100192 | B193: 6293817450 | C193: EDWARDS | D193: 28504 | E193: GYN | F193: C-1044 | G193: CL-107 | H193: 45688 | I193: 09:30 | J193: DNA | K193: 135 | L193: OPEN | M193: 19.3 | N193: GP | O193: LE3 4PQ | P193: =IF(AND(ISNUMBER(K193),K193>=0),K193,IF(ISNUMBER(M193),ROUND(M193*7,0),"")) -> 135 | Q193: =IF(ISTEXT(K193),"TEXT - recovered",IF(K193<0,"NEGATIVE",IF(K193>728,">104 WEEKS","OK"))) -> OK | R193: =IF(E193="GEN","GM",E193) -> GYN
A194: APT-100193 | B194: 2948371605 | C194: PHILLIPS | D194: 25358 | E194: OR | F194: C-1033 | G194: CL-103 | H194: 45688 | I194: 10:00 | J194: ATT | K194: 90 | L194: CLOSED | M194: 12.9 | N194: CONS | O194: NG3 5HI | P194: =IF(AND(ISNUMBER(K194),K194>=0),K194,IF(ISNUMBER(M194),ROUND(M194*7,0),"")) -> 90 | Q194: =IF(ISTEXT(K194),"TEXT - recovered",IF(K194<0,"NEGATIVE",IF(K194>728,">104 WEEKS","OK"))) -> OK | R194: =IF(E194="GEN","GM",E194) -> OR
A195: APT-100194 | B195: 7483921605 | C195: PETERSON | D195: 17154 | E195: EM | F195: C-1009 | G195: CL-106 | H195: 45688 | I195: 10:30 | J195: CAN | K195: 15 | L195: OPEN | M195: 2.1 | N195: ED | O195: NG1 9BC | P195: =IF(AND(ISNUMBER(K195),K195>=0),K195,IF(ISNUMBER(M195),ROUND(M195*7,0),"")) -> 15 | Q195: =IF(ISTEXT(K195),"TEXT - recovered",IF(K195<0,"NEGATIVE",IF(K195>728,">104 WEEKS","OK"))) -> OK | R195: =IF(E195="GEN","GM",E195) -> EM
A196: APT-100195 | B196: 5927384160 | C196: GRAY | D196: 28343 | E196: GYN | F196: C-1044 | G196: CL-107 | H196: 45688 | I196: 11:00 | J196: ATT | K196: 68 | L196: CLOSED | M196: 9.7 | N196: GP | O196: LE4 4DE | P196: =IF(AND(ISNUMBER(K196),K196>=0),K196,IF(ISNUMBER(M196),ROUND(M196*7,0),"")) -> 68 | Q196: =IF(ISTEXT(K196),"TEXT - recovered",IF(K196<0,"NEGATIVE",IF(K196>728,">104 WEEKS","OK"))) -> OK | R196: =IF(E196="GEN","GM",E196) -> GYN
A197: APT-100196 | B197: 8163924750 | C197: MENSAH | D197: 23813 | E197: RS | F197: C-1051 | G197: CL-105 | H197: 45688 | I197: 11:30 | J197: DNA | K197: 190 | L197: OPEN | M197: 27.1 | N197: GP | O197: NG7 5CD | P197: =IF(AND(ISNUMBER(K197),K197>=0),K197,IF(ISNUMBER(M197),ROUND(M197*7,0),"")) -> 190 | Q197: =IF(ISTEXT(K197),"TEXT - recovered",IF(K197<0,"NEGATIVE",IF(K197>728,">104 WEEKS","OK"))) -> OK | R197: =IF(E197="GEN","GM",E197) -> RS
A198: APT-100197 | B198: 1847293605 | C198: RAMIREZ | D198: 34083 | E198: URO | F198: C-1022 | G198: CL-108 | H198: 45688 | I198: 13:00 | J198: ATT | K198: 24 | L198: CLOSED | M198: 3.4 | N198: GP | O198: NG7 3FG | P198: =IF(AND(ISNUMBER(K198),K198>=0),K198,IF(ISNUMBER(M198),ROUND(M198*7,0),"")) -> 24 | Q198: =IF(ISTEXT(K198),"TEXT - recovered",IF(K198<0,"NEGATIVE",IF(K198>728,">104 WEEKS","OK"))) -> OK | R198: =IF(E198="GEN","GM",E198) -> URO
A199: APT-100198 | B199: 3947821605 | C199: ADEYEMI | D199: 31460 | E199: GYN | F199: C-1044 | G199: CL-107 | H199: 45688 | I199: 13:30 | J199: ATT | K199: 35 | L199: CLOSED | M199: 5 | N199: GP | O199: LE4 2MN | P199: =IF(AND(ISNUMBER(K199),K199>=0),K199,IF(ISNUMBER(M199),ROUND(M199*7,0),"")) -> 35 | Q199: =IF(ISTEXT(K199),"TEXT - recovered",IF(K199<0,"NEGATIVE",IF(K199>728,">104 WEEKS","OK"))) -> OK | R199: =IF(E199="GEN","GM",E199) -> GYN
A200: APT-100199 | B200: 6374821095 | C200: ODUYA | D200: 26570 | E200: GEN | G200: CL-DEP | H200: 45688 | I200: 14:00 | J200: N/A | K200: 89 | L200: OPEN | M200: 12.7 | N200: Other | O200: XX1 1XX | P200: =IF(AND(ISNUMBER(K200),K200>=0),K200,IF(ISNUMBER(M200),ROUND(M200*7,0),"")) -> 89 | Q200: =IF(ISTEXT(K200),"TEXT - recovered",IF(K200<0,"NEGATIVE",IF(K200>728,">104 WEEKS","OK"))) -> OK | R200: =IF(E200="GEN","GM",E200) -> GM
A201: APT-100200 | B201: 4182739605 | C201: IBRAHIM | D201: 30818 | E201: GM | F201: C-1042 | G201: CL-101 | H201: 45688 | I201: TBC | J201: ATT | K201: -3 | L201: OPEN | N201: GP | O201: NG1 8ZA | P201: =IF(AND(ISNUMBER(K201),K201>=0),K201,IF(ISNUMBER(M201),ROUND(M201*7,0),"")) | Q201: =IF(ISTEXT(K201),"TEXT - recovered",IF(K201<0,"NEGATIVE",IF(K201>728,">104 WEEKS","OK"))) -> NEGATIVE | R201: =IF(E201="GEN","GM",E201) -> GM
A202: APT-100201 | B202: 8291736450 | C202: OKONKWO | D202: 29089 | E202: GS | G202: CL-104 | H202: 45691 | I202: 09:00 | J202: ATT | K202: 68 | L202: CLOSED | M202: 9.7 | N202: GP | O202: LE9 3NO | P202: =IF(AND(ISNUMBER(K202),K202>=0),K202,IF(ISNUMBER(M202),ROUND(M202*7,0),"")) -> 68 | Q202: =IF(ISTEXT(K202),"TEXT - recovered",IF(K202<0,"NEGATIVE",IF(K202>728,">104 WEEKS","OK"))) -> OK | R202: =IF(E202="GEN","GM",E202) -> GS
A203: APT-100202 | B203: 1637294805 | C203: EVANS | D203: 23555 | E203: EM | F203: C-1009 | G203: CL-106 | H203: 45691 | I203: 09:30 | J203: CAN | K203: 9 | L203: OPEN | M203: 1.3 | N203: ED | O203: NG1 2NO | P203: =IF(AND(ISNUMBER(K203),K203>=0),K203,IF(ISNUMBER(M203),ROUND(M203*7,0),"")) -> 9 | Q203: =IF(ISTEXT(K203),"TEXT - recovered",IF(K203<0,"NEGATIVE",IF(K203>728,">104 WEEKS","OK"))) -> OK | R203: =IF(E203="GEN","GM",E203) -> EM
A204: APT-100203 | B204: 5847291036 | C204: WALLACE | D204: 20175 | E204: GS | F204: C-1028 | G204: CL-104 | H204: 45691 | I204: 10:00 | J204: ATT | K204: 35 | L204: CLOSED | M204: 5 | N204: GP | O204: NG5 1ZA | P204: =IF(AND(ISNUMBER(K204),K204>=0),K204,IF(ISNUMBER(M204),ROUND(M204*7,0),"")) -> 35 | Q204: =IF(ISTEXT(K204),"TEXT - recovered",IF(K204<0,"NEGATIVE",IF(K204>728,">104 WEEKS","OK"))) -> OK | R204: =IF(E204="GEN","GM",E204) -> GS
A205: APT-100204 | B205: 7184926350 | C205: NGUYEN | D205: 21492 | E205: CS | F205: C-1017 | G205: CL-102 | H205: 45691 | I205: 10:30 | J205: ATT | K205: 35 | L205: CLOSED | M205: 5 | N205: GP | O205: LE1 1AA | P205: =IF(AND(ISNUMBER(K205),K205>=0),K205,IF(ISNUMBER(M205),ROUND(M205*7,0),"")) -> 35 | Q205: =IF(ISTEXT(K205),"TEXT - recovered",IF(K205<0,"NEGATIVE",IF(K205>728,">104 WEEKS","OK"))) -> OK | R205: =IF(E205="GEN","GM",E205) -> CS
A206: APT-100205 | B206: 3829174605 | C206: BROOKS | D206: 30112 | E206: GM | F206: C-1042 | G206: CL-101 | H206: 45691 | I206: 11:00 | J206: ATT | K206: 46 | L206: CLOSED | M206: 6.6 | N206: GP | O206: LE6 3LM | P206: =IF(AND(ISNUMBER(K206),K206>=0),K206,IF(ISNUMBER(M206),ROUND(M206*7,0),"")) -> 46 | Q206: =IF(ISTEXT(K206),"TEXT - recovered",IF(K206<0,"NEGATIVE",IF(K206>728,">104 WEEKS","OK"))) -> OK | R206: =IF(E206="GEN","GM",E206) -> GM
A207: APT-100206 | B207: 6374821095 | C207: ODUYA | D207: 26570 | E207: GM | F207: C-1042 | G207: CL-101 | H207: 45691 | I207: 11:30 | J207: ATT | K207: 35 | L207: CLOSED | M207: 5 | N207: GP | O207: NG1 7DE | P207: =IF(AND(ISNUMBER(K207),K207>=0),K207,IF(ISNUMBER(M207),ROUND(M207*7,0),"")) -> 35 | Q207: =IF(ISTEXT(K207),"TEXT - recovered",IF(K207<0,"NEGATIVE",IF(K207>728,">104 WEEKS","OK"))) -> OK | R207: =IF(E207="GEN","GM",E207) -> GM
A208: APT-100207 | B208: 2947163850 | C208: JACKSON | D208: 29102 | E208: GS | F208: C-1028 | G208: CL-104 | H208: 45691 | I208: 13:00 | J208: ATT | K208: 43 | L208: CLOSED | M208: 6.1 | N208: GP | O208: LE7 2BC | P208: =IF(AND(ISNUMBER(K208),K208>=0),K208,IF(ISNUMBER(M208),ROUND(M208*7,0),"")) -> 43 | Q208: =IF(ISTEXT(K208),"TEXT - recovered",IF(K208<0,"NEGATIVE",IF(K208>728,">104 WEEKS","OK"))) -> OK | R208: =IF(E208="GEN","GM",E208) -> GS
A209: APT-100208 | B209: 4829173650 | C209: CARTER | D209: 32118 | E209: URO | F209: C-1022 | G209: CL-108 | H209: 45691 | I209: 13:30 | J209: ATT | K209: 35 | L209: CLOSED | M209: 5 | N209: GP | O209: NG8 7XY | P209: =IF(AND(ISNUMBER(K209),K209>=0),K209,IF(ISNUMBER(M209),ROUND(M209*7,0),"")) -> 35 | Q209: =IF(ISTEXT(K209),"TEXT - recovered",IF(K209<0,"NEGATIVE",IF(K209>728,">104 WEEKS","OK"))) -> OK | R209: =IF(E209="GEN","GM",E209) -> URO
A210: APT-100209 | B210: 9273618450 | C210: LEE | D210: 17626 | E210: GS | F210: C-1028 | G210: CL-104 | H210: 45691 | I210: 14:00 | J210: ATT | K210: 35 | L210: CLOSED | M210: 5 | N210: GP | O210: LE2 5VW | P210: =IF(AND(ISNUMBER(K210),K210>=0),K210,IF(ISNUMBER(M210),ROUND(M210*7,0),"")) -> 35 | Q210: =IF(ISTEXT(K210),"TEXT - recovered",IF(K210<0,"NEGATIVE",IF(K210>728,">104 WEEKS","OK"))) -> OK | R210: =IF(E210="GEN","GM",E210) -> GS
A211: APT-100210 | B211: 5183627490 | C211: TURNER | D211: 30210 | E211: CS | F211: C-1017 | G211: CL-102 | H211: 45691 | I211: 14:30 | J211: ATT | K211: 79 | L211: CLOSED | M211: 11.3 | N211: CONS | O211: LE1 6FG | P211: =IF(AND(ISNUMBER(K211),K211>=0),K211,IF(ISNUMBER(M211),ROUND(M211*7,0),"")) -> 79 | Q211: =IF(ISTEXT(K211),"TEXT - recovered",IF(K211<0,"NEGATIVE",IF(K211>728,">104 WEEKS","OK"))) -> OK | R211: =IF(E211="GEN","GM",E211) -> CS
A212: APT-100211 | B212: 1938472605 | C212: GONZALEZ | D212: 22526 | E212: EM | F212: C-1009 | G212: CL-106 | H212: 45692 | I212: 09:00 | J212: ATT | K212: 23 | L212: OPEN | M212: 3.3 | N212: ED | O212: NG1 6TU | P212: =IF(AND(ISNUMBER(K212),K212>=0),K212,IF(ISNUMBER(M212),ROUND(M212*7,0),"")) -> 23 | Q212: =IF(ISTEXT(K212),"TEXT - recovered",IF(K212<0,"NEGATIVE",IF(K212>728,">104 WEEKS","OK"))) -> OK | R212: =IF(E212="GEN","GM",E212) -> EM
A213: APT-100212 | B213: 6374829015 | C213: WEST | D213: 22860 | E213: EM | F213: C-1009 | G213: CL-106 | H213: 45692 | I213: 09:30 | J213: CAN | K213: 12 | L213: OPEN | M213: 1.7 | N213: ED | O213: NG1 7DE | P213: =IF(AND(ISNUMBER(K213),K213>=0),K213,IF(ISNUMBER(M213),ROUND(M213*7,0),"")) -> 12 | Q213: =IF(ISTEXT(K213),"TEXT - recovered",IF(K213<0,"NEGATIVE",IF(K213>728,">104 WEEKS","OK"))) -> OK | R213: =IF(E213="GEN","GM",E213) -> EM
A214: APT-100213 | B214: 4938271560 | C214: HENRY | D214: 22681 | E214: RHE | F214: C-1015 | G214: CL-110 | H214: 45692 | I214: 10:00 | J214: ATT | K214: 114 | L214: CLOSED | M214: 16.3 | N214: GP | O214: NG2 9ZA | P214: =IF(AND(ISNUMBER(K214),K214>=0),K214,IF(ISNUMBER(M214),ROUND(M214*7,0),"")) -> 114 | Q214: =IF(ISTEXT(K214),"TEXT - recovered",IF(K214<0,"NEGATIVE",IF(K214>728,">104 WEEKS","OK"))) -> OK | R214: =IF(E214="GEN","GM",E214) -> RHE
... A362: APT-100361 | B362: 3248153249 | C362: ODUYA | D362: 32422 | E362: CS | F362: C-1017 | G362: CL-102 | H362: 45712 | I362: 09:00 | J362: ATT | K362: 94 | L362: CLOSED | M362: 13.4 | N362: CONS | O362: LE7 2BC | P362: =IF(AND(ISNUMBER(K362),K362>=0),K362,IF(ISNUMBER(M362),ROUND(M362*7,0),"")) -> 94 | Q362: =IF(ISTEXT(K362),"TEXT - recovered",IF(K362<0,"NEGATIVE",IF(K362>728,">104 WEEKS","OK"))) -> OK | R362: =IF(E362="GEN","GM",E362) -> CS
A363: APT-100362 | B363: 0721302594 | C363: LEE | D363: 18818 | E363: URO | F363: C-1022 | G363: CL-108 | H363: 45734 | I363: 10:00 | J363: ATT | K363: ATT | L363: CLOSED | M363: 56.4 | N363: CONS | O363: NG4 3ZA | P363: =IF(AND(ISNUMBER(K363),K363>=0),K363,IF(ISNUMBER(M363),ROUND(M363*7,0),"")) -> 395 | Q363: =IF(ISTEXT(K363),"TEXT - recovered",IF(K363<0,"NEGATIVE",IF(K363>728,">104 WEEKS","OK"))) -> TEXT - recovered | R363: =IF(E363="GEN","GM",E363) -> URO
A364: APT-100363 | B364: 9750998642 | C364: MORGAN | D364: 21035 | E364: GM | F364: C-1042 | G364: CL-101 | H364: 45723 | I364: 14:30 | J364: ATT | K364: 23 | L364: CLOSED | M364: 3.3 | N364: ED | O364: NG6 5JK | P364: =IF(AND(ISNUMBER(K364),K364>=0),K364,IF(ISNUMBER(M364),ROUND(M364*7,0),"")) -> 23 | Q364: =IF(ISTEXT(K364),"TEXT - recovered",IF(K364<0,"NEGATIVE",IF(K364>728,">104 WEEKS","OK"))) -> OK | R364: =IF(E364="GEN","GM",E364) -> GM
A365: APT-100364 | B365: 6250508717 | C365: COOPER | D365: 35898 | E365: RHE | F365: C-1015 | G365: CL-110 | H365: 45726 | I365: 09:00 | J365: ATT | K365: 116 | L365: CLOSED | M365: 16.6 | N365: GP | O365: NG6 5JK | P365: =IF(AND(ISNUMBER(K365),K365>=0),K365,IF(ISNUMBER(M365),ROUND(M365*7,0),"")) -> 116 | Q365: =IF(ISTEXT(K365),"TEXT - recovered",IF(K365<0,"NEGATIVE",IF(K365>728,">104 WEEKS","OK"))) -> OK | R365: =IF(E365="GEN","GM",E365) -> RHE
A366: APT-100365 | B366: 8363207002 | C366: COOPER | D366: 27067 | E366: CS | F366: C-1017 | G366: CL-102 | H366: 45727 | I366: 14:00 | J366: ATT | K366: 58 | L366: CLOSED | M366: 8.3 | N366: GP | O366: NG8 6PQ | P366: =IF(AND(ISNUMBER(K366),K366>=0),K366,IF(ISNUMBER(M366),ROUND(M366*7,0),"")) -> 58 | Q366: =IF(ISTEXT(K366),"TEXT - recovered",IF(K366<0,"NEGATIVE",IF(K366>728,">104 WEEKS","OK"))) -> OK | R366: =IF(E366="GEN","GM",E366) -> CS
A367: APT-100366 | B367: 5626794051 | C367: GREEN | D367: 26865 | E367: EM | F367: C-1009 | G367: CL-106 | H367: 45719 | I367: 10:00 | J367: ATT | K367: 93 | L367: CLOSED | M367: 13.3 | N367: GP | O367: NG2 1TU | P367: =IF(AND(ISNUMBER(K367),K367>=0),K367,IF(ISNUMBER(M367),ROUND(M367*7,0),"")) -> 93 | Q367: =IF(ISTEXT(K367),"TEXT - recovered",IF(K367<0,"NEGATIVE",IF(K367>728,">104 WEEKS","OK"))) -> OK | R367: =IF(E367="GEN","GM",E367) -> EM
A368: APT-100367 | B368: 6758287448 | C368: CLARK | D368: 31934 | E368: RS | F368: C-1051 | G368: CL-105 | H368: 45715 | I368: 10:30 | J368: ATT | K368: 15 | L368: CLOSED | M368: 2.1 | N368: GP | O368: NG2 4TU | P368: =IF(AND(ISNUMBER(K368),K368>=0),K368,IF(ISNUMBER(M368),ROUND(M368*7,0),"")) -> 15 | Q368: =IF(ISTEXT(K368),"TEXT - recovered",IF(K368<0,"NEGATIVE",IF(K368>728,">104 WEEKS","OK"))) -> OK | R368: =IF(E368="GEN","GM",E368) -> RS
A369: APT-100368 | B369: 6986102946 | C369: MORGAN | D369: 35951 | E369: GM | F369: C-1042 | G369: CL-101 | H369: 45733 | I369: 09:30 | J369: ATT | K369: 97 | L369: CLOSED | M369: 13.9 | N369: GP | O369: LE7 2BC | P369: =IF(AND(ISNUMBER(K369),K369>=0),K369,IF(ISNUMBER(M369),ROUND(M369*7,0),"")) -> 97 | Q369: =IF(ISTEXT(K369),"TEXT - recovered",IF(K369<0,"NEGATIVE",IF(K369>728,">104 WEEKS","OK"))) -> OK | R369: =IF(E369="GEN","GM",E369) -> GM
A370: APT-100369 | B370: 1312841340 | C370: LEE | D370: 25619 | E370: RS | F370: C-1051 | G370: CL-105 | H370: 45734 | I370: 14:30 | J370: ATT | K370: ATT | L370: CLOSED | M370: 28 | N370: GP | O370: LE5 0RS | P370: =IF(AND(ISNUMBER(K370),K370>=0),K370,IF(ISNUMBER(M370),ROUND(M370*7,0),"")) -> 196 | Q370: =IF(ISTEXT(K370),"TEXT - recovered",IF(K370<0,"NEGATIVE",IF(K370>728,">104 WEEKS","OK"))) -> TEXT - recovered | R370: =IF(E370="GEN","GM",E370) -> RS
A371: APT-100370 | B371: 6350521955 | C371: OSEI | D371: 16387 | E371: OPH | F371: C-1037 | G371: CL-109 | H371: 45722 | I371: 09:30 | J371: ATT | K371: 100 | L371: CLOSED | M371: 14.3 | N371: CONS | O371: LE9 4LM | P371: =IF(AND(ISNUMBER(K371),K371>=0),K371,IF(ISNUMBER(M371),ROUND(M371*7,0),"")) -> 100 | Q371: =IF(ISTEXT(K371),"TEXT - recovered",IF(K371<0,"NEGATIVE",IF(K371>728,">104 WEEKS","OK"))) -> OK | R371: =IF(E371="GEN","GM",E371) -> OPH
A372: APT-100371 | B372: 3134797032 | C372: MENSAH | D372: 16935 | E372: EM | F372: C-1009 | G372: CL-106 | H372: 45737 | I372: 13:00 | J372: ATT | K372: 37 | L372: CLOSED | M372: 5.3 | N372: GP | O372: LE6 1XY | P372: =IF(AND(ISNUMBER(K372),K372>=0),K372,IF(ISNUMBER(M372),ROUND(M372*7,0),"")) -> 37 | Q372: =IF(ISTEXT(K372),"TEXT - recovered",IF(K372<0,"NEGATIVE",IF(K372>728,">104 WEEKS","OK"))) -> OK | R372: =IF(E372="GEN","GM",E372) -> EM
A373: APT-100372 | B373: 4684168512 | C373: BELL | D373: 24359 | E373: EM | F373: C-1009 | G373: CL-106 | H373: 45715 | I373: 11:00 | J373: ATT | K373: 38 | L373: CLOSED | M373: 5.4 | N373: GP | O373: NG7 4EF | P373: =IF(AND(ISNUMBER(K373),K373>=0),K373,IF(ISNUMBER(M373),ROUND(M373*7,0),"")) -> 38 | Q373: =IF(ISTEXT(K373),"TEXT - recovered",IF(K373<0,"NEGATIVE",IF(K373>728,">104 WEEKS","OK"))) -> OK | R373: =IF(E373="GEN","GM",E373) -> EM
A374: APT-100373 | B374: 0955310018 | C374: IBRAHIM | D374: 28748 | E374: URO | F374: C-1022 | G374: CL-108 | H374: 45734 | I374: 14:30 | J374: CAN | K374: 84 | L374: OPEN | M374: 12 | N374: GP | O374: LE8 3HI | P374: =IF(AND(ISNUMBER(K374),K374>=0),K374,IF(ISNUMBER(M374),ROUND(M374*7,0),"")) -> 84 | Q374: =IF(ISTEXT(K374),"TEXT - recovered",IF(K374<0,"NEGATIVE",IF(K374>728,">104 WEEKS","OK"))) -> OK | R374: =IF(E374="GEN","GM",E374) -> URO
A375: APT-100374 | B375: 7913278731 | C375: BELL | D375: 23956 | E375: GYN | F375: C-1044 | G375: CL-107 | H375: 45712 | I375: 13:00 | J375: ATT | K375: 116 | L375: CLOSED | M375: 16.6 | N375: GP | O375: LE2 7GH | P375: =IF(AND(ISNUMBER(K375),K375>=0),K375,IF(ISNUMBER(M375),ROUND(M375*7,0),"")) -> 116 | Q375: =IF(ISTEXT(K375),"TEXT - recovered",IF(K375<0,"NEGATIVE",IF(K375>728,">104 WEEKS","OK"))) -> OK | R375: =IF(E375="GEN","GM",E375) -> GYN
A376: APT-100375 | B376: 3961559484 | C376: CLARK | D376: 33649 | E376: RHE | F376: C-1015 | G376: CL-110 | H376: 45727 | I376: 09:00 | J376: ATT | K376: ATT | L376: CLOSED | M376: 38.9 | N376: GP | O376: NG2 4TU | P376: =IF(AND(ISNUMBER(K376),K376>=0),K376,IF(ISNUMBER(M376),ROUND(M376*7,0),"")) -> 272 | Q376: =IF(ISTEXT(K376),"TEXT - recovered",IF(K376<0,"NEGATIVE",IF(K376>728,">104 WEEKS","OK"))) -> TEXT - recovered | R376: =IF(E376="GEN","GM",E376) -> RHE
A377: APT-100376 | B377: 5754483554 | C377: STEWART | D377: 14623 | E377: RS | F377: C-1051 | G377: CL-105 | H377: 45730 | I377: 14:00 | J377: ATT | K377: 85 | L377: CLOSED | M377: 12.1 | N377: GP | O377: NG2 1TU | P377: =IF(AND(ISNUMBER(K377),K377>=0),K377,IF(ISNUMBER(M377),ROUND(M377*7,0),"")) -> 85 | Q377: =IF(ISTEXT(K377),"TEXT - recovered",IF(K377<0,"NEGATIVE",IF(K377>728,">104 WEEKS","OK"))) -> OK | R377: =IF(E377="GEN","GM",E377) -> RS
A378: APT-100377 | B378: 4781076894 | C378: OKAFOR | D378: 36810 | E378: EM | F378: C-1009 | G378: CL-106 | H378: 45715 | I378: 14:00 | J378: ATT | K378: 35 | L378: CLOSED | M378: 5 | N378: GP | O378: LE8 3HI | P378: =IF(AND(ISNUMBER(K378),K378>=0),K378,IF(ISNUMBER(M378),ROUND(M378*7,0),"")) -> 35 | Q378: =IF(ISTEXT(K378),"TEXT - recovered",IF(K378<0,"NEGATIVE",IF(K378>728,">104 WEEKS","OK"))) -> OK | R378: =IF(E378="GEN","GM",E378) -> EM
A379: APT-100378 | B379: 1010984224 | C379: MORGAN | D379: 18130 | E379: EM | F379: C-1009 | G379: CL-106 | H379: 45719 | I379: 11:00 | J379: ATT | K379: 41 | L379: CLOSED | M379: 5.9 | N379: ED | O379: LE5 0RS | P379: =IF(AND(ISNUMBER(K379),K379>=0),K379,IF(ISNUMBER(M379),ROUND(M379*7,0),"")) -> 41 | Q379: =IF(ISTEXT(K379),"TEXT - recovered",IF(K379<0,"NEGATIVE",IF(K379>728,">104 WEEKS","OK"))) -> OK | R379: =IF(E379="GEN","GM",E379) -> EM
A380: APT-100379 | B380: 0834716663 | C380: IBRAHIM | D380: 26126 | E380: URO | F380: C-1022 | G380: CL-108 | H380: 45719 | I380: 13:30 | J380: CAN | K380: 48 | L380: OPEN | M380: 6.9 | N380: GP | O380: NG3 2VW | P380: =IF(AND(ISNUMBER(K380),K380>=0),K380,IF(ISNUMBER(M380),ROUND(M380*7,0),"")) -> 48 | Q380: =IF(ISTEXT(K380),"TEXT - recovered",IF(K380<0,"NEGATIVE",IF(K380>728,">104 WEEKS","OK"))) -> OK | R380: =IF(E380="GEN","GM",E380) -> URO
A381: APT-100380 | B381: 0991392069 | C381: ALLEN | D381: 33381 | E381: RHE | F381: C-1015 | G381: CL-110 | H381: 45715 | I381: 11:00 | J381: ATT | K381: 64 | L381: CLOSED | M381: 9.1 | N381: GP | O381: NG2 4TU | P381: =IF(AND(ISNUMBER(K381),K381>=0),K381,IF(ISNUMBER(M381),ROUND(M381*7,0),"")) -> 64 | Q381: =IF(ISTEXT(K381),"TEXT - recovered",IF(K381<0,"NEGATIVE",IF(K381>728,">104 WEEKS","OK"))) -> OK | R381: =IF(E381="GEN","GM",E381) -> RHE
A382: APT-100381 | B382: 9863138258 | C382: AHMED | D382: 29567 | E382: GYN | F382: C-1044 | G382: CL-107 | H382: 45715 | I382: 09:30 | J382: ATT | K382: 88 | L382: CLOSED | M382: 12.6 | N382: GP | O382: NG6 5JK | P382: =IF(AND(ISNUMBER(K382),K382>=0),K382,IF(ISNUMBER(M382),ROUND(M382*7,0),"")) -> 88 | Q382: =IF(ISTEXT(K382),"TEXT - recovered",IF(K382<0,"NEGATIVE",IF(K382>728,">104 WEEKS","OK"))) -> OK | R382: =IF(E382="GEN","GM",E382) -> GYN
A383: APT-100382 | B383: 8522555809 | C383: WRIGHT | D383: 35170 | E383: GS | F383: C-1028 | G383: CL-104 | H383: 45719 | I383: 14:30 | J383: ATT | K383: 108 | L383: CLOSED | M383: 15.4 | N383: SELF | O383: LE7 2BC | P383: =IF(AND(ISNUMBER(K383),K383>=0),K383,IF(ISNUMBER(M383),ROUND(M383*7,0),"")) -> 108 | Q383: =IF(ISTEXT(K383),"TEXT - recovered",IF(K383<0,"NEGATIVE",IF(K383>728,">104 WEEKS","OK"))) -> OK | R383: =IF(E383="GEN","GM",E383) -> GS
A384: APT-100383 | B384: 7747198282 | C384: COOK | D384: 15874 | E384: RHE | F384: C-1015 | G384: CL-110 | H384: 45734 | I384: 10:00 | J384: ATT | K384: 27 | L384: CLOSED | M384: 3.9 | N384: GP | O384: NG1 5KL | P384: =IF(AND(ISNUMBER(K384),K384>=0),K384,IF(ISNUMBER(M384),ROUND(M384*7,0),"")) -> 27 | Q384: =IF(ISTEXT(K384),"TEXT - recovered",IF(K384<0,"NEGATIVE",IF(K384>728,">104 WEEKS","OK"))) -> OK | R384: =IF(E384="GEN","GM",E384) -> RHE
A385: APT-100384 | B385: 9350491322 | C385: MORGAN | D385: 16565 | E385: GM | F385: C-1042 | G385: CL-101 | H385: 45734 | I385: 11:00 | J385: ATT | K385: 22 | L385: CLOSED | M385: 3.1 | N385: GP | O385: LE8 3HI | P385: =IF(AND(ISNUMBER(K385),K385>=0),K385,IF(ISNUMBER(M385),ROUND(M385*7,0),"")) -> 22 | Q385: =IF(ISTEXT(K385),"TEXT - recovered",IF(K385<0,"NEGATIVE",IF(K385>728,">104 WEEKS","OK"))) -> OK | R385: =IF(E385="GEN","GM",E385) -> GM
A386: APT-100385 | B386: 1696910696 | C386: CLARK | D386: 16180 | E386: GM | F386: C-1042 | G386: CL-101 | H386: 45736 | I386: 11:30 | J386: ATT | K386: 105 | L386: CLOSED | M386: 15 | N386: GP | O386: LE1 3RS | P386: =IF(AND(ISNUMBER(K386),K386>=0),K386,IF(ISNUMBER(M386),ROUND(M386*7,0),"")) -> 105 | Q386: =IF(ISTEXT(K386),"TEXT - recovered",IF(K386<0,"NEGATIVE",IF(K386>728,">104 WEEKS","OK"))) -> OK | R386: =IF(E386="GEN","GM",E386) -> GM
A387: APT-100386 | B387: 5597606837 | C387: ROGERS | D387: 24066 | E387: URO | F387: C-1022 | G387: CL-108 | H387: 45715 | I387: 10:00 | J387: CAN | K387: 69 | L387: OPEN | M387: 9.9 | N387: GP | O387: NG1 5KL | P387: =IF(AND(ISNUMBER(K387),K387>=0),K387,IF(ISNUMBER(M387),ROUND(M387*7,0),"")) -> 69 | Q387: =IF(ISTEXT(K387),"TEXT - recovered",IF(K387<0,"NEGATIVE",IF(K387>728,">104 WEEKS","OK"))) -> OK | R387: =IF(E387="GEN","GM",E387) -> URO
A388: APT-100387 | B388: 7617528613 | C388: DAVIES | D388: 16561 | E388: GM | F388: C-1042 | G388: CL-101 | H388: 45713 | I388: 09:30 | J388: ATT | K388: 117 | L388: CLOSED | M388: 16.7 | N388: GP | O388: LE7 2BC | P388: =IF(AND(ISNUMBER(K388),K388>=0),K388,IF(ISNUMBER(M388),ROUND(M388*7,0),"")) -> 117 | Q388: =IF(ISTEXT(K388),"TEXT - recovered",IF(K388<0,"NEGATIVE",IF(K388>728,">104 WEEKS","OK"))) -> OK | R388: =IF(E388="GEN","GM",E388) -> GM
...

Sheet IP_Raw
A1: Episode_ID | B1: NHS_Number | C1: Patient_Surname | D1: Patient_DOB | E1: Admission_Date | F1: Admission_Type | G1: Ward_Code | H1: Specialty_Code | I1: Discharge_Date | J1: Discharge_Method | K1: Length_of_Stay | L1: Readmission_Flag | M1: HRG_Code | N1: Bed_Days | O1: Consultant_Code | P1: ICD10_Code | Q1: OPCS4_Code | R1: Specialty_Code_Clean
A2: EP-10000001 | B2: 8079359782 | C2: GONZALEZ | D2: 32717 | E2: 45725 | F2: ELEC | G2: W-02 | H2: URO | I2: 45727 | J2: HOME | K2: 2 | L2: N | M2: DD44D | N2: 2 | O2: C-1022 | P2: J45 | Q2: W41 | R2: =IF(H2="GEN","GM",H2) -> URO
A3: EP-10000002 | B3: 8705932525 | C3: MITCHELL | D3: 21626 | E3: 45601 | F3: EMER | G3: W-01 | H3: RHE | I3: 45607 | J3: HOME | K3: 6 | L3: N | M3: GG77G | N3: 6 | O3: C-1015 | P3: K57 | Q3: J21 | R3: =IF(H3="GEN","GM",H3) -> RHE
A4: EP-10000003 | B4: 4161692845 | C4: ADEYEMI | D4: 26750 | E4: 45709 | F4: EMER | G4: W-02 | H4: URO | I4: 45715 | J4: HOME | K4: 6 | L4: N | M4: KK11K | N4: 6 | O4: C-1022 | P4: M79 | Q4: M02 | R4: =IF(H4="GEN","GM",H4) -> URO
A5: EP-10000004 | B5: 2341389994 | C5: TAYLOR | D5: 34806 | E5: 45604 | F5: ELEC | G5: W-03 | H5: OPH | I5: 45605 | J5: HOME | K5: 1 | L5: N | M5: QQ66Q | N5: 1 | O5: C-1037 | P5: J44 | R5: =IF(H5="GEN","GM",H5) -> OPH
A6: EP-10000005 | B6: 4679970246 | C6: RODRIGUEZ | D6: 20327 | E6: 45664 | F6: EMER | G6: W-06 | H6: GYN | I6: 45664 | J6: ABSENT | K6: 0 | L6: Y | N6: 0 | O6: C-1044 | P6: K57 | Q6: J19 | R6: =IF(H6="GEN","GM",H6) -> GYN
A7: EP-10000006 | B7: 2268018242 | C7: ADEYEMI | D7: 27091 | E7: 45600 | F7: EMER | G7: W-03 | H7: OPH | I7: 45603 | J7: HOME | K7: 3 | L7: N | M7: EE55E | N7: 3 | O7: C-1037 | P7: I21 | Q7: W43 | R7: =IF(H7="GEN","GM",H7) -> OPH
A8: EP-10000007 | B8: 3150983930 | C8: SANCHEZ | D8: 24735 | E8: 45595 | F8: ELEC | G8: W-04 | H8: CS | I8: 45597 | J8: HOME | K8: 2 | L8: N | M8: RR77R | N8: 2 | O8: C-1017 | P8: N13 | Q8: M01 | R8: =IF(H8="GEN","GM",H8) -> CS
A9: EP-10000008 | B9: 0170127706 | C9: HARRIS | D9: 25990 | E9: 45617 | F9: ELEC | G9: W-02 | H9: GS | I9: 45619 | J9: HOME | K9: 2 | L9: N | N9: 2 | O9: C-1028 | P9: M16 | Q9: W43 | R9: =IF(H9="GEN","GM",H9) -> GS
A10: EP-10000009 | B10: 8728080100 | C10: TAYLOR | D10: 17308 | E10: 45610 | F10: ELEC | G10: W-05 | H10: RS | I10: 45615 | J10: HOME | K10: 5 | L10: N | N10: 5 | O10: C-1051 | P10: J44 | Q10: K42 | R10: =IF(H10="GEN","GM",H10) -> RS
A11: EP-10000010 | B11: 7062962015 | C11: EVANS | D11: 30108 | E11: 45688 | F11: ELEC | G11: W-02 | H11: URO | I11: 45692 | J11: HOME | K11: 4 | L11: N | M11: TT99T | N11: 4 | O11: C-1022 | P11: M79 | Q11: M03 | R11: =IF(H11="GEN","GM",H11) -> URO
A12: EP-10000011 | B12: 8281489325 | C12: MARTIN | D12: 35281 | E12: 45700 | F12: EMER | G12: W-01 | H12: EM | I12: 45706 | J12: ABSENT | K12: 6 | L12: N | M12: HH88H | N12: 6 | O12: C-1009 | P12: K92 | Q12: M01 | R12: =IF(H12="GEN","GM",H12) -> EM
A13: EP-10000012 | B13: 7234309805 | C13: PATEL | D13: 20360 | E13: 45637 | F13: EMER | G13: W-02 | H13: URO | I13: 45638 | J13: HOME | K13: 1 | L13: N | M13: PP55P | N13: 1 | O13: C-1022 | P13: C34 | Q13: K40 | R13: =IF(H13="GEN","GM",H13) -> URO
A14: EP-10000013 | B14: 1043321819 | C14: EVANS | D14: 26925 | E14: 45623 | F14: ELEC | G14: W-01 | H14: EM | I14: 45628 | J14: HOME | K14: 5 | L14: N | M14: AA11A | N14: 5 | O14: C-1009 | P14: N20 | Q14: J21 | R14: =IF(H14="GEN","GM",H14) -> EM
A15: EP-10000014 | B15: 9091334123 | C15: HASSAN | D15: 19352 | E15: 45621 | F15: EMER | G15: W-02 | H15: GS | I15: 45625 | J15: HOME | K15: 4 | L15: N | M15: PP55P | N15: 4 | O15: C-1028 | P15: M79 | Q15: E89 | R15: =IF(H15="GEN","GM",H15) -> GS
A16: EP-10000015 | B16: 6247317810 | C16: NDLOVU | D16: 33162 | E16: 45592 | F16: EMER | G16: W-01 | H16: RHE | I16: 45595 | J16: HOME | K16: 3 | L16: N | M16: KK11K | N16: 3 | O16: C-1015 | P16: N39 | Q16: M01 | R16: =IF(H16="GEN","GM",H16) -> RHE
A17: EP-10000016 | B17: 6231203875 | C17: MITCHELL | D17: 38526 | E17: 45654 | F17: EMER | G17: W-02 | H17: GS | I17: 45664 | J17: ABSENT | K17: 10 | L17: N | M17: SS88S | N17: 10 | O17: C-1028 | P17: M79 | Q17: W42 | R17: =IF(H17="GEN","GM",H17) -> GS
A18: EP-10000017 | B18: 3097289623 | C18: PATEL | D18: 36923 | E18: 45639 | F18: ELEC | G18: W-01 | H18: GM | I18: 45642 | J18: HOME | K18: 3 | L18: N | M18: SS88S | N18: 3 | O18: C-1042 | P18: K85 | Q18: J20 | R18: =IF(H18="GEN","GM",H18) -> GM
A19: EP-10000018 | B19: 0607159696 | C19: JONES | D19: 30511 | E19: 45630 | F19: TRANSFER | G19: W-01 | H19: EM | I19: 45633 | J19: HOME | K19: 3 | L19: N | M19: UU00U | N19: 3 | O19: C-1009 | P19: I50 | Q19: M02 | R19: =IF(H19="GEN","GM",H19) -> EM
A20: EP-10000019 | B20: 4994717464 | C20: IBRAHIM | D20: 18446 | E20: 45567 | F20: ELEC | G20: W-03 | H20: OR | I20: 45569 | J20: HOME | K20: 2 | L20: N | M20: QQ66Q | N20: 2 | O20: C-1033 | P20: K85 | Q20: E88 | R20: =IF(H20="GEN","GM",H20) -> OR
A21: EP-10000020 | B21: 6808760385 | C21: ODUYA | D21: 15955 | E21: 45735 | F21: ELEC | G21: W-04 | H21: CS | I21: 45737 | J21: HOME | K21: 2 | L21: N | N21: 2 | O21: C-1017 | P21: N39 | Q21: J19 | R21: =IF(H21="GEN","GM",H21) -> CS
A22: EP-10000021 | B22: 1031051834 | C22: TURNER | D22: 30360 | E22: 45696 | F22: ELEC | G22: W-01 | H22: GM | I22: 45698 | J22: HOME | K22: 2 | L22: N | M22: AA11A | N22: 2 | O22: C-1042 | P22: I50 | Q22: E87 | R22: =IF(H22="GEN","GM",H22) -> GM
A23: EP-10000022 | B23: 4262655110 | C23: MURPHY | D23: 16428 | E23: 45611 | F23: ELEC | G23: W-01 | H23: EM | I23: 45615 | J23: HOME | K23: 4 | L23: N | N23: 4 | O23: C-1009 | P23: K85 | Q23: K40 | R23: =IF(H23="GEN","GM",H23) -> EM
A24: EP-10000023 | B24: 1557924991 | C24: SMITH | D24: 16240 | E24: 45678 | F24: ELEC | G24: W-05 | H24: RS | I24: 45680 | J24: HOME | K24: 2 | L24: N | M24: EE55E | N24: 2 | O24: C-1051 | P24: I10 | Q24: K40 | R24: =IF(H24="GEN","GM",H24) -> RS
A25: EP-10000024 | B25: 3863794026 | C25: ASANTE | D25: 31308 | E25: 45697 | F25: EMER | G25: W-01 | H25: EM | I25: 45699 | J25: HOME | K25: 2 | L25: Y | M25: SS88S | N25: 2 | O25: C-1009 | P25: K85 | Q25: J18 | R25: =IF(H25="GEN","GM",H25) -> EM
A26: EP-10000025 | B26: 1541006762 | C26: NGUYEN | D26: 28281 | E26: 45681 | F26: EMER | G26: W-04 | H26: CS | I26: 45684 | J26: HOME | K26: 3 | L26: N | M26: HH88H | N26: 3 | O26: C-1017 | P26: M54 | Q26: W41 | R26: =IF(H26="GEN","GM",H26) -> CS
A27: EP-10000026 | B27: 5243106903 | C27: RICHARDSON | D27: 33780 | E27: 45637 | F27: ELEC | G27: W-03 | H27: OR | I27: 45642 | J27: HOME | K27: 5 | L27: Y | M27: AA11A | N27: 5 | O27: C-1033 | P27: M79 | Q27: J20 | R27: =IF(H27="GEN","GM",H27) -> OR
A28: EP-10000027 | B28: 3657661565 | C28: CHIRWA | D28: 38220 | E28: 45684 | F28: EMER | G28: W-01 | H28: RHE | I28: 45688 | J28: HOME | K28: 4 | L28: N | M28: EE55E | N28: 4 | O28: C-1015 | P28: J44 | Q28: W43 | R28: =IF(H28="GEN","GM",H28) -> RHE
A29: EP-10000028 | B29: 3368844431 | C29: OSEI | D29: 29228 | E29: 45658 | F29: EMER | G29: W-02 | H29: GS | I29: 45661 | J29: HOME | K29: 3 | L29: N | M29: II99I | N29: 3 | O29: C-1028 | P29: M79 | Q29: K41 | R29: =IF(H29="GEN","GM",H29) -> GS
A30: EP-10000029 | B30: 5053315869 | C30: ODUYA | D30: 24661 | E30: 45567 | F30: EMER | G30: W-02 | H30: URO | I30: 45571 | J30: HOME | K30: 4 | L30: N | M30: DD44D | N30: 4 | O30: C-1022 | P30: M54 | Q30: K42 | R30: =IF(H30="GEN","GM",H30) -> URO
A31: EP-10000030 | B31: 0504556238 | C31: CLARK | D31: 31785 | E31: 45712 | F31: ELEC | G31: W-03 | H31: OR | I31: 45713 | J31: HOME | K31: 1 | L31: N | M31: JJ00J | N31: 1 | O31: C-1033 | P31: I50 | Q31: M03 | R31: =IF(H31="GEN","GM",H31) -> OR
A32: EP-10000031 | B32: 9440640909 | C32: COOK | D32: 19659 | E32: 45682 | F32: EMER | G32: W-03 | H32: OR | I32: 45686 | J32: HOME | K32: 4 | L32: N | M32: UU00U | N32: 4 | O32: C-1033 | P32: C34 | Q32: M04 | R32: =IF(H32="GEN","GM",H32) -> OR
A33: EP-10000032 | B33: 2061632945 | C33: HARRIS | D33: 17036 | E33: 45699 | F33: ELEC | G33: W-01 | H33: GM | I33: 45701 | J33: HOME | K33: 2 | L33: N | M33: TT99T | N33: 2 | O33: C-1042 | P33: N18 | Q33: W41 | R33: =IF(H33="GEN","GM",H33) -> GM
A34: EP-10000033 | B34: 4324451076 | C34: CHIRWA | D34: 31904 | E34: 45733 | F34: ELEC | G34: W-01 | H34: GM | I34: 45734 | J34: HOME | K34: 1 | L34: N | M34: UU00U | N34: 1 | P34: K92 | Q34: E87 | R34: =IF(H34="GEN","GM",H34) -> GM
A35: EP-10000034 | B35: 3102786814 | C35: MWANGI | D35: 35195 | E35: 45624 | F35: EMER | G35: W-03 | H35: OR | I35: 45627 | J35: HOME | K35: 3 | L35: N | M35: FF66F | N35: 3 | O35: C-1033 | P35: I21 | Q35: J18 | R35: =IF(H35="GEN","GM",H35) -> OR
A36: EP-10000035 | B36: 1693406088 | C36: BROWN | D36: 24940 | E36: 45733 | F36: ELEC | G36: W-06 | H36: GYN | I36: 45736 | J36: TRANSFER | K36: 3 | L36: N | M36: RR77R | N36: 3 | O36: C-1044 | P36: J18 | Q36: M04 | R36: =IF(H36="GEN","GM",H36) -> GYN
A37: EP-10000036 | B37: 1826199062 | C37: KHAN | D37: 29697 | E37: 45667 | F37: ELEC | G37: W-05 | H37: RS | I37: 45669 | J37: HOME | K37: 2 | L37: N | M37: LL22L | N37: 2 | O37: C-1051 | P37: M17 | Q37: J19 | R37: =IF(H37="GEN","GM",H37) -> RS
A38: EP-10000037 | B38: 1051238282 | C38: AHMED | D38: 24911 | E38: 45631 | F38: EMER | G38: W-01 | H38: EM | I38: 45639 | J38: HOME | K38: 8 | L38: N | M38: PP55P | N38: 8 | O38: C-1009 | P38: M79 | Q38: K40 | R38: =IF(H38="GEN","GM",H38) -> EM
A39: EP-10000038 | B39: 9440640909 | C39: KING | D39: 27587 | E39: 45653 | F39: EMER | G39: W-02 | H39: GS | I39: 45654 | J39: HOME | K39: 1 | L39: N | M39: QQ66Q | N39: 1 | O39: C-1028 | P39: K57 | Q39: J19 | R39: =IF(H39="GEN","GM",H39) -> GS
A40: EP-10000039 | B40: 3950240268 | C40: EDWARDS | D40: 19759 | E40: 45576 | F40: EMER | G40: W-01 | H40: RHE | I40: 45584 | J40: TRANSFER | K40: 8 | L40: N | M40: RR77R | N40: 8 | O40: C-1015 | P40: K57 | Q40: W43 | R40: =IF(H40="GEN","GM",H40) -> RHE
A41: EP-10000040 | B41: 4754121267 | C41: KHAN | D41: 36324 | E41: 45568 | F41: EMER | G41: W-04 | H41: CS | I41: 45568 | J41: HOME | K41: 0 | L41: N | M41: UU00U | N41: 0 | O41: C-1017 | P41: J45 | Q41: E88 | R41: =IF(H41="GEN","GM",H41) -> CS
A42: EP-10000041 | B42: 2061632945 | C42: STEWART | D42: 29776 | E42: 45626 | F42: EMER | G42: W-02 | H42: GS | I42: 45630 | J42: TRANSFER | K42: 4 | M42: EE55E | N42: 4 | O42: C-1028 | P42: I63 | Q42: J21 | R42: =IF(H42="GEN","GM",H42) -> GS
A43: EP-10000042 | B43: 6617979688 | C43: KOFI | D43: 15161 | E43: 45651 | F43: EMER | G43: W-02 | H43: URO | I43: 45653 | J43: TRANSFER | K43: 2 | L43: N | M43: TT99T | N43: 2 | O43: C-1022 | P43: K85 | Q43: K41 | R43: =IF(H43="GEN","GM",H43) -> URO
A44: EP-10000043 | B44: 8728080100 | C44: NGUYEN | D44: 33647 | E44: 45673 | F44: EMER | G44: W-03 | H44: OR | I44: 45678 | J44: HOME | K44: 5 | L44: N | M44: MM33M | N44: 5 | O44: C-1033 | P44: N39 | Q44: E88 | R44: =IF(H44="GEN","GM",H44) -> OR
A45: EP-10000044 | B45: 2812067974 | C45: LEE | D45: 13598 | E45: 45590 | F45: ELEC | G45: W-04 | H45: CS | I45: 45591 | J45: HOME | K45: 1 | L45: N | M45: MM33M | N45: 1 | O45: C-1017 | P45: K57 | Q45: M02 | R45: =IF(H45="GEN","GM",H45) -> CS
A46: EP-10000045 | B46: 6183242102 | C46: OKAFOR | D46: 14561 | E46: 45600 | F46: EMER | G46: W-03 | H46: OPH | I46: 45613 | J46: HOME | K46: 13 | L46: N | M46: JJ00J | N46: 13 | O46: C-1037 | P46: C34 | Q46: J21 | R46: =IF(H46="GEN","GM",H46) -> OPH
A47: EP-10000046 | B47: 5852398680 | C47: ADAMS | D47: 19845 | E47: 45568 | F47: ELEC | G47: W-03 | H47: OR | I47: 45571 | J47: HOME | K47: 3 | L47: N | M47: GG77G | N47: 3 | O47: C-1033 | P47: K85 | Q47: W42 | R47: =IF(H47="GEN","GM",H47) -> OR
A48: EP-10000047 | B48: 2299590010 | C48: SANCHEZ | D48: 23134 | E48: 45638 | F48: ELEC | G48: W-01 | H48: RHE | I48: 45641 | J48: HOME | K48: 3 | L48: N | M48: UU00U | N48: 3 | O48: C-1015 | P48: J45 | Q48: K40 | R48: =IF(H48="GEN","GM",H48) -> RHE
A49: EP-10000048 | B49: 9367632016 | C49: NELSON | D49: 25285 | E49: 45653 | F49: ELEC | G49: W-04 | H49: CS | I49: 45655 | J49: HOME | K49: 2 | L49: N | M49: II99I | N49: 2 | O49: C-1017 | P49: K80 | Q49: J21 | R49: =IF(H49="GEN","GM",H49) -> CS
A50: EP-10000049 | B50: 2517785289 | C50: PATEL | D50: 18605 | E50: 45683 | F50: ELEC | G50: W-02 | H50: GS | I50: 45687 | J50: HOME | K50: 4 | L50: N | M50: SS88S | N50: 4 | O50: C-1028 | P50: M17 | Q50: K43 | R50: =IF(H50="GEN","GM",H50) -> GS
A51: EP-10000050 | B51: 4937597383 | C51: YOUNG | D51: 18009 | E51: 45628 | F51: ELEC | G51: W-05 | H51: RS | I51: 45628 | J51: HOME | K51: 0 | L51: N | M51: UU00U | N51: 0 | O51: C-1051 | P51: J45 | Q51: E85 | R51: =IF(H51="GEN","GM",H51) -> RS
A52: EP-10000051 | B52: 7889579868 | C52: MARTIN | D52: 35531 | E52: 45615 | F52: TRANSFER | G52: W-01 | H52: EM | I52: 45616 | J52: HOME | K52: 1 | L52: N | M52: TT99T | N52: 1 | O52: C-1009 | P52: I10 | Q52: K42 | R52: =IF(H52="GEN","GM",H52) -> EM
A53: EP-10000052 | B53: 9245937526 | C53: CLARK | D53: 15954 | E53: 45729 | F53: ELEC | G53: W-03 | H53: OPH | I53: 45732 | J53: HOME | K53: 3 | L53: Y | M53: MM33M | N53: 3 | P53: C34 | Q53: J21 | R53: =IF(H53="GEN","GM",H53) -> OPH
A54: EP-10000053 | B54: 0592962229 | C54: WHITE | D54: 17432 | E54: 45593 | F54: ELEC | G54: W-03 | H54: OR | I54: 45595 | J54: HOME | K54: 2 | L54: N | M54: UU00U | N54: 2 | O54: C-1033 | P54: I21 | Q54: E87 | R54: =IF(H54="GEN","GM",H54) -> OR
A55: EP-10000054 | B55: 7072867908 | C55: WILLIAMS | D55: 29853 | E55: 45584 | F55: EMER | G55: W-01 | H55: GM | I55: 45591 | J55: HOME | K55: 7 | L55: N | M55: TT99T | N55: 7 | O55: C-1042 | P55: J44 | Q55: J21 | R55: =IF(H55="GEN","GM",H55) -> GM
A56: EP-10000055 | B56: 3761379180 | C56: ASANTE | D56: 29540 | E56: 45734 | F56: EMER | G56: W-03 | H56: OR | I56: 45736 | J56: HOME | K56: 2 | L56: N | M56: NN44N | N56: 2 | O56: C-1033 | P56: J45 | Q56: M04 | R56: =IF(H56="GEN","GM",H56) -> OR
A57: EP-10000056 | B57: 5437993712 | C57: GREEN | D57: 29813 | E57: 45643 | F57: Elective | G57: W-01 | H57: GM | I57: 45644 | J57: HOME | K57: 1 | L57: N | M57: TT99T | N57: 1 | O57: C-1042 | P57: N18 | Q57: W40 | R57: =IF(H57="GEN","GM",H57) -> GM
A58: EP-10000057 | B58: 3556909275 | C58: SCOTT | D58: 23523 | E58: 45649 | F58: ELEC | G58: W-01 | H58: RHE | I58: 45653 | J58: HOME | K58: 4 | L58: N | M58: TT99T | N58: 4 | O58: C-1015 | P58: J18 | Q58: K42 | R58: =IF(H58="GEN","GM",H58) -> RHE
A59: EP-10000058 | B59: 2729806990 | C59: KING | D59: 13479 | E59: 45694 | F59: EMER | G59: W-01 | H59: EM | I59: 45699 | J59: ABSENT | K59: 5 | L59: N | M59: MM33M | N59: 5 | O59: C-1009 | P59: J45 | Q59: J18 | R59: =IF(H59="GEN","GM",H59) -> EM
A60: EP-10000059 | B60: 4527111161 | C60: DAVIES | D60: 31669 | E60: 45712 | F60: EMER | G60: W-03 | H60: OPH | I60: 45714 | J60: HOME | K60: 2 | L60: N | M60: NN44N | N60: 2 | O60: C-1037 | P60: I10 | Q60: E87 | R60: =IF(H60="GEN","GM",H60) -> OPH
A61: EP-10000060 | B61: 8079359782 | C61: RODRIGUEZ | D61: 29155 | E61: 45625 | F61: TRANSFER | G61: W-03 | H61: OR | I61: 45628 | J61: TRANSFER | K61: 3 | L61: N | M61: JJ00J | N61: 5 | O61: C-1033 | P61: M16 | R61: =IF(H61="GEN","GM",H61) -> OR
A62: EP-10000061 | B62: 4262655110 | C62: YOUNG | D62: 22541 | E62: 45662 | F62: EMER | G62: W-03 | H62: OR | I62: 45666 | J62: HOME | K62: 4 | L62: Y | M62: AA11A | N62: 4 | O62: C-1033 | P62: M17 | R62: =IF(H62="GEN","GM",H62) -> OR
A63: EP-10000057 | B63: 3556909275 | C63: SCOTT | D63: 23523 | E63: 45649 | F63: ELEC | G63: W-02 | H63: RHE | I63: 45653 | J63: HOME | K63: 4 | L63: N | M63: TT99T | N63: 4 | O63: C-1015 | P63: J18 | Q63: K42 | R63: =IF(H63="GEN","GM",H63) -> RHE
A64: EP-10000062 | B64: 1799042102 | C64: MORRIS | D64: 23575 | E64: 45588 | F64: TRANSFER | G64: W-01 | H64: EM | I64: 45591 | J64: TRANSFER | K64: 3 | L64: N | M64: FF66F | N64: 5 | O64: C-1009 | P64: I10 | Q64: E88 | R64: =IF(H64="GEN","GM",H64) -> EM
A65: EP-10000063 | B65: 3854678544 | C65: GONZALEZ | D65: 15654 | E65: 45653 | F65: EMER | G65: W-01 | H65: GM | I65: 45662 | J65: HOME | K65: 9 | L65: N | M65: EE55E | N65: 9 | O65: C-1042 | P65: N20 | Q65: M04 | R65: =IF(H65="GEN","GM",H65) -> GM
A66: EP-10000064 | B66: 2849877694 | C66: CHIRWA | D66: 21985 | E66: 45603 | F66: EMER | G66: W-06 | H66: GYN | I66: 45608 | J66: HOME | K66: 5 | L66: N | M66: AA11A | N66: 5 | O66: C-1044 | P66: M54 | Q66: W42 | R66: =IF(H66="GEN","GM",H66) -> GYN
A67: EP-10000065 | B67: 3761379180 | C67: GONZALEZ | D67: 19818 | E67: 45722 | F67: ELEC | G67: W-01 | H67: RHE | I67: 45723 | J67: HOME | K67: 1 | L67: N | M67: LL22L | N67: 1 | O67: C-1015 | P67: K92 | Q67: K43 | R67: =IF(H67="GEN","GM",H67) -> RHE
A68: EP-10000066 | B68: 0983584168 | C68: PATEL | D68: 25392 | E68: 45678 | F68: EMER | G68: W-04 | H68: CS | I68: 45686 | J68: HOME | K68: 8 | L68: N | M68: KK11K | N68: 8 | O68: C-1017 | P68: M79 | Q68: M04 | R68: =IF(H68="GEN","GM",H68) -> CS
A69: EP-10000067 | B69: 3150983930 | C69: ODUYA | D69: 17760 | E69: 45576 | F69: EMER | G69: W-03 | H69: OPH | I69: 45580 | J69: HOME | K69: 4 | L69: N | M69: NN44N | N69: 4 | O69: C-1037 | P69: J18 | Q69: E89 | R69: =IF(H69="GEN","GM",H69) -> OPH
A70: EP-10000068 | B70: 3561595148 | C70: ADEYEMI | D70: 17982 | E70: 45611 | F70: EMER | G70: W-06 | H70: GYN | I70: 45615 | J70: TRANSFER | K70: 4 | L70: N | M70: DD44D | N70: 4 | O70: C-1044 | P70: N39 | Q70: E88 | R70: =IF(H70="GEN","GM",H70) -> GYN
A71: EP-10000069 | B71: 8728080100 | C71: CLARK | D71: 30572 | E71: 45604 | F71: ELEC | G71: W-01 | H71: EM | I71: 45605 | J71: HOME | K71: 1 | L71: N | M71: EE55E | N71: 1 | O71: C-1009 | P71: I21 | R71: =IF(H71="GEN","GM",H71) -> EM
A72: EP-10000070 | B72: 4033173936 | C72: CHIRWA | D72: 13073 | E72: 45719 | F72: ELEC | G72: W-02 | H72: URO | I72: 45722 | J72: HOME | K72: 3 | L72: N | M72: BB22B | N72: 3 | O72: C-1022 | P72: J18 | Q72: W43 | R72: =IF(H72="GEN","GM",H72) -> URO
A73: EP-10000071 | B73: 8013267736 | C73: JACKSON | D73: 32208 | E73: 45682 | F73: EMER | G73: W-01 | H73: RHE | I73: 45688 | J73: TRANSFER | K73: 6 | L73: N | M73: CC33C | N73: 6 | O73: C-1015 | P73: N18 | Q73: W40 | R73: =IF(H73="GEN","GM",H73) -> RHE
A74: EP-10000072 | B74: 2176591803 | C74: ALLEN | D74: 22556 | E74: 45720 | F74: ELEC | G74: W-03 | H74: OPH | I74: 45726 | J74: HOME | K74: 6 | L74: N | M74: TT99T | N74: 6 | O74: C-1037 | P74: C34 | Q74: K43 | R74: =IF(H74="GEN","GM",H74) -> OPH
A75: EP-10000073 | B75: 6416052975 | C75: WALKER | D75: 12816 | E75: 45671 | F75: EMER | G75: W-02 | H75: GS | I75: 45672 | J75: HOME | K75: 1 | L75: Y | M75: SS88S | N75: 1 | O75: C-1028 | P75: I21 | Q75: W40 | R75: =IF(H75="GEN","GM",H75) -> GS
A76: EP-10000074 | B76: 5458929750 | C76: OKAFOR | D76: 20921 | E76: 45689 | F76: EMER | G76: W-02 | H76: URO | I76: 45691 | J76: TRANSFER | K76: 2 | L76: Y | M76: TT99T | N76: 2 | O76: C-1022 | P76: J45 | Q76: J21 | R76: =IF(H76="GEN","GM",H76) -> URO
A77: EP-10000075 | B77: 4034505415 | C77: BROWN | D77: 19871 | E77: 45665 | F77: ELEC | G77: W-03 | H77: OPH | I77: 45666 | J77: HOME | K77: 1 | L77: N | M77: LL22L | N77: 1 | O77: C-1037 | P77: N20 | Q77: E87 | R77: =IF(H77="GEN","GM",H77) -> OPH
A78: EP-10000076 | B78: 3150983930 | C78: HALL | D78: 17031 | E78: 45689 | F78: ELEC | G78: W-03 | H78: OPH | I78: 45693 | J78: HOME | K78: 4 | L78: N | M78: BB22B | N78: 4 | O78: C-1037 | Q78: W40 | R78: =IF(H78="GEN","GM",H78) -> OPH
A79: EP-10000077 | B79: 6767721903 | C79: EVANS | D79: 28339 | E79: 45729 | F79: ELEC | G79: W-05 | H79: RS | I79: 45734 | J79: HOME | K79: 5 | L79: N | M79: AA11A | N79: 5 | O79: C-1051 | P79: K85 | Q79: E89 | R79: =IF(H79="GEN","GM",H79) -> RS
A80: EP-10000078 | B80: 9368998094 | C80: MARTINEZ | D80: 26214 | E80: 45573 | F80: ELEC | G80: W-01 | H80: EM | I80: 45575 | J80: HOME | K80: 2 | L80: N | M80: PP55P | N80: 2 | O80: C-1009 | P80: N20 | Q80: K42 | R80: =IF(H80="GEN","GM",H80) -> EM
A81: EP-10000079 | B81: 6504773586 | C81: DAVIES | D81: 34612 | E81: 45730 | F81: ELEC | G81: W-02 | H81: URO | I81: 45734 | J81: HOME | K81: 4 | L81: N | M81: KK11K | N81: 4 | O81: C-1022 | P81: J45 | Q81: M03 | R81: =IF(H81="GEN","GM",H81) -> URO
A82: EP-10000080 | B82: 5243106903 | C82: RICHARDSON | D82: 20600 | E82: 45593 | F82: ELEC | G82: W-03 | H82: OPH | I82: 45595 | J82: HOME | K82: 2 | L82: N | M82: MM33M | N82: 2 | O82: C-1037 | P82: I50 | Q82: W43 | R82: =IF(H82="GEN","GM",H82) -> OPH
A83: EP-10000081 | B83: 9324609539 | C83: CHIRWA | D83: 23823 | E83: 45649 | F83: EMER | G83: W-02 | H83: URO | I83: 45653 | J83: ABSENT | K83: 4 | L83: N | M83: QQ66Q | N83: 4 | O83: C-1022 | P83: J18 | Q83: J18 | R83: =IF(H83="GEN","GM",H83) -> URO
A84: EP-10000082 | B84: 1168685487 | C84: AHMED | D84: 19668 | E84: 45647 | F84: EMER | G84: W-02 | H84: URO | I84: 45650 | J84: DIED | K84: 3 | L84: N | M84: UU00U | N84: 3 | O84: C-1022 | P84: K92 | Q84: M01 | R84: =IF(H84="GEN","GM",H84) -> URO
A85: EP-10000083 | B85: 7234309805 | C85: AHMED | D85: 29279 | E85: 45647 | F85: ELEC | G85: W-06 | H85: GYN | I85: 45651 | J85: HOME | K85: 4 | L85: N | M85: NN44N | N85: 4 | O85: C-1044 | Q85: M01 | R85: =IF(H85="GEN","GM",H85) -> GYN
A86: EP-10000084 | B86: 6440892687 | C86: MURPHY | D86: 19029 | E86: 45682 | F86: EMER | G86: W-01 | H86: RHE | I86: 45686 | J86: HOME | K86: 4 | L86: N | M86: RR77R | N86: 4 | O86: C-1015 | P86: K85 | Q86: W43 | R86: =IF(H86="GEN","GM",H86) -> RHE
A87: EP-10000085 | B87: 5932133480 | C87: STEWART | D87: 18187 | E87: 45637 | F87: TRANSFER | G87: W-03 | H87: OPH | I87: 45641 | J87: HOME | K87: 4 | L87: Y | M87: TT99T | N87: 4 | O87: C-1037 | P87: J18 | R87: =IF(H87="GEN","GM",H87) -> OPH
A88: EP-10000086 | B88: 7406403910 | C88: ASANTE | D88: 28318 | E88: 45718 | F88: TRANSFER | G88: W-05 | H88: RS | I88: 45724 | J88: HOME | K88: 6 | L88: N | M88: UU00U | N88: 7 | O88: C-1051 | P88: K80 | Q88: M01 | R88: =IF(H88="GEN","GM",H88) -> RS
A89: EP-10000087 | B89: 4966319314 | C89: GONZALEZ | D89: 25689 | E89: 45610 | F89: EMER | G89: W-03 | H89: OR | I89: 45612 | J89: TRANSFER | K89: 2 | L89: N | M89: EE55E | N89: 2 | O89: C-1033 | P89: M54 | Q89: J20 | R89: =IF(H89="GEN","GM",H89) -> OR
A90: EP-10000088 | B90: 0504556238 | C90: ASANTE | D90: 28876 | E90: 45702 | F90: ELEC | G90: W-01 | H90: GM | I90: 45703 | J90: HOME | K90: 1 | L90: N | M90: KK11K | N90: 1 | O90: C-1042 | P90: J18 | Q90: W40 | R90: =IF(H90="GEN","GM",H90) -> GM
A91: EP-10000089 | B91: 4437575844 | C91: BAKER | D91: 28254 | E91: 45716 | F91: EMER | G91: W-02 | H91: URO | I91: 45722 | J91: ABSENT | K91: 6 | M91: NN44N | N91: 6 | O91: C-1022 | P91: M16 | Q91: M03 | R91: =IF(H91="GEN","GM",H91) -> URO
A92: EP-10000090 | B92: 2278248963 | C92: OKAFOR | D92: 16822 | E92: 45720 | F92: EMER | G92: W-04 | H92: CS | I92: 45722 | J92: HOME | K92: 2 | L92: N | M92: CC33C | N92: 2 | O92: C-1017 | P92: M17 | Q92: W42 | R92: =IF(H92="GEN","GM",H92) -> CS
A93: EP-10000091 | B93: 2499856984 | C93: CLARK | D93: 16217 | E93: 45583 | F93: ELEC | G93: W-01 | H93: GM | I93: 45585 | J93: HOME | K93: 2 | L93: N | M93: PP55P | N93: 2 | O93: C-1042 | P93: M16 | Q93: E85 | R93: =IF(H93="GEN","GM",H93) -> GM
A94: EP-10000092 | B94: 2400499154 | C94: WILSON | D94: 35875 | E94: 45666 | F94: EMER | G94: W-05 | H94: RS | I94: 45670 | J94: HOME | K94: 4 | L94: N | M94: AA11A | N94: 4 | O94: C-1051 | P94: C34 | Q94: W40 | R94: =IF(H94="GEN","GM",H94) -> RS
A95: EP-10000093 | B95: 1124903521 | C95: MITCHELL | D95: 31433 | E95: 45586 | F95: TRANSFER | G95: W-01 | H95: EM | I95: 45594 | J95: HOME | K95: 8 | L95: N | M95: DD44D | N95: 8 | O95: C-1009 | P95: I10 | Q95: K43 | R95: =IF(H95="GEN","GM",H95) -> EM
A96: EP-10000094 | B96: 5314737996 | C96: KHAN | D96: 21574 | E96: 45644 | F96: TRANSFER | G96: W-06 | H96: GYN | I96: 45649 | J96: DIED | K96: 5 | L96: N | M96: GG77G | N96: 5 | O96: C-1044 | P96: I63 | Q96: M03 | R96: =IF(H96="GEN","GM",H96) -> GYN
A97: EP-10000095 | B97: 1714677418 | C97: KING | D97: 16095 | E97: 45628 | F97: ELEC | G97: W-02 | H97: URO | I97: 45631 | J97: HOME | K97: 3 | L97: N | M97: DD44D | N97: 3 | O97: C-1022 | P97: N13 | Q97: M04 | R97: =IF(H97="GEN","GM",H97) -> URO
A98: EP-10000096 | B98: 0698720506 | C98: REED | D98: 27812 | E98: 45651 | F98: EMER | G98: W-02 | H98: GS | I98: 45652 | J98: HOME | K98: 1 | L98: N | M98: UU00U | N98: 1 | O98: C-1028 | P98: J44 | Q98: K40 | R98: =IF(H98="GEN","GM",H98) -> GS
A99: EP-10000097 | C99: EVANS | D99: 26137 | E99: 45681 | F99: EMER | G99: W-02 | H99: GS | I99: 45684 | J99: HOME | K99: 3 | L99: N | M99: LL22L | N99: 3 | O99: C-1028 | P99: K85 | Q99: J19 | R99: =IF(H99="GEN","GM",H99) -> GS
A100: EP-10000098 | B100: 0170127706 | C100: COLLINS | D100: 38238 | E100: 45687 | F100: EMER | G100: W-01 | H100: GM | I100: 45691 | J100: HOME | K100: 4 | L100: N | M100: PP55P | N100: 4 | O100: C-1042 | P100: J18 | Q100: J21 | R100: =IF(H100="GEN","GM",H100) -> GM
...

Sheet ED_Raw
A1: Attendance_ID | B1: NHS_Number | C1: Patient_Surname | D1: Patient_DOB | E1: Arrival_Date | F1: Arrival_Time | G1: Triage_Category | H1: Seen_by_Clinician_Time | I1: Departure_Time | J1: Departure_Code | K1: Four_Hour_Breach | L1: Total_ED_Time_Minutes | M1: Chief_Complaint | N1: Specialty_Referred | O1: Calc_ED_Minutes | P1: Duplicate_Flag | Q1: Calc_Breach
A2: ED-7000001 | B2: 2961112422 | C2: MENSAH | D2: 34548 | E2: 45619 | F2: 11:47 | G2: 3 | H2: 12:37 | I2: 15:14 | J2: DISC | K2: N | L2: 207 | M2: Fall | N2: NONE | O2: =IF(I2="","",ROUND(MOD(TIMEVALUE(I2)-TIMEVALUE(F2),1)*1440,0)) -> 207 | P2: =IF(COUNTIF($A$2:A2,A2)>1,"DUP","") | Q2: =IF(O2="","",IF(O2>240,"Y","N")) -> N
A3: ED-7000002 | B3: 6881973699 | C3: CAMPBELL | D3: 31325 | E3: 45646 | F3: 23:07 | G3: 4 | H3: 01:32 | I3: 02:29 | J3: DISC | K3: N | L3: 202 | M3: abdominal pain | N3: NONE | O3: =IF(I3="","",ROUND(MOD(TIMEVALUE(I3)-TIMEVALUE(F3),1)*1440,0)) -> 202 | P3: =IF(COUNTIF($A$2:A3,A3)>1,"DUP","") | Q3: =IF(O3="","",IF(O3>240,"Y","N")) -> N
A4: ED-7000003 | B4: 5801030738 | C4: RIVERA | D4: 26674 | E4: 45568 | F4: 16:29 | G4: 5 | H4: 19:13 | I4: 17:03 | J4: LEFT | K4: N | L4: 34 | M4: CHEST PAIN | N4: NONE | O4: =IF(I4="","",ROUND(MOD(TIMEVALUE(I4)-TIMEVALUE(F4),1)*1440,0)) -> 34 | P4: =IF(COUNTIF($A$2:A4,A4)>1,"DUP","") | Q4: =IF(O4="","",IF(O4>240,"Y","N")) -> N
A5: ED-7000004 | B5: 5054324636 | C5: HALL | D5: 26644 | E5: 45614 | F5: 02:19 | G5: 3 | H5: 04:01 | I5: 03:33 | J5: DISC | K5: N | L5: 74 | M5: Overdose | N5: NONE | O5: =IF(I5="","",ROUND(MOD(TIMEVALUE(I5)-TIMEVALUE(F5),1)*1440,0)) -> 74 | P5: =IF(COUNTIF($A$2:A5,A5)>1,"DUP","") | Q5: =IF(O5="","",IF(O5>240,"Y","N")) -> N
A6: ED-7000005 | B6: 7657963974 | C6: RODRIGUEZ | D6: 30516 | E6: 45640 | F6: 22:21 | G6: 4 | H6: 23:37 | I6: 01:21 | J6: DISC | K6: N | L6: 180 | M6: Vomiting | N6: NONE | O6: =IF(I6="","",ROUND(MOD(TIMEVALUE(I6)-TIMEVALUE(F6),1)*1440,0)) -> 180 | P6: =IF(COUNTIF($A$2:A6,A6)>1,"DUP","") | Q6: =IF(O6="","",IF(O6>240,"Y","N")) -> N
A7: ED-7000006 | B7: 6519803788 | C7: KHAN | D7: 32046 | E7: 45678 | F7: 00:22 | G7: 3 | H7: 02:15 | I7: 02:26 | J7: LEFT | K7: N | L7: 124 | M7: SEIZURE | N7: NONE | O7: =IF(I7="","",ROUND(MOD(TIMEVALUE(I7)-TIMEVALUE(F7),1)*1440,0)) -> 124 | P7: =IF(COUNTIF($A$2:A7,A7)>1,"DUP","") | Q7: =IF(O7="","",IF(O7>240,"Y","N")) -> N
A8: ED-7000007 | C8: BAILEY | D8: 33673 | E8: 45711 | F8: 11:43 | G8: 3 | H8: 13:07 | I8: 14:06 | J8: DISC | K8: N | L8: 143 | M8: overdose | N8: NONE | O8: =IF(I8="","",ROUND(MOD(TIMEVALUE(I8)-TIMEVALUE(F8),1)*1440,0)) -> 143 | P8: =IF(COUNTIF($A$2:A8,A8)>1,"DUP","") | Q8: =IF(O8="","",IF(O8>240,"Y","N")) -> N
A9: ED-7000008 | B9: 3368746373 | C9: CHIRWA | D9: 31519 | E9: 45692 | F9: 03:10 | G9: 3 | H9: 03:56 | I9: 04:39 | J9: ADM | K9: N | L9: 89 | M9: vomiting | N9: GM | O9: =IF(I9="","",ROUND(MOD(TIMEVALUE(I9)-TIMEVALUE(F9),1)*1440,0)) -> 89 | P9: =IF(COUNTIF($A$2:A9,A9)>1,"DUP","") | Q9: =IF(O9="","",IF(O9>240,"Y","N")) -> N
A10: ED-7000009 | C10: HALL | D10: 23205 | E10: 45698 | F10: 22:27 | G10: 3 | H10: 23:19 | I10: 23:09 | J10: ADM | K10: N | L10: 42 | M10: Back Pain | N10: RHE | O10: =IF(I10="","",ROUND(MOD(TIMEVALUE(I10)-TIMEVALUE(F10),1)*1440,0)) -> 42 | P10: =IF(COUNTIF($A$2:A10,A10)>1,"DUP","") | Q10: =IF(O10="","",IF(O10>240,"Y","N")) -> N
A11: ED-7000010 | B11: 6745287732 | C11: JONES | D11: 28041 | E11: 45580 | F11: 06:24 | G11: 3 | H11: 07:02 | I11: 07:20 | J11: DISC | K11: N | L11: 56 | M11: Vomiting | N11: NONE | O11: =IF(I11="","",ROUND(MOD(TIMEVALUE(I11)-TIMEVALUE(F11),1)*1440,0)) -> 56 | P11: =IF(COUNTIF($A$2:A11,A11)>1,"DUP","") | Q11: =IF(O11="","",IF(O11>240,"Y","N")) -> N
A12: ED-7000011 | B12: 8020572130 | C12: ODUYA | D12: 18297 | E12: 45629 | F12: 00:42 | G12: 3 | H12: 01:11 | I12: 01:31 | J12: DISC | K12: N | L12: 49 | M12: Fall | N12: NONE | O12: =IF(I12="","",ROUND(MOD(TIMEVALUE(I12)-TIMEVALUE(F12),1)*1440,0)) -> 49 | P12: =IF(COUNTIF($A$2:A12,A12)>1,"DUP","") | Q12: =IF(O12="","",IF(O12>240,"Y","N")) -> N
A13: ED-7000012 | B13: 3566844537 | C13: PATEL | D13: 27925 | E13: 45578 | F13: 11:02 | G13: 4 | H13: 14:33 | I13: 20:40 | J13: DISC | K13: Y | L13: 578 | M13: COLLAPSE | N13: NONE | O13: =IF(I13="","",ROUND(MOD(TIMEVALUE(I13)-TIMEVALUE(F13),1)*1440,0)) -> 578 | P13: =IF(COUNTIF($A$2:A13,A13)>1,"DUP","") | Q13: =IF(O13="","",IF(O13>240,"Y","N")) -> Y
A14: ED-7000013 | B14: 5802869654 | C14: CLARK | D14: 33914 | E14: 45705 | F14: 22:23 | G14: 3 | H14: 23:16 | I14: 02:05 | J14: DISC | K14: N | L14: 222 | M14: shortness of breath | N14: NONE | O14: =IF(I14="","",ROUND(MOD(TIMEVALUE(I14)-TIMEVALUE(F14),1)*1440,0)) -> 222 | P14: =IF(COUNTIF($A$2:A14,A14)>1,"DUP","") | Q14: =IF(O14="","",IF(O14>240,"Y","N")) -> N
A15: ED-7000014 | B15: 6502459662 | C15: LEE | D15: 36157 | E15: 45617 | F15: 19:08 | G15: 2 | H15: 19:28 | I15: 02:32 | J15: DISC | K15: Y | L15: 444 | M15: seizure | N15: NONE | O15: =IF(I15="","",ROUND(MOD(TIMEVALUE(I15)-TIMEVALUE(F15),1)*1440,0)) -> 444 | P15: =IF(COUNTIF($A$2:A15,A15)>1,"DUP","") | Q15: =IF(O15="","",IF(O15>240,"Y","N")) -> Y
A16: ED-7000015 | B16: 3830288835 | C16: REED | D16: 19701 | E16: 45608 | F16: 01:46 | G16: 3 | H16: 02:28 | I16: 03:52 | J16: DISC | K16: N | L16: 126 | M16: Fall | N16: NONE | O16: =IF(I16="","",ROUND(MOD(TIMEVALUE(I16)-TIMEVALUE(F16),1)*1440,0)) -> 126 | P16: =IF(COUNTIF($A$2:A16,A16)>1,"DUP","") | Q16: =IF(O16="","",IF(O16>240,"Y","N")) -> N
A17: ED-7000016 | B17: 3647176418 | C17: WALKER | D17: 17149 | E17: 45579 | F17: 10:35 | G17: 4 | H17: 13:29 | I17: 15:25 | J17: DISC | K17: Y | L17: 290 | M17: seizure | N17: NONE | O17: =IF(I17="","",ROUND(MOD(TIMEVALUE(I17)-TIMEVALUE(F17),1)*1440,0)) -> 290 | P17: =IF(COUNTIF($A$2:A17,A17)>1,"DUP","") | Q17: =IF(O17="","",IF(O17>240,"Y","N")) -> Y
A18: ED-7000017 | B18: 0817196486 | C18: PEREZ | D18: 37236 | E18: 45654 | F18: 18:58 | G18: 4 | H18: 21:10 | I18: 20:34 | J18: DISC | K18: N | L18: 96 | M18: back pain | N18: NONE | O18: =IF(I18="","",ROUND(MOD(TIMEVALUE(I18)-TIMEVALUE(F18),1)*1440,0)) -> 96 | P18: =IF(COUNTIF($A$2:A18,A18)>1,"DUP","") | Q18: =IF(O18="","",IF(O18>240,"Y","N")) -> N
A19: ED-7000018 | B19: 1200176347 | C19: NGUYEN | D19: 14525 | E19: 45615 | F19: 3:53 PM | G19: 3 | H19: 17:32 | I19: 18:01 | J19: DIED | K19: N | L19: 128 | M19: Head Injury | N19: NONE | O19: =IF(I19="","",ROUND(MOD(TIMEVALUE(I19)-TIMEVALUE(F19),1)*1440,0)) -> 128 | P19: =IF(COUNTIF($A$2:A19,A19)>1,"DUP","") | Q19: =IF(O19="","",IF(O19>240,"Y","N")) -> N
A20: ED-7000019 | B20: 5331064224 | C20: WHITE | D20: 14777 | E20: 45699 | F20: 21:33 | G20: 3 | H20: 22:20 | I20: 22:33 | J20: DISC | K20: N | L20: 60 | M20: Abdominal Pain | N20: NONE | O20: =IF(I20="","",ROUND(MOD(TIMEVALUE(I20)-TIMEVALUE(F20),1)*1440,0)) -> 60 | P20: =IF(COUNTIF($A$2:A20,A20)>1,"DUP","") | Q20: =IF(O20="","",IF(O20>240,"Y","N")) -> N
A21: ED-7000020 | B21: 0512833004 | C21: LEE | D21: 33982 | E21: 45633 | F21: 12:13 AM | G21: 3 | H21: 02:10 | I21: 00:43 | J21: DISC | K21: N | L21: 30 | M21: Abdominal Pain | N21: NONE | O21: =IF(I21="","",ROUND(MOD(TIMEVALUE(I21)-TIMEVALUE(F21),1)*1440,0)) -> 30 | P21: =IF(COUNTIF($A$2:A21,A21)>1,"DUP","") | Q21: =IF(O21="","",IF(O21>240,"Y","N")) -> N
A22: ED-7000021 | B22: 1782327517 | C22: ADAMS | D22: 20581 | E22: 45653 | F22: 04:47 | G22: 1 | H22: 04:49 | I22: 05:30 | J22: DISC | K22: N | L22: 43 | M22: head injury | N22: NONE | O22: =IF(I22="","",ROUND(MOD(TIMEVALUE(I22)-TIMEVALUE(F22),1)*1440,0)) -> 43 | P22: =IF(COUNTIF($A$2:A22,A22)>1,"DUP","") | Q22: =IF(O22="","",IF(O22>240,"Y","N")) -> N
... A25: ED-7000024 | B25: 7854933496 | C25: CHIRWA | D25: 19613 | E25: 45673 | F25: 05:03 | G25: 4 | H25: 07:10 | I25: 14:00 | J25: DIED | K25: Y | L25: 537 | M25: fever | N25: NONE | O25: =IF(I25="","",ROUND(MOD(TIMEVALUE(I25)-TIMEVALUE(F25),1)*1440,0)) -> 537 | P25: =IF(COUNTIF($A$2:A25,A25)>1,"DUP","") | Q25: =IF(O25="","",IF(O25>240,"Y","N")) -> Y
A26: ED-7000025 | C26: CHIRWA | D26: 31648 | E26: 45605 | F26: 04:42 | G26: 4 | H26: 08:35 | I26: 05:50 | J26: LEFT | K26: N | L26: 68 | M26: PALPITATIONS | N26: NONE | O26: =IF(I26="","",ROUND(MOD(TIMEVALUE(I26)-TIMEVALUE(F26),1)*1440,0)) -> 68 | P26: =IF(COUNTIF($A$2:A26,A26)>1,"DUP","") | Q26: =IF(O26="","",IF(O26>240,"Y","N")) -> N
A27: ED-7000026 | B27: 1671103134 | C27: MWANGI | D27: 30317 | E27: 45590 | F27: 21:26 | G27: 3 | H27: 22:14 | I27: 06:55 | J27: DISC | K27: Y | L27: 569 | M27: back pain | N27: NONE | O27: =IF(I27="","",ROUND(MOD(TIMEVALUE(I27)-TIMEVALUE(F27),1)*1440,0)) -> 569 | P27: =IF(COUNTIF($A$2:A27,A27)>1,"DUP","") | Q27: =IF(O27="","",IF(O27>240,"Y","N")) -> Y
A28: ED-7000027 | B28: 1192742786 | C28: ROGERS | D28: 36132 | E28: 45615 | F28: 02:22 | G28: 1 | H28: 02:24 | I28: 03:05 | J28: ADM | K28: N | L28: 43 | M28: abdominal pain | N28: CS | O28: =IF(I28="","",ROUND(MOD(TIMEVALUE(I28)-TIMEVALUE(F28),1)*1440,0)) -> 43 | P28: =IF(COUNTIF($A$2:A28,A28)>1,"DUP","") | Q28: =IF(O28="","",IF(O28>240,"Y","N")) -> N
A29: ED-7000028 | B29: 1062069153 | C29: PARKER | D29: 15864 | E29: 45641 | F29: 09:35 | G29: 3 | I29: 10:52 | J29: DISC | K29: N | L29: 77 | M29: FRACTURE | N29: NONE | O29: =IF(I29="","",ROUND(MOD(TIMEVALUE(I29)-TIMEVALUE(F29),1)*1440,0)) -> 77 | P29: =IF(COUNTIF($A$2:A29,A29)>1,"DUP","") | Q29: =IF(O29="","",IF(O29>240,"Y","N")) -> N
A30: ED-7000029 | B30: 6312789138 | C30: GONZALEZ | D30: 21786 | E30: 45577 | F30: 12:53 | G30: 3 | H30: 14:43 | I30: 20:41 | J30: DISC | K30: Y | L30: 468 | M30: SEIZURE | N30: NONE | O30: =IF(I30="","",ROUND(MOD(TIMEVALUE(I30)-TIMEVALUE(F30),1)*1440,0)) -> 468 | P30: =IF(COUNTIF($A$2:A30,A30)>1,"DUP","") | Q30: =IF(O30="","",IF(O30>240,"Y","N")) -> Y
A31: ED-7000030 | C31: CHIRWA | D31: 24639 | E31: 45570 | F31: 02:05 | G31: 4 | H31: 04:24 | I31: 04:15 | J31: DISC | K31: N | L31: 130 | M31: Head Injury | N31: NONE | O31: =IF(I31="","",ROUND(MOD(TIMEVALUE(I31)-TIMEVALUE(F31),1)*1440,0)) -> 130 | P31: =IF(COUNTIF($A$2:A31,A31)>1,"DUP","") | Q31: =IF(O31="","",IF(O31>240,"Y","N")) -> N
A32: ED-7000031 | B32: 3250026805 | C32: HARRIS | D32: 15672 | E32: 45714 | F32: 04:15 | G32: 3 | H32: 05:05 | I32: 04:50 | J32: DISC | K32: N | L32: 35 | M32: head injury | N32: NONE | O32: =IF(I32="","",ROUND(MOD(TIMEVALUE(I32)-TIMEVALUE(F32),1)*1440,0)) -> 35 | P32: =IF(COUNTIF($A$2:A32,A32)>1,"DUP","") | Q32: =IF(O32="","",IF(O32>240,"Y","N")) -> N
A33: ED-7000032 | B33: 5259077982 | C33: NELSON | D33: 34046 | E33: 45693 | F33: 03:25 | G33: 3 | H33: 03:47 | I33: 05:29 | J33: DISC | K33: N | L33: 124 | M33: COLLAPSE | N33: N/A | O33: =IF(I33="","",ROUND(MOD(TIMEVALUE(I33)-TIMEVALUE(F33),1)*1440,0)) -> 124 | P33: =IF(COUNTIF($A$2:A33,A33)>1,"DUP","") | Q33: =IF(O33="","",IF(O33>240,"Y","N")) -> N
A34: ED-7000033 | B34: 9687897192 | C34: HERNANDEZ | D34: 30353 | E34: 45620 | F34: 23:00 | G34: 3 | H34: 00:24 | I34: 01:45 | J34: ADM | K34: N | L34: 165 | M34: Stroke Symptoms | N34: RHE | O34: =IF(I34="","",ROUND(MOD(TIMEVALUE(I34)-TIMEVALUE(F34),1)*1440,0)) -> 165 | P34: =IF(COUNTIF($A$2:A34,A34)>1,"DUP","") | Q34: =IF(O34="","",IF(O34>240,"Y","N")) -> N
A35: ED-7000034 | B35: 6649561827 | C35: NDLOVU | D35: 22746 | E35: 45654 | F35: 05:42 | G35: 3 | H35: 06:40 | I35: 09:07 | J35: DISC | K35: N | L35: 205 | M35: STROKE | N35: NONE | O35: =IF(I35="","",ROUND(MOD(TIMEVALUE(I35)-TIMEVALUE(F35),1)*1440,0)) -> 205 | P35: =IF(COUNTIF($A$2:A35,A35)>1,"DUP","") | Q35: =IF(O35="","",IF(O35>240,"Y","N")) -> N
A36: ED-7000035 | B36: 2469973653 | C36: BELL | D36: 19093 | E36: 45606 | F36: 13:47 | G36: 3 | H36: 14:21 | I36: 14:49 | J36: ADM | K36: N | L36: 62 | M36: head injury | N36: GS | O36: =IF(I36="","",ROUND(MOD(TIMEVALUE(I36)-TIMEVALUE(F36),1)*1440,0)) -> 62 | P36: =IF(COUNTIF($A$2:A36,A36)>1,"DUP","") | Q36: =IF(O36="","",IF(O36>240,"Y","N")) -> N
A37: ED-7000036 | B37: 9370642122 | C37: MURPHY | D37: 23300 | E37: 45708 | F37: 23:40 | G37: 4 | H37: 02:12 | I37: 01:15 | J37: DISC | K37: N | L37: 95 | M37: Vomiting | N37: NONE | O37: =IF(I37="","",ROUND(MOD(TIMEVALUE(I37)-TIMEVALUE(F37),1)*1440,0)) -> 95 | P37: =IF(COUNTIF($A$2:A37,A37)>1,"DUP","") | Q37: =IF(O37="","",IF(O37>240,"Y","N")) -> N
A38: ED-7000037 | B38: 7310060530 | C38: CARTER | D38: 32370 | E38: 45576 | F38: 13:13 | G38: 5 | H38: 17:47 | I38: 14:45 | J38: DISC | K38: N | L38: 92 | M38: Chest Pain | N38: NONE | O38: =IF(I38="","",ROUND(MOD(TIMEVALUE(I38)-TIMEVALUE(F38),1)*1440,0)) -> 92 | P38: =IF(COUNTIF($A$2:A38,A38)>1,"DUP","") | Q38: =IF(O38="","",IF(O38>240,"Y","N")) -> N
A39: ED-7000038 | B39: 7972183780 | C39: LEWIS | D39: 26826 | E39: 45679 | F39: 11:35 | G39: 2 | H39: 11:56 | I39: 13:28 | J39: ADM | K39: N | L39: 113 | M39: fall | N39: OPH | O39: =IF(I39="","",ROUND(MOD(TIMEVALUE(I39)-TIMEVALUE(F39),1)*1440,0)) -> 113 | P39: =IF(COUNTIF($A$2:A39,A39)>1,"DUP","") | Q39: =IF(O39="","",IF(O39>240,"Y","N")) -> N
A40: ED-7000039 | B40: 2108560544 | C40: NDLOVU | D40: 33740 | E40: 45652 | F40: 15:23 | G40: 5 | H40: 20:07 | I40: 16:25 | J40: LEFT | K40: N | L40: 62 | M40: Overdose | N40: NONE | O40: =IF(I40="","",ROUND(MOD(TIMEVALUE(I40)-TIMEVALUE(F40),1)*1440,0)) -> 62 | P40: =IF(COUNTIF($A$2:A40,A40)>1,"DUP","") | Q40: =IF(O40="","",IF(O40>240,"Y","N")) -> N
A41: ED-7000040 | C41: STEWART | D41: 17480 | E41: 45589 | F41: 06:49 | G41: 4 | I41: 08:17 | J41: ADM | K41: N | L41: 88 | M41: Vomiting | N41: OPH | O41: =IF(I41="","",ROUND(MOD(TIMEVALUE(I41)-TIMEVALUE(F41),1)*1440,0)) -> 88 | P41: =IF(COUNTIF($A$2:A41,A41)>1,"DUP","") | Q41: =IF(O41="","",IF(O41>240,"Y","N")) -> N
A42: ED-7000041 | B42: 6688134595 | C42: WALKER | D42: 22109 | E42: 45572 | F42: 05:02 | G42: 3 | H42: 06:35 | I42: 06:15 | J42: DIED | K42: N | L42: 73 | M42: VOMITING | N42: NONE | O42: =IF(I42="","",ROUND(MOD(TIMEVALUE(I42)-TIMEVALUE(F42),1)*1440,0)) -> 73 | P42: =IF(COUNTIF($A$2:A42,A42)>1,"DUP","") | Q42: =IF(O42="","",IF(O42>240,"Y","N")) -> N
A43: ED-7000042 | B43: 7657963974 | C43: LEE | D43: 25486 | E43: 45630 | F43: 10:14 | G43: 4 | H43: 14:03 | I43: 10:48 | J43: DISC | K43: N | L43: 34 | M43: Back Pain | N43: NONE | O43: =IF(I43="","",ROUND(MOD(TIMEVALUE(I43)-TIMEVALUE(F43),1)*1440,0)) -> 34 | P43: =IF(COUNTIF($A$2:A43,A43)>1,"DUP","") | Q43: =IF(O43="","",IF(O43>240,"Y","N")) -> N
A44: ED-7000043 | B44: 0274755553 | C44: HALL | D44: 27476 | E44: 45585 | F44: 13:22 | G44: 4 | H44: 15:25 | I44: 17:18 | J44: DISC | K44: N | L44: 236 | M44: laceration | N44: NONE | O44: =IF(I44="","",ROUND(MOD(TIMEVALUE(I44)-TIMEVALUE(F44),1)*1440,0)) -> 236 | P44: =IF(COUNTIF($A$2:A44,A44)>1,"DUP","") | Q44: =IF(O44="","",IF(O44>240,"Y","N")) -> N
A45: ED-7000044 | B45: 1062069153 | C45: NELSON | D45: 39423 | E45: 45653 | F45: 10:29 | G45: 3 | H45: 11:37 | I45: 14:27 | J45: DISC | K45: N | L45: 238 | M45: vomiting | N45: NONE | O45: =IF(I45="","",ROUND(MOD(TIMEVALUE(I45)-TIMEVALUE(F45),1)*1440,0)) -> 238 | P45: =IF(COUNTIF($A$2:A45,A45)>1,"DUP","") | Q45: =IF(O45="","",IF(O45>240,"Y","N")) -> N
A46: ED-7000045 | B46: 9416104776 | C46: CAMPBELL | D46: 24161 | E46: 45659 | F46: 08:16 | G46: 5 | H46: 10:57 | I46: 14:37 | J46: DISC | K46: Y | L46: 381 | M46: VOMITING | N46: NONE | O46: =IF(I46="","",ROUND(MOD(TIMEVALUE(I46)-TIMEVALUE(F46),1)*1440,0)) -> 381 | P46: =IF(COUNTIF($A$2:A46,A46)>1,"DUP","") | Q46: =IF(O46="","",IF(O46>240,"Y","N")) -> Y
A47: ED-7000046 | B47: 6881973699 | C47: ALLEN | D47: 19823 | E47: 45584 | F47: 20:35 | G47: 3 | H47: 21:52 | J47: ADM | M47: STROKE | N47: GS | O47: =IF(I47="","",ROUND(MOD(TIMEVALUE(I47)-TIMEVALUE(F47),1)*1440,0)) | P47: =IF(COUNTIF($A$2:A47,A47)>1,"DUP","") | Q47: =IF(O47="","",IF(O47>240,"Y","N"))
A48: ED-7000047 | B48: 5768684551 | C48: PHILLIPS | D48: 35807 | E48: 45614 | F48: 04:51 | G48: 3 | H48: 06:42 | I48: 06:26 | J48: DISC | K48: N | L48: 95 | M48: cut | N48: NONE | O48: =IF(I48="","",ROUND(MOD(TIMEVALUE(I48)-TIMEVALUE(F48),1)*1440,0)) -> 95 | P48: =IF(COUNTIF($A$2:A48,A48)>1,"DUP","") | Q48: =IF(O48="","",IF(O48>240,"Y","N")) -> N
A49: ED-7000048 | B49: 3816568553 | C49: WILSON | D49: 17983 | E49: 45728 | F49: 20:27 | G49: 3 | H49: 21:33 | I49: 00:01 | J49: ADM | K49: N | L49: 214 | M49: shortness of breath | N49: OR | O49: =IF(I49="","",ROUND(MOD(TIMEVALUE(I49)-TIMEVALUE(F49),1)*1440,0)) -> 214 | P49: =IF(COUNTIF($A$2:A49,A49)>1,"DUP","") | Q49: =IF(O49="","",IF(O49>240,"Y","N")) -> N
A50: ED-7000049 | B50: 9065286303 | C50: WRIGHT | D50: 19248 | E50: 45625 | F50: 17:21 | G50: 4 | H50: 20:41 | I50: 19:56 | J50: DISC | K50: N | L50: 155 | M50: Stroke Symptoms | N50: NONE | O50: =IF(I50="","",ROUND(MOD(TIMEVALUE(I50)-TIMEVALUE(F50),1)*1440,0)) -> 155 | P50: =IF(COUNTIF($A$2:A50,A50)>1,"DUP","") | Q50: =IF(O50="","",IF(O50>240,"Y","N")) -> N
A51: ED-7000050 | B51: 1211925595 | C51: AHMED | D51: 32397 | E51: 45666 | F51: 14:59 | G51: 5 | H51: 17:49 | I51: 15:58 | J51: DISC | K51: N | L51: 59 | M51: fall | N51: NONE | O51: =IF(I51="","",ROUND(MOD(TIMEVALUE(I51)-TIMEVALUE(F51),1)*1440,0)) -> 59 | P51: =IF(COUNTIF($A$2:A51,A51)>1,"DUP","") | Q51: =IF(O51="","",IF(O51>240,"Y","N")) -> N
A52: ED-7000051 | B52: 6937162617 | C52: NDLOVU | D52: 20548 | E52: 45637 | F52: 21:36 | G52: 4 | H52: 00:18 | I52: 01:06 | J52: DISC | K52: N | L52: 210 | M52: Overdose | N52: NONE | O52: =IF(I52="","",ROUND(MOD(TIMEVALUE(I52)-TIMEVALUE(F52),1)*1440,0)) -> 210 | P52: =IF(COUNTIF($A$2:A52,A52)>1,"DUP","") | Q52: =IF(O52="","",IF(O52>240,"Y","N")) -> N
A53: ED-7000052 | B53: 6650321868 | C53: JONES | D53: 22423 | E53: 45709 | F53: 16:28 | G53: 4 | H53: 20:17 | I53: 19:55 | J53: LEFT | K53: N | L53: 207 | M53: vomiting | N53: NONE | O53: =IF(I53="","",ROUND(MOD(TIMEVALUE(I53)-TIMEVALUE(F53),1)*1440,0)) -> 207 | P53: =IF(COUNTIF($A$2:A53,A53)>1,"DUP","") | Q53: =IF(O53="","",IF(O53>240,"Y","N")) -> N
A54: ED-7000053 | B54: 2261941338 | C54: WILSON | D54: 33468 | E54: 45619 | F54: 06:26 | G54: 2 | H54: 06:56 | I54: 07:39 | J54: LEFT | K54: N | L54: 73 | M54: laceration | N54: NONE | O54: =IF(I54="","",ROUND(MOD(TIMEVALUE(I54)-TIMEVALUE(F54),1)*1440,0)) -> 73 | P54: =IF(COUNTIF($A$2:A54,A54)>1,"DUP","") | Q54: =IF(O54="","",IF(O54>240,"Y","N")) -> N
A55: ED-7000054 | B55: 0867129356 | C55: MARTIN | D55: 30726 | E55: 45696 | F55: 05:01 | G55: 4 | H55: 06:44 | I55: 08:37 | J55: DISC | K55: N | L55: 216 | M55: overdose | N55: NONE | O55: =IF(I55="","",ROUND(MOD(TIMEVALUE(I55)-TIMEVALUE(F55),1)*1440,0)) -> 216 | P55: =IF(COUNTIF($A$2:A55,A55)>1,"DUP","") | Q55: =IF(O55="","",IF(O55>240,"Y","N")) -> N
A56: ED-7000055 | B56: 2737340942 | C56: MORGAN | D56: 24528 | E56: 45639 | F56: 00:56 | G56: 4 | H56: 03:23 | I56: 02:56 | J56: DIED | K56: N | L56: 120 | M56: UTI symptoms | N56: NONE | O56: =IF(I56="","",ROUND(MOD(TIMEVALUE(I56)-TIMEVALUE(F56),1)*1440,0)) -> 120 | P56: =IF(COUNTIF($A$2:A56,A56)>1,"DUP","") | Q56: =IF(O56="","",IF(O56>240,"Y","N")) -> N
A57: ED-7000056 | B57: 5210884334 | C57: MORRIS | D57: 17800 | E57: 45619 | F57: 00:20 | G57: 3 | H57: 01:05 | I57: 04:03 | J57: DISC | K57: N | L57: 223 | M57: fracture | N57: NONE | O57: =IF(I57="","",ROUND(MOD(TIMEVALUE(I57)-TIMEVALUE(F57),1)*1440,0)) -> 223 | P57: =IF(COUNTIF($A$2:A57,A57)>1,"DUP","") | Q57: =IF(O57="","",IF(O57>240,"Y","N")) -> N
A58: ED-7000057 | B58: 4831034591 | C58: GREEN | D58: 13858 | E58: 45598 | F58: 12:39 | G58: 3 | H58: 13:47 | I58: 13:38 | J58: DISC | K58: N | L58: 59 | M58: Vomiting | N58: NONE | O58: =IF(I58="","",ROUND(MOD(TIMEVALUE(I58)-TIMEVALUE(F58),1)*1440,0)) -> 59 | P58: =IF(COUNTIF($A$2:A58,A58)>1,"DUP","") | Q58: =IF(O58="","",IF(O58>240,"Y","N")) -> N
A59: ED-7000058 | B59: 3537217004 | C59: MWANGI | D59: 34585 | E59: 45579 | F59: 15:52 | G59: 3 | H59: 17:33 | I59: 20:51 | J59: DISC | K59: Y | L59: 299 | M59: urinary symptoms | N59: NONE | O59: =IF(I59="","",ROUND(MOD(TIMEVALUE(I59)-TIMEVALUE(F59),1)*1440,0)) -> 299 | P59: =IF(COUNTIF($A$2:A59,A59)>1,"DUP","") | Q59: =IF(O59="","",IF(O59>240,"Y","N")) -> Y
A60: ED-7000059 | B60: 1736971111 | C60: MARTIN | D60: 33629 | E60: 45700 | F60: 10:44 | G60: 3 | H60: 12:18 | I60: 11:37 | J60: DISC | K60: N | L60: 53 | M60: COLLAPSE | N60: NONE | O60: =IF(I60="","",ROUND(MOD(TIMEVALUE(I60)-TIMEVALUE(F60),1)*1440,0)) -> 53 | P60: =IF(COUNTIF($A$2:A60,A60)>1,"DUP","") | Q60: =IF(O60="","",IF(O60>240,"Y","N")) -> N
A61: ED-7000060 | C61: DIALLO | D61: 38693 | E61: 45652 | F61: 14:46 | G61: 5 | H61: 18:55 | I61: 00:27 | J61: DISC | K61: Y | L61: 581 | M61: abdominal pain | N61: NONE | O61: =IF(I61="","",ROUND(MOD(TIMEVALUE(I61)-TIMEVALUE(F61),1)*1440,0)) -> 581 | P61: =IF(COUNTIF($A$2:A61,A61)>1,"DUP","") | Q61: =IF(O61="","",IF(O61>240,"Y","N")) -> Y
A62: ED-7000061 | B62: 6745287732 | C62: PEREZ | D62: 23153 | E62: 45612 | F62: 06:27 | G62: 2 | H62: 06:36 | I62: 10:07 | J62: ADM | K62: N | L62: 220 | M62: palpitations | N62: CS | O62: =IF(I62="","",ROUND(MOD(TIMEVALUE(I62)-TIMEVALUE(F62),1)*1440,0)) -> 220 | P62: =IF(COUNTIF($A$2:A62,A62)>1,"DUP","") | Q62: =IF(O62="","",IF(O62>240,"Y","N")) -> N
A63: ED-7000062 | B63: 6530453042 | C63: ADAMS | D63: 17577 | E63: 45701 | F63: 12:25 | G63: 3 | H63: 13:26 | I63: 14:06 | J63: DISC | K63: N | L63: 101 | M63: Vomiting | N63: N/A | O63: =IF(I63="","",ROUND(MOD(TIMEVALUE(I63)-TIMEVALUE(F63),1)*1440,0)) -> 101 | P63: =IF(COUNTIF($A$2:A63,A63)>1,"DUP","") | Q63: =IF(O63="","",IF(O63>240,"Y","N")) -> N
A64: ED-7000063 | C64: COLLINS | D64: 23535 | E64: 45653 | F64: 03:03 | G64: 3 | H64: 04:57 | I64: 11:40 | J64: DISC | K64: Y | L64: 517 | M64: UTI symptoms | N64: NONE | O64: =IF(I64="","",ROUND(MOD(TIMEVALUE(I64)-TIMEVALUE(F64),1)*1440,0)) -> 517 | P64: =IF(COUNTIF($A$2:A64,A64)>1,"DUP","") | Q64: =IF(O64="","",IF(O64>240,"Y","N")) -> Y
A65: ED-7000064 | B65: 2093576529 | C65: LEWIS | D65: 13521 | E65: 45719 | F65: 00:43 | G65: 4 | H65: 03:02 | I65: 02:31 | J65: ADM | K65: N | L65: 108 | M65: FEVER | N65: RHE | O65: =IF(I65="","",ROUND(MOD(TIMEVALUE(I65)-TIMEVALUE(F65),1)*1440,0)) -> 108 | P65: =IF(COUNTIF($A$2:A65,A65)>1,"DUP","") | Q65: =IF(O65="","",IF(O65>240,"Y","N")) -> N
A66: ED-7000065 | B66: 3830288835 | C66: WILLIAMS | D66: 24544 | E66: 45737 | F66: 18:37 | G66: 2 | H66: 19:04 | I66: 20:14 | J66: DIED | K66: N | L66: 97 | M66: fracture | N66: NONE | O66: =IF(I66="","",ROUND(MOD(TIMEVALUE(I66)-TIMEVALUE(F66),1)*1440,0)) -> 97 | P66: =IF(COUNTIF($A$2:A66,A66)>1,"DUP","") | Q66: =IF(O66="","",IF(O66>240,"Y","N")) -> N
A67: ED-7000066 | B67: 4668328603 | C67: ADEYEMI | D67: 24996 | E67: 45704 | F67: 20:13 | G67: 3 | H67: 20:51 | I67: 00:09 | J67: ADM | K67: N | L67: 236 | M67: FALL | N67: RHE | O67: =IF(I67="","",ROUND(MOD(TIMEVALUE(I67)-TIMEVALUE(F67),1)*1440,0)) -> 236 | P67: =IF(COUNTIF($A$2:A67,A67)>1,"DUP","") | Q67: =IF(O67="","",IF(O67>240,"Y","N")) -> N
A68: ED-7000067 | C68: ODUYA | D68: 22174 | E68: 45654 | F68: 07:57 | G68: 4 | H68: 10:42 | I68: 09:59 | J68: DIED | K68: N | L68: 122 | M68: FEVER | N68: NONE | O68: =IF(I68="","",ROUND(MOD(TIMEVALUE(I68)-TIMEVALUE(F68),1)*1440,0)) -> 122 | P68: =IF(COUNTIF($A$2:A68,A68)>1,"DUP","") | Q68: =IF(O68="","",IF(O68>240,"Y","N")) -> N
A69: ED-7000068 | B69: 2260185845 | C69: NGUYEN | D69: 34764 | E69: 45592 | F69: 06:24 | G69: 4 | H69: 09:14 | I69: 11:17 | J69: DISC | K69: Y | L69: 293 | M69: FALL | N69: NONE | O69: =IF(I69="","",ROUND(MOD(TIMEVALUE(I69)-TIMEVALUE(F69),1)*1440,0)) -> 293 | P69: =IF(COUNTIF($A$2:A69,A69)>1,"DUP","") | Q69: =IF(O69="","",IF(O69>240,"Y","N")) -> Y
A70: ED-7000069 | B70: 2034601120 | C70: ROGERS | D70: 20040 | E70: 45624 | F70: 22:07 | G70: 3 | H70: 23:07 | I70: 00:28 | J70: DISC | K70: N | L70: 141 | M70: abdominal pain | N70: NONE | O70: =IF(I70="","",ROUND(MOD(TIMEVALUE(I70)-TIMEVALUE(F70),1)*1440,0)) -> 141 | P70: =IF(COUNTIF($A$2:A70,A70)>1,"DUP","") | Q70: =IF(O70="","",IF(O70>240,"Y","N")) -> N
A71: ED-7000070 | C71: IHEJIRIKA | D71: 21903 | E71: 45691 | F71: 10:25 | G71: 3 | H71: 12:16 | I71: 13:39 | J71: DISC | K71: N | L71: 194 | M71: cut | N71: NONE | O71: =IF(I71="","",ROUND(MOD(TIMEVALUE(I71)-TIMEVALUE(F71),1)*1440,0)) -> 194 | P71: =IF(COUNTIF($A$2:A71,A71)>1,"DUP","") | Q71: =IF(O71="","",IF(O71>240,"Y","N")) -> N
A72: ED-7000071 | B72: 6688134595 | C72: CAMPBELL | D72: 38162 | E72: 45707 | F72: 06:18 | G72: 4 | H72: 08:46 | I72: 07:57 | J72: DISC | K72: N | L72: 99 | M72: Head Injury | N72: NONE | O72: =IF(I72="","",ROUND(MOD(TIMEVALUE(I72)-TIMEVALUE(F72),1)*1440,0)) -> 99 | P72: =IF(COUNTIF($A$2:A72,A72)>1,"DUP","") | Q72: =IF(O72="","",IF(O72>240,"Y","N")) -> N
A73: ED-7000072 | B73: 4198254530 | C73: CLARK | D73: 29590 | E73: 45627 | F73: 20:20 | G73: 3 | H73: 21:06 | I73: 21:15 | J73: DISC | K73: N | L73: 55 | M73: Seizure | N73: NONE | O73: =IF(I73="","",ROUND(MOD(TIMEVALUE(I73)-TIMEVALUE(F73),1)*1440,0)) -> 55 | P73: =IF(COUNTIF($A$2:A73,A73)>1,"DUP","") | Q73: =IF(O73="","",IF(O73>240,"Y","N")) -> N
A74: ED-7000073 | C74: BROWN | D74: 26463 | E74: 45697 | F74: 02:27 | G74: 3 | H74: 03:48 | I74: 05:30 | J74: DISC | K74: N | L74: 183 | M74: SEIZURE | N74: NONE | O74: =IF(I74="","",ROUND(MOD(TIMEVALUE(I74)-TIMEVALUE(F74),1)*1440,0)) -> 183 | P74: =IF(COUNTIF($A$2:A74,A74)>1,"DUP","") | Q74: =IF(O74="","",IF(O74>240,"Y","N")) -> N
A75: ED-7000074 | B75: 0030339338 | C75: DAVIES | D75: 35415 | E75: 45605 | F75: 04:38 | G75: 3 | H75: 06:36 | I75: 11:29 | J75: DISC | K75: Y | L75: 411 | M75: Fracture | N75: NONE | O75: =IF(I75="","",ROUND(MOD(TIMEVALUE(I75)-TIMEVALUE(F75),1)*1440,0)) -> 411 | P75: =IF(COUNTIF($A$2:A75,A75)>1,"DUP","") | Q75: =IF(O75="","",IF(O75>240,"Y","N")) -> Y
A76: ED-7000075 | B76: 4842742358 | C76: PEREZ | D76: 28933 | E76: 45604 | F76: 10:03 | G76: 4 | H76: 13:47 | I76: 16:23 | J76: DISC | K76: Y | L76: 380 | M76: vomiting | N76: NONE | O76: =IF(I76="","",ROUND(MOD(TIMEVALUE(I76)-TIMEVALUE(F76),1)*1440,0)) -> 380 | P76: =IF(COUNTIF($A$2:A76,A76)>1,"DUP","") | Q76: =IF(O76="","",IF(O76>240,"Y","N")) -> Y
A77: ED-7000076 | B77: 0030339338 | C77: OSEI | D77: 25468 | E77: 45726 | F77: 17:27 | G77: 2 | I77: 21:07 | J77: ADM | K77: N | L77: 220 | M77: Laceration | N77: CS | O77: =IF(I77="","",ROUND(MOD(TIMEVALUE(I77)-TIMEVALUE(F77),1)*1440,0)) -> 220 | P77: =IF(COUNTIF($A$2:A77,A77)>1,"DUP","") | Q77: =IF(O77="","",IF(O77>240,"Y","N")) -> N
A78: ED-7000077 | B78: 2787994879 | C78: ADEYEMI | D78: 32671 | E78: 45640 | F78: 12:52 | G78: 3 | H78: 14:42 | I78: 16:05 | J78: ADM | K78: N | L78: 193 | M78: PALPITATIONS | N78: GS | O78: =IF(I78="","",ROUND(MOD(TIMEVALUE(I78)-TIMEVALUE(F78),1)*1440,0)) -> 193 | P78: =IF(COUNTIF($A$2:A78,A78)>1,"DUP","") | Q78: =IF(O78="","",IF(O78>240,"Y","N")) -> N
A79: ED-7000078 | B79: 5894719029 | C79: ADAMS | D79: 24780 | E79: 45715 | F79: 02:51 | G79: 4 | H79: 05:59 | I79: 04:26 | J79: DISC | K79: N | L79: 95 | M79: Fracture | N79: NONE | O79: =IF(I79="","",ROUND(MOD(TIMEVALUE(I79)-TIMEVALUE(F79),1)*1440,0)) -> 95 | P79: =IF(COUNTIF($A$2:A79,A79)>1,"DUP","") | Q79: =IF(O79="","",IF(O79>240,"Y","N")) -> N
A80: ED-7000079 | C80: OSEI | D80: 18828 | E80: 45675 | F80: 13:15 | G80: 3 | H80: 14:51 | I80: 15:01 | J80: DIED | K80: N | L80: 106 | M80: CHEST PAIN | N80: NONE | O80: =IF(I80="","",ROUND(MOD(TIMEVALUE(I80)-TIMEVALUE(F80),1)*1440,0)) -> 106 | P80: =IF(COUNTIF($A$2:A80,A80)>1,"DUP","") | Q80: =IF(O80="","",IF(O80>240,"Y","N")) -> N
A81: ED-7000080 | B81: 2723267745 | C81: PEREZ | D81: 32148 | E81: 45693 | F81: 11:56 | G81: 4 | H81: 15:49 | I81: 12:29 | J81: DISC | K81: N | L81: 33 | M81: Shortness of Breath | N81: NONE | O81: =IF(I81="","",ROUND(MOD(TIMEVALUE(I81)-TIMEVALUE(F81),1)*1440,0)) -> 33 | P81: =IF(COUNTIF($A$2:A81,A81)>1,"DUP","") | Q81: =IF(O81="","",IF(O81>240,"Y","N")) -> N
A82: ED-7000081 | B82: 6881973699 | C82: OKONKWO | D82: 33266 | E82: 45727 | F82: 11:32 | G82: 3 | H82: 12:19 | I82: 15:02 | J82: DIED | K82: N | L82: 210 | M82: Abdominal Pain | N82: NONE | O82: =IF(I82="","",ROUND(MOD(TIMEVALUE(I82)-TIMEVALUE(F82),1)*1440,0)) -> 210 | P82: =IF(COUNTIF($A$2:A82,A82)>1,"DUP","") | Q82: =IF(O82="","",IF(O82>240,"Y","N")) -> N
A83: ED-7000082 | B83: 4462224088 | C83: MORGAN | D83: 30764 | E83: 45613 | F83: 08:51 | G83: 3 | H83: 10:00 | I83: 09:30 | J83: DIED | K83: N | L83: 39 | M83: Collapse | N83: NONE | O83: =IF(I83="","",ROUND(MOD(TIMEVALUE(I83)-TIMEVALUE(F83),1)*1440,0)) -> 39 | P83: =IF(COUNTIF($A$2:A83,A83)>1,"DUP","") | Q83: =IF(O83="","",IF(O83>240,"Y","N")) -> N
A84: ED-7000083 | C84: ODUYA | D84: 19517 | E84: 45573 | F84: 15:26 | G84: 2 | H84: 15:37 | I84: 19:02 | J84: DISC | K84: N | L84: 216 | M84: shortness of breath | N84: NONE | O84: =IF(I84="","",ROUND(MOD(TIMEVALUE(I84)-TIMEVALUE(F84),1)*1440,0)) -> 216 | P84: =IF(COUNTIF($A$2:A84,A84)>1,"DUP","") | Q84: =IF(O84="","",IF(O84>240,"Y","N")) -> N
A85: ED-7000084 | B85: 1062069153 | C85: RIVERA | D85: 26802 | E85: 45685 | F85: 14:48 | G85: 3 | H85: 15:44 | I85: 16:51 | J85: DISC | K85: N | L85: 123 | M85: SEIZURE | N85: NONE | O85: =IF(I85="","",ROUND(MOD(TIMEVALUE(I85)-TIMEVALUE(F85),1)*1440,0)) -> 123 | P85: =IF(COUNTIF($A$2:A85,A85)>1,"DUP","") | Q85: =IF(O85="","",IF(O85>240,"Y","N")) -> N
A86: ED-7000085 | C86: LEE | D86: 19778 | E86: 45637 | F86: 16:08 | G86: 4 | H86: 17:48 | I86: 16:43 | J86: DISC | K86: N | L86: 35 | M86: seizure | N86: NONE | O86: =IF(I86="","",ROUND(MOD(TIMEVALUE(I86)-TIMEVALUE(F86),1)*1440,0)) -> 35 | P86: =IF(COUNTIF($A$2:A86,A86)>1,"DUP","") | Q86: =IF(O86="","",IF(O86>240,"Y","N")) -> N
A87: ED-7000086 | B87: 7310060530 | C87: MURPHY | D87: 14156 | E87: 45697 | F87: 21:21 | G87: 1 | H87: 21:24 | I87: 01:05 | J87: LWBS | K87: N | L87: 224 | M87: SOB | N87: NONE | O87: =IF(I87="","",ROUND(MOD(TIMEVALUE(I87)-TIMEVALUE(F87),1)*1440,0)) -> 224 | P87: =IF(COUNTIF($A$2:A87,A87)>1,"DUP","") | Q87: =IF(O87="","",IF(O87>240,"Y","N")) -> N
A88: ED-7000087 | C88: IHEJIRIKA | D88: 37045 | E88: 45633 | F88: 13:39 | G88: 4 | H88: 15:27 | I88: 14:27 | J88: DISC | K88: N | L88: 48 | M88: Collapse | N88: NONE | O88: =IF(I88="","",ROUND(MOD(TIMEVALUE(I88)-TIMEVALUE(F88),1)*1440,0)) -> 48 | P88: =IF(COUNTIF($A$2:A88,A88)>1,"DUP","") | Q88: =IF(O88="","",IF(O88>240,"Y","N")) -> N
A89: ED-7000088 | B89: 6518116296 | C89: BROWN | D89: 16234 | E89: 45647 | F89: 12:40 | G89: 3 | H89: 14:16 | I89: 16:04 | J89: DISC | K89: N | L89: 204 | M89: Head Injury | N89: NONE | O89: =IF(I89="","",ROUND(MOD(TIMEVALUE(I89)-TIMEVALUE(F89),1)*1440,0)) -> 204 | P89: =IF(COUNTIF($A$2:A89,A89)>1,"DUP","") | Q89: =IF(O89="","",IF(O89>240,"Y","N")) -> N
A90: ED-7000089 | B90: 1186953531 | C90: ROBINSON | D90: 23282 | E90: 45679 | F90: 07:26 | G90: 3 | H90: 08:20 | I90: 09:24 | J90: DISC | K90: N | L90: 118 | M90: overdose | N90: NONE | O90: =IF(I90="","",ROUND(MOD(TIMEVALUE(I90)-TIMEVALUE(F90),1)*1440,0)) -> 118 | P90: =IF(COUNTIF($A$2:A90,A90)>1,"DUP","") | Q90: =IF(O90="","",IF(O90>240,"Y","N")) -> N
A91: ED-7000090 | B91: 9870917999 | C91: MARTIN | D91: 19594 | E91: 45700 | F91: 19:54 | G91: 3 | I91: 03:50 | J91: LEFT | K91: Y | L91: 476 | M91: VOMITING | N91: NONE | O91: =IF(I91="","",ROUND(MOD(TIMEVALUE(I91)-TIMEVALUE(F91),1)*1440,0)) -> 476 | P91: =IF(COUNTIF($A$2:A91,A91)>1,"DUP","") | Q91: =IF(O91="","",IF(O91>240,"Y","N")) -> Y
A92: ED-7000091 | B92: 6566658120 | C92: NELSON | D92: 37253 | E92: 45593 | F92: 08:42 | G92: 4 | H92: 09:57 | I92: 11:51 | J92: DIED | K92: N | L92: 189 | M92: Overdose | N92: NONE | O92: =IF(I92="","",ROUND(MOD(TIMEVALUE(I92)-TIMEVALUE(F92),1)*1440,0)) -> 189 | P92: =IF(COUNTIF($A$2:A92,A92)>1,"DUP","") | Q92: =IF(O92="","",IF(O92>240,"Y","N")) -> N
A93: ED-7000092 | B93: 1503465807 | C93: WHITE | D93: 13677 | E93: 45721 | F93: 17:11 | G93: 3 | H93: 18:41 | I93: 02:26 | J93: DISC | K93: Y | L93: 555 | M93: shortness of breath | N93: NONE | O93: =IF(I93="","",ROUND(MOD(TIMEVALUE(I93)-TIMEVALUE(F93),1)*1440,0)) -> 555 | P93: =IF(COUNTIF($A$2:A93,A93)>1,"DUP","") | Q93: =IF(O93="","",IF(O93>240,"Y","N")) -> Y
A94: ED-7000093 | B94: 7233589236 | C94: ASANTE | D94: 34452 | E94: 45687 | F94: 01:37 | G94: 3 | H94: 03:09 | I94: 04:57 | J94: DISC | K94: N | L94: 200 | M94: cut | N94: NONE | O94: =IF(I94="","",ROUND(MOD(TIMEVALUE(I94)-TIMEVALUE(F94),1)*1440,0)) -> 200 | P94: =IF(COUNTIF($A$2:A94,A94)>1,"DUP","") | Q94: =IF(O94="","",IF(O94>240,"Y","N")) -> N
A95: ED-7000094 | B95: 2374884839 | C95: GREEN | D95: 23921 | E95: 45710 | F95: 08:52 | G95: 5 | H95: 11:42 | J95: DISC | M95: laceration | N95: NONE | O95: =IF(I95="","",ROUND(MOD(TIMEVALUE(I95)-TIMEVALUE(F95),1)*1440,0)) | P95: =IF(COUNTIF($A$2:A95,A95)>1,"DUP","") | Q95: =IF(O95="","",IF(O95>240,"Y","N"))
A96: ED-7000095 | B96: 4716649470 | C96: GARCIA | D96: 15943 | E96: 45574 | F96: 12:51 | G96: 4 | H96: 15:42 | I96: 14:22 | J96: DISC | K96: N | L96: 91 | M96: SOB | N96: NONE | O96: =IF(I96="","",ROUND(MOD(TIMEVALUE(I96)-TIMEVALUE(F96),1)*1440,0)) -> 91 | P96: =IF(COUNTIF($A$2:A96,A96)>1,"DUP","") | Q96: =IF(O96="","",IF(O96>240,"Y","N")) -> N
A97: ED-7000096 | C97: MORRIS | D97: 14558 | E97: 45657 | F97: 14:15 | G97: 3 | H97: 16:05 | I97: 14:45 | J97: DISC | K97: N | L97: 30 | M97: collapse | N97: NONE | O97: =IF(I97="","",ROUND(MOD(TIMEVALUE(I97)-TIMEVALUE(F97),1)*1440,0)) -> 30 | P97: =IF(COUNTIF($A$2:A97,A97)>1,"DUP","") | Q97: =IF(O97="","",IF(O97>240,"Y","N")) -> N
A98: ED-7000097 | B98: 5638210023 | C98: ADAMS | D98: 32382 | E98: 45590 | F98: 07:10 | G98: 4 | I98: 08:41 | J98: DISC | K98: N | L98: 91 | M98: Head Injury | N98: NONE | O98: =IF(I98="","",ROUND(MOD(TIMEVALUE(I98)-TIMEVALUE(F98),1)*1440,0)) -> 91 | P98: =IF(COUNTIF($A$2:A98,A98)>1,"DUP","") | Q98: =IF(O98="","",IF(O98>240,"Y","N")) -> N
A99: ED-7000098 | B99: 5054324636 | C99: ROBINSON | D99: 37938 | E99: 45616 | F99: 19:33 | G99: 4 | H99: 22:02 | J99: DIED | M99: SEIZURE | N99: NONE | O99: =IF(I99="","",ROUND(MOD(TIMEVALUE(I99)-TIMEVALUE(F99),1)*1440,0)) | P99: =IF(COUNTIF($A$2:A99,A99)>1,"DUP","") | Q99: =IF(O99="","",IF(O99>240,"Y","N"))
A100: ED-7000099 | B100: 8329951008 | C100: ROGERS | D100: 21912 | E100: 45623 | F100: 07:26 | G100: 2 | H100: 07:49 | I100: 10:57 | J100: DISC | K100: N | L100: 211 | M100: Vomiting | N100: NONE | O100: =IF(I100="","",ROUND(MOD(TIMEVALUE(I100)-TIMEVALUE(F100),1)*1440,0)) -> 211 | P100: =IF(COUNTIF($A$2:A100,A100)>1,"DUP","") | Q100: =IF(O100="","",IF(O100>240,"Y","N")) -> N
A101: ED-7000100 | C101: WRIGHT | D101: 19871 | E101: 45682 | F101: 19:32 | G101: 3 | H101: 21:32 | I101: 21:07 | J101: LEFT | K101: N | L101: 95 | M101: stroke symptoms | N101: NONE | O101: =IF(I101="","",ROUND(MOD(TIMEVALUE(I101)-TIMEVALUE(F101),1)*1440,0)) -> 95 | P101: =IF(COUNTIF($A$2:A101,A101)>1,"DUP","") | Q101: =IF(O101="","",IF(O101>240,"Y","N")) -> N
A102: ED-7000101 | C102: PATEL | D102: 38553 | E102: 45589 | F102: 21:25 | G102: 3 | I102: 05:19 | J102: DISC | K102: Y | L102: 474 | M102: FALL | N102: NONE | O102: =IF(I102="","",ROUND(MOD(TIMEVALUE(I102)-TIMEVALUE(F102),1)*1440,0)) -> 474 | P102: =IF(COUNTIF($A$2:A102,A102)>1,"DUP","") | Q102: =IF(O102="","",IF(O102>240,"Y","N")) -> Y
...

Sheet TH_Raw
A1: Week_Ending | B1: Theatre_ID | C1: Sessions_Available | D1: Sessions_Used | E1: Utilisation_Pct | F1: Cases_Planned | G1: Cases_Completed | H1: Cancellations_Trust | I1: Cancellations_Patient | J1: Overrun_Minutes | K1: Specialty_Code | L1: Specialty_Code_Clean
A2: 45389 | B2: T1 | C2: 10 | D2: 7 | E2: 70 | F2: 22 | G2: 22 | H2: 2 | I2: 3 | J2: 30 | K2: OR | L2: =IF(K2="GEN","GM",K2) -> OR
A3: 45389 | B3: T2 | C3: 10 | D3: 7 | E3: 70 | F3: 25 | G3: 24 | I3: 2 | J3: 33 | K3: GYN | L3: =IF(K3="GEN","GM",K3) -> GYN
A4: 45389 | B4: T3 | C4: 8 | D4: 6 | E4: 75 | F4: 22 | G4: 22 | H4: 1 | J4: 59 | K4: OR | L4: =IF(K4="GEN","GM",K4) -> OR
A5: 45389 | B5: T4 | C5: 14 | D5: 11 | E5: 78.6 | F5: 39 | G5: 36 | H5: 4 | I5: 1 | J5: 17 | K5: CS | L5: =IF(K5="GEN","GM",K5) -> CS
A6: 45396 | B6: T1 | C6: 10 | D6: 7 | E6: 70 | F6: 28 | G6: 26 | I6: 3 | J6: 88 | K6: GS | L6: =IF(K6="GEN","GM",K6) -> GS
A7: 45396 | B7: T2 | C7: 10 | D7: 7 | E7: 70 | F7: 28 | G7: 28 | H7: 3 | I7: 1 | J7: 3 | K7: GYN | L7: =IF(K7="GEN","GM",K7) -> GYN
A8: 45396 | B8: T3 | C8: 8 | D8: 5 | E8: 62.5 | F8: 21 | G8: 19 | H8: 1 | I8: 0 | J8: 6 | K8: URO | L8: =IF(K8="GEN","GM",K8) -> URO
A9: 45396 | B9: T4 | C9: 14 | D9: 12 | E9: 85.7 | F9: 40 | G9: 36 | H9: 0 | I9: 3 | J9: 35 | K9: GS | L9: =IF(K9="GEN","GM",K9) -> GS
A10: 45403 | B10: T1 | C10: 10 | D10: 5 | E10: 50 | F10: 19 | G10: 18 | H10: 0 | I10: 3 | J10: 49 | K10: OPH | L10: =IF(K10="GEN","GM",K10) -> OPH
A11: 45403 | B11: T2 | C11: 10 | D11: 6 | E11: 60 | F11: 25 | G11: 25 | H11: 4 | I11: 2 | J11: 35 | K11: RHE | L11: =IF(K11="GEN","GM",K11) -> RHE
A12: 45403 | B12: T3 | C12: 8 | D12: 5 | E12: 62.5 | F12: 22 | G12: 18 | H12: 2 | I12: 0 | J12: 17 | K12: OR | L12: =IF(K12="GEN","GM",K12) -> OR
A13: 45403 | B13: T4 | C13: 14 | D13: 11 | E13: 78.6 | F13: 39 | G13: 35 | H13: 0 | I13: 1 | J13: -21 | K13: CS | L13: =IF(K13="GEN","GM",K13) -> CS
A14: 45410 | B14: T1 | C14: 10 | D14: 6 | E14: 60 | F14: 25 | G14: 28 | H14: 1 | I14: 3 | J14: 9 | K14: OR | L14: =IF(K14="GEN","GM",K14) -> OR
A15: 45410 | B15: T2 | C15: 10 | D15: 7 | E15: 70 | F15: 29 | G15: 28 | I15: 0 | J15: 49 | K15: GS | L15: =IF(K15="GEN","GM",K15) -> GS
A16: 45410 | B16: T3 | C16: 8 | D16: 5 | E16: 62.5 | F16: 17 | G16: 13 | H16: 3 | I16: 3 | J16: 25 | K16: GEN | L16: =IF(K16="GEN","GM",K16) -> GM
A17: 45410 | B17: T4 | C17: 14 | D17: 12 | E17: 85.7 | F17: 38 | G17: 37 | H17: 4 | I17: 2 | J17: 45 | K17: GS | L17: =IF(K17="GEN","GM",K17) -> GS
A18: 45417 | B18: T1 | C18: 10 | D18: 6 | E18: 60 | F18: 21 | G18: 21 | H18: 3 | I18: 0 | J18: 1 | K18: OPH | L18: =IF(K18="GEN","GM",K18) -> OPH
A19: 45417 | B19: T2 | C19: 10 | D19: 7 | E19: 70 | F19: 19 | G19: 15 | H19: 2 | I19: 3 | J19: 21 | K19: RHE | L19: =IF(K19="GEN","GM",K19) -> RHE
A20: 45417 | B20: T3 | C20: 8 | D20: 5 | E20: 62.5 | F20: 18 | G20: 14 | H20: 0 | I20: 0 | J20: 47 | K20: OR | L20: =IF(K20="GEN","GM",K20) -> OR
A21: 45417 | B21: T4 | C21: 14 | D21: 10 | E21: 71.4 | F21: 35 | G21: 33 | H21: 0 | I21: 2 | J21: 42 | K21: EM | L21: =IF(K21="GEN","GM",K21) -> EM
A22: 45424 | B22: T1 | C22: 10 | D22: 7 | E22: 70 | F22: 26 | G22: 23 | H22: 0 | J22: 7 | K22: OPH | L22: =IF(K22="GEN","GM",K22) -> OPH
A23: 45424 | B23: T2 | C23: 10 | D23: 6 | E23: 60 | F23: 18 | G23: 18 | H23: 4 | I23: 1 | J23: 27 | K23: CS | L23: =IF(K23="GEN","GM",K23) -> CS
A24: 45424 | B24: Theatre One | C24: 8 | D24: 6 | E24: 75 | F24: 23 | G24: 22 | H24: 0 | I24: 3 | J24: 52 | K24: OR | L24: =IF(K24="GEN","GM",K24) -> OR
A25: 45424 | B25: T4 | C25: 14 | D25: 12 | E25: 85.7 | F25: 53 | G25: 51 | H25: 3 | I25: 2 | J25: -22 | K25: GS | L25: =IF(K25="GEN","GM",K25) -> GS
A26: 45431 | B26: T1 | C26: 10 | D26: 5 | E26: 50 | F26: 15 | G26: 12 | H26: 1 | I26: 3 | J26: 42 | K26: OR | L26: =IF(K26="GEN","GM",K26) -> OR
A27: 45431 | B27: T2 | C27: 10 | D27: 6 | E27: 60 | F27: 26 | G27: 26 | H27: 0 | I27: 0 | J27: 62 | K27: RHE | L27: =IF(K27="GEN","GM",K27) -> RHE
A28: 45431 | B28: T3 | C28: 8 | D28: 6 | E28: 75 | F28: 22 | G28: 22 | H28: 1 | I28: 2 | J28: 13 | K28: OPH | L28: =IF(K28="GEN","GM",K28) -> OPH
A29: 45431 | B29: T4 | C29: 14 | D29: 12 | E29: 85.7 | F29: 43 | G29: 45 | H29: 2 | I29: 3 | J29: 43 | K29: EM | L29: =IF(K29="GEN","GM",K29) -> EM
A30: 45438 | B30: T1 | C30: 10 | D30: 6 | E30: 60 | F30: 25 | G30: 28 | H30: 0 | I30: 3 | J30: 50 | K30: URO | L30: =IF(K30="GEN","GM",K30) -> URO
A31: 45438 | B31: T2 | C31: 10 | D31: 6 | E31: 60 | F31: 26 | G31: 23 | H31: 0 | J31: 65 | K31: GYN | L31: =IF(K31="GEN","GM",K31) -> GYN
A32: 45438 | B32: T3 | C32: 8 | D32: 6 | E32: 75 | F32: 21 | G32: 21 | H32: 2 | I32: 1 | J32: 48 | K32: OR | L32: =IF(K32="GEN","GM",K32) -> OR
A33: 45438 | B33: T4 | C33: 14 | D33: 10 | E33: 71.4 | F33: 36 | G33: 32 | H33: 2 | I33: 1 | J33: 89 | K33: EM | L33: =IF(K33="GEN","GM",K33) -> EM
A34: 45445 | B34: T1 | C34: 10 | D34: 7 | E34: 70 | F34: 23 | G34: 19 | H34: 1 | I34: 3 | J34: 58 | K34: URO | L34: =IF(K34="GEN","GM",K34) -> URO
A35: 45445 | B35: T2 | C35: 10 | D35: 5 | E35: 50 | F35: 16 | G35: 16 | I35: 2 | J35: 27 | K35: CS | L35: =IF(K35="GEN","GM",K35) -> CS
A36: 45445 | B36: T3 | C36: 8 | D36: 5 | E36: 62.5 | F36: 13 | G36: 11 | H36: 2 | I36: 0 | J36: 80 | K36: GYN | L36: =IF(K36="GEN","GM",K36) -> GYN
A37: 45445 | B37: T4 | C37: 14 | D37: 12 | E37: 85.7 | F37: 52 | G37: 55 | H37: 4 | I37: 3 | J37: 82 | K37: GS | L37: =IF(K37="GEN","GM",K37) -> GS
A38: 45452 | B38: T1 | C38: 10 | D38: 6 | E38: 60 | F38: 23 | G38: 21 | I38: 2 | J38: 68 | K38: GS | L38: =IF(K38="GEN","GM",K38) -> GS
A39: 45452 | B39: T2 | C39: 10 | D39: 11 | E39: 110 | F39: 23 | G39: 21 | H39: 3 | I39: 0 | J39: 73 | K39: GYN | L39: =IF(K39="GEN","GM",K39) -> GYN
A40: 45452 | B40: T3 | C40: 8 | D40: 5 | E40: 62.5 | F40: 16 | G40: 12 | H40: 1 | I40: 2 | J40: 47 | K40: OR | L40: =IF(K40="GEN","GM",K40) -> OR
A41: 45452 | B41: T4 | C41: 14 | D41: 10 | E41: 71.4 | F41: 37 | G41: 33 | H41: 4 | I41: 3 | J41: 27 | K41: GS | L41: =IF(K41="GEN","GM",K41) -> GS
A42: 45460 | B42: T1 | C42: 10 | D42: 5 | E42: 50 | F42: 16 | G42: 15 | H42: 3 | I42: 0 | J42: 84 | K42: OPH | L42: =IF(K42="GEN","GM",K42) -> OPH
A43: 45459 | B43: T2 | C43: 10 | D43: 6 | E43: 60 | F43: 17 | G43: 17 | H43: 0 | I43: 1 | J43: 46 | K43: GS | L43: =IF(K43="GEN","GM",K43) -> GS
A44: 45459 | B44: T3 | C44: 8 | D44: 5 | E44: 62.5 | F44: 17 | G44: 15 | H44: 2 | I44: 3 | J44: 89 | K44: GYN | L44: =IF(K44="GEN","GM",K44) -> GYN
A45: 45459 | B45: T4 | C45: 14 | D45: 11 | E45: 78.6 | F45: 28 | G45: 25 | H45: 0 | I45: 3 | J45: 38 | K45: CS | L45: =IF(K45="GEN","GM",K45) -> CS
A46: 45466 | B46: T1 | C46: 10 | D46: 6 | E46: 60 | F46: 26 | G46: 22 | H46: 1 | I46: 0 | J46: 25 | K46: URO | L46: =IF(K46="GEN","GM",K46) -> URO
A47: 45466 | B47: T2 | C47: 10 | D47: 5 | E47: 41.5 | F47: 22 | G47: 18 | H47: 1 | I47: 0 | J47: 24 | K47: CS | L47: =IF(K47="GEN","GM",K47) -> CS
A48: 45466 | B48: T3 | C48: 8 | D48: 5 | E48: 62.5 | F48: 18 | G48: 18 | H48: 3 | I48: 1 | J48: 83 | K48: URO | L48: =IF(K48="GEN","GM",K48) -> URO
A49: 45466 | B49: T4 | C49: 14 | D49: 13 | E49: 92.9 | F49: 47 | G49: 47 | H49: 3 | I49: 3 | J49: 26 | K49: CS | L49: =IF(K49="GEN","GM",K49) -> CS
A50: 45473 | B50: T1 | C50: 10 | D50: 5 | E50: 50 | F50: 17 | G50: 13 | H50: 3 | I50: 1 | J50: 90 | K50: OPH | L50: =IF(K50="GEN","GM",K50) -> OPH
... A57: 45480 | B57: T4 | C57: 14 | D57: 10 | E57: 71.4 | F57: 39 | G57: 35 | H57: 2 | I57: 0 | J57: 13 | K57: EM | L57: =IF(K57="GEN","GM",K57) -> EM
A58: 45487 | B58: T1 | C58: 10 | D58: 7 | E58: 70 | F58: 24 | G58: 20 | H58: 2 | J58: 58 | K58: GS | L58: =IF(K58="GEN","GM",K58) -> GS
A59: 45487 | B59: T2 | C59: 10 | D59: 6 | E59: 60 | F59: 16 | G59: 13 | H59: 1 | I59: 3 | J59: 83 | K59: CS | L59: =IF(K59="GEN","GM",K59) -> CS
A60: 45487 | B60: T3 | C60: 8 | D60: 5 | E60: 62.5 | F60: 13 | G60: 12 | I60: 1 | J60: 11 | K60: OPH | L60: =IF(K60="GEN","GM",K60) -> OPH
A61: 45487 | B61: T4 | C61: 14 | D61: 10 | E61: 71.4 | F61: 30 | G61: 28 | H61: 1 | J61: 22 | K61: EM | L61: =IF(K61="GEN","GM",K61) -> EM
A62: 45494 | B62: T1 | C62: 10 | D62: 7 | E62: 70 | F62: 20 | G62: 18 | H62: 0 | I62: 3 | J62: 9 | K62: OR | L62: =IF(K62="GEN","GM",K62) -> OR
A63: 45494 | B63: T2 | C63: 10 | D63: 7 | E63: 61.5 | F63: 23 | G63: 20 | H63: 3 | J63: 85 | K63: GS | L63: =IF(K63="GEN","GM",K63) -> GS
A64: 45494 | B64: T3 | C64: 8 | D64: 6 | E64: 75 | F64: 21 | G64: 21 | H64: 1 | I64: 1 | J64: 38 | K64: GYN | L64: =IF(K64="GEN","GM",K64) -> GYN
A65: 45494 | B65: T4 | C65: 14 | D65: 12 | E65: 85.7 | F65: 33 | G65: 36 | H65: 2 | I65: 0 | J65: 76 | K65: EM | L65: =IF(K65="GEN","GM",K65) -> EM
A66: 45501 | B66: T1 | C66: 10 | D66: 7 | E66: 70 | F66: 21 | G66: 21 | I66: 0 | J66: -21 | K66: GS | L66: =IF(K66="GEN","GM",K66) -> GS
A67: 45501 | B67: T2 | C67: 10 | D67: 6 | E67: 60 | F67: 22 | G67: 20 | H67: 4 | J67: 35 | K67: GS | L67: =IF(K67="GEN","GM",K67) -> GS
A68: 45501 | B68: T3 | C68: 8 | D68: 6 | E68: 75 | F68: 19 | G68: 15 | H68: 2 | I68: 2 | J68: 57 | K68: GEN | L68: =IF(K68="GEN","GM",K68) -> GM
A69: 45501 | B69: T4 | C69: 14 | D69: 12 | E69: 85.7 | F69: 39 | G69: 39 | H69: 4 | I69: 3 | J69: 1 | K69: EM | L69: =IF(K69="GEN","GM",K69) -> EM
A70: 45508 | B70: T1 | C70: 10 | D70: 6 | E70: 60 | F70: 17 | G70: 20 | H70: 4 | I70: 0 | J70: -16 | K70: URO | L70: =IF(K70="GEN","GM",K70) -> URO
A71: 45508 | B71: T2 | C71: 10 | D71: 6 | E71: 60 | F71: 20 | G71: 18 | H71: 4 | J71: 19 | K71: GS | L71: =IF(K71="GEN","GM",K71) -> GS
A72: 45508 | B72: T3 | C72: 8 | D72: 6 | E72: 75 | F72: 15 | G72: 14 | H72: 1 | I72: 0 | J72: 16 | K72: GYN | L72: =IF(K72="GEN","GM",K72) -> GYN
A73: 45508 | B73: T4 | C73: 14 | D73: 11 | E73: 78.6 | F73: 42 | G73: 39 | H73: 0 | I73: 0 | J73: 39 | K73: EM | L73: =IF(K73="GEN","GM",K73) -> EM
A74: 45515 | B74: T1 | C74: 10 | D74: 6 | E74: 60 | F74: 26 | G74: 27 | H74: 3 | I74: 1 | J74: 48 | K74: URO | L74: =IF(K74="GEN","GM",K74) -> URO
A75: 45515 | B75: T2 | C75: 10 | D75: 6 | E75: 60 | F75: 20 | G75: 16 | H75: 3 | I75: 1 | J75: 31 | K75: GS | L75: =IF(K75="GEN","GM",K75) -> GS
A76: 45515 | B76: T3 | C76: 8 | D76: 5 | E76: 62.5 | F76: 13 | G76: 11 | H76: 3 | J76: 62 | K76: OR | L76: =IF(K76="GEN","GM",K76) -> OR
A77: 45515 | B77: T4 | C77: 14 | D77: 10 | E77: 71.4 | F77: 43 | G77: 42 | H77: 0 | I77: 1 | J77: 86 | K77: EM | L77: =IF(K77="GEN","GM",K77) -> EM
A78: 45522 | B78: T1 | C78: 10 | D78: 6 | E78: 60 | F78: 20 | G78: 19 | H78: 4 | I78: 0 | J78: 45 | K78: URO | L78: =IF(K78="GEN","GM",K78) -> URO
A79: 45522 | B79: T2 | C79: 10 | D79: 6 | E79: 60 | F79: 16 | G79: 15 | H79: 3 | I79: 3 | J79: 71 | K79: GS | L79: =IF(K79="GEN","GM",K79) -> GS
A80: 45522 | B80: T3 | C80: 8 | D80: 6 | E80: 75 | F80: 16 | G80: 15 | H80: 4 | I80: 2 | J80: 39 | K80: URO | L80: =IF(K80="GEN","GM",K80) -> URO
A81: 45522 | B81: T4 | C81: 14 | D81: 12 | E81: 85.7 | F81: 31 | G81: 31 | I81: 1 | J81: 59 | K81: OR | L81: =IF(K81="GEN","GM",K81) -> OR
A82: 45529 | B82: T1 | C82: 10 | D82: 6 | E82: 60 | F82: 22 | G82: 21 | I82: 3 | J82: 66 | K82: GS | L82: =IF(K82="GEN","GM",K82) -> GS
A83: 45529 | B83: T2 | C83: 10 | D83: 7 | E83: 70 | F83: 25 | G83: 21 | I83: 2 | J83: 37 | K83: CS | L83: =IF(K83="GEN","GM",K83) -> CS
A84: 45529 | B84: T3 | C84: 8 | D84: 5 | E84: 62.5 | F84: 15 | G84: 13 | H84: 1 | I84: 0 | J84: 32 | K84: OPH | L84: =IF(K84="GEN","GM",K84) -> OPH
A85: 45529 | B85: T4 | C85: 14 | D85: 11 | E85: 78.6 | F85: 49 | G85: 49 | H85: 3 | I85: 0 | J85: 62 | K85: EM | L85: =IF(K85="GEN","GM",K85) -> EM
A86: 45536 | B86: T1 | C86: 10 | D86: 7 | E86: 70 | F86: 26 | G86: 26 | H86: 4 | I86: 1 | J86: 54 | K86: URO | L86: =IF(K86="GEN","GM",K86) -> URO
A87: 45536 | B87: T2 | C87: 10 | D87: 7 | E87: 70 | F87: 31 | G87: 31 | I87: 3 | J87: 90 | K87: CS | L87: =IF(K87="GEN","GM",K87) -> CS
A88: 45536 | B88: T3 | C88: 8 | D88: 6 | E88: 75 | F88: 15 | G88: 14 | H88: 4 | I88: 0 | J88: 26 | K88: OPH | L88: =IF(K88="GEN","GM",K88) -> OPH
A89: 45536 | B89: T4 | C89: 14 | D89: 12 | E89: 85.7 | F89: 52 | G89: 50 | H89: 3 | I89: 3 | J89: 9 | K89: GS | L89: =IF(K89="GEN","GM",K89) -> GS
A90: 45543 | B90: T1 | C90: 10 | D90: 5 | E90: 50 | F90: 18 | G90: 16 | H90: 2 | I90: 3 | J90: 5 | K90: GS | L90: =IF(K90="GEN","GM",K90) -> GS
A91: 45543 | B91: T2 | C91: 10 | D91: 5 | E91: 50 | F91: 19 | G91: 16 | J91: 28 | K91: GS | L91: =IF(K91="GEN","GM",K91) -> GS
A92: 45543 | B92: T3 | C92: 8 | D92: 6 | E92: 75 | F92: 17 | G92: 14 | H92: 1 | I92: 0 | J92: 84 | K92: URO | L92: =IF(K92="GEN","GM",K92) -> URO
A93: 45543 | B93: T4 | C93: 14 | D93: 11 | E93: 78.6 | F93: 49 | G93: 47 | H93: 0 | J93: 30 | K93: CS | L93: =IF(K93="GEN","GM",K93) -> CS
A94: 45550 | B94: T1 | C94: 10 | D94: 6 | E94: 60 | F94: 18 | G94: 16 | H94: 0 | I94: 2 | J94: 50 | K94: GS | L94: =IF(K94="GEN","GM",K94) -> GS
A95: 45550 | B95: T2 | C95: 10 | D95: 5 | E95: 50 | F95: 13 | G95: 10 | H95: 2 | I95: 1 | J95: 87 | K95: CS | L95: =IF(K95="GEN","GM",K95) -> CS
A96: 45550 | B96: T3 | C96: 8 | D96: 6 | E96: 70.2 | F96: 17 | G96: 14 | H96: 4 | I96: 3 | J96: 83 | K96: GYN | L96: =IF(K96="GEN","GM",K96) -> GYN
A97: 45550 | B97: T4 | C97: 14 | D97: 11 | E97: 78.6 | F97: 40 | G97: 38 | H97: 3 | I97: 2 | J97: 67 | K97: GS | L97: =IF(K97="GEN","GM",K97) -> GS
A98: 45557 | B98: T1 | C98: 10 | D98: 6 | E98: 60 | F98: 17 | G98: 13 | H98: 4 | I98: 2 | J98: 4 | K98: GS | L98: =IF(K98="GEN","GM",K98) -> GS
A99: 45557 | B99: T2 | C99: 10 | D99: 6 | E99: 60 | F99: 27 | G99: 28 | H99: 0 | I99: 1 | J99: 11 | K99: GS | L99: =IF(K99="GEN","GM",K99) -> GS
A100: 45557 | B100: T3 | C100: 8 | D100: 5 | E100: 62.5 | F100: 22 | G100: 22 | I100: 0 | J100: 57 | K100: OPH | L100: =IF(K100="GEN","GM",K100) -> OPH
A101: 45557 | B101: T4 | C101: 14 | D101: 11 | E101: 78.6 | F101: 43 | G101: 42 | H101: 2 | I101: 2 | J101: 42 | K101: OR | L101: =IF(K101="GEN","GM",K101) -> OR
A102: 45564 | B102: T1 | C102: 10 | D102: 7 | E102: 70 | F102: 22 | G102: 18 | H102: 0 | I102: 3 | J102: 20 | K102: OPH | L102: =IF(K102="GEN","GM",K102) -> OPH
A103: 45564 | B103: T2 | C103: 10 | D103: 7 | E103: 70 | F103: 27 | G103: 28 | H103: 4 | I103: 1 | J103: 46 | K103: GS | L103: =IF(K103="GEN","GM",K103) -> GS
A104: 45564 | B104: T3 | C104: 8 | D104: 5 | E104: 62.5 | F104: 16 | G104: 16 | I104: 0 | J104: 41 | K104: GYN | L104: =IF(K104="GEN","GM",K104) -> GYN
A105: 45564 | B105: T4 | C105: 14 | D105: 11 | E105: 78.6 | F105: 37 | G105: 36 | H105: 0 | I105: 3 | J105: 58 | K105: OR | L105: =IF(K105="GEN","GM",K105) -> OR
A106: 45571 | B106: T1 | C106: 10 | D106: 6 | E106: 60 | F106: 18 | G106: 17 | H106: 2 | I106: 3 | J106: 43 | K106: GS | L106: =IF(K106="GEN","GM",K106) -> GS
...

Sheet WF_Raw
A1: Shift_ID | B1: Staff_ID | C1: Staff_Grade | D1: Ward_Code | E1: Shift_Date | F1: Shift_Type | G1: Hours_Rostered | H1: Hours_Worked | I1: Agency_Flag | J1: Absence_Flag | K1: Overtime_Hours | L1: Specialty_Code | M1: Specialty_Code_Clean
A2: SH-9000001 | B2: ST-49673 | C2: REG | D2: W-01 | E2: 45663 | F2: NIGHT | G2: 11.5 | H2: 11.5 | I2: N | J2: N | K2: 0 | L2: GM | M2: =IF(L2="GEN","GM",L2) -> GM
A3: SH-9000002 | B3: ST-84756 | C3: HCA | D3: W-01 | E3: 45663 | F3: DAY | G3: 7.5 | H3: 7.5 | I3: N | J3: N | K3: 0 | L3: GYN | M3: =IF(L3="GEN","GM",L3) -> GYN
A4: SH-9000003 | B4: ST-71339 | C4: SHO | D4: W-01 | E4: 45663 | F4: DAY | G4: 7.5 | H4: 7.5 | I4: N | J4: N | K4: 0 | L4: GM | M4: =IF(L4="GEN","GM",L4) -> GM
A5: SH-9000004 | B5: ST-26449 | C5: REG | D5: W-02 | E5: 45663 | F5: NIGHT | G5: 11.5 | H5: 12.5 | I5: N | J5: N | K5: 1 | L5: OR | M5: =IF(L5="GEN","GM",L5) -> OR
A6: SH-9000005 | B6: ST-64866 | C6: NURSE | D6: W-02 | E6: 45663 | F6: LONG | G6: 12 | H6: 13.2 | I6: N | J6: N | K6: 1.2 | L6: OR | M6: =IF(L6="GEN","GM",L6) -> OR
A7: SH-9000006 | B7: ST-55360 | C7: HCA | D7: W-02 | E7: 45663 | F7: NIGHT | G7: 11.5 | H7: 11.5 | I7: N | J7: N | K7: 0 | L7: OR | M7: =IF(L7="GEN","GM",L7) -> OR
A8: SH-9000007 | B8: ST-71595 | C8: HCA | D8: W-02 | E8: 45663 | F8: DAY | G8: 7.5 | H8: 8.9 | I8: N | J8: N | K8: 1.4 | L8: CS | M8: =IF(L8="GEN","GM",L8) -> CS
A9: SH-9000008 | B9: ST-17271 | C9: NURSE | D9: W-02 | E9: 45663 | F9: LONG | G9: 12 | H9: 12 | I9: N | J9: N | K9: 0 | L9: GM | M9: =IF(L9="GEN","GM",L9) -> GM
A10: SH-9000009 | B10: ST-84901 | C10: NURSE | D10: W-03 | E10: 45663 | F10: LONG | G10: 12 | H10: 12 | I10: Y | J10: N | K10: 0 | L10: GM | M10: =IF(L10="GEN","GM",L10) -> GM
A11: SH-9000010 | B11: ST-32610 | C11: REG | D11: W-03 | E11: 45663 | F11: LONG | G11: 12 | H11: 12 | I11: N | J11: N | K11: 0 | L11: GM | M11: =IF(L11="GEN","GM",L11) -> GM
A12: SH-9000011 | B12: ST-85070 | C12: REG | D12: W-03 | E12: 45663 | F12: LONG | G12: 12 | H12: 12 | I12: N | J12: N | K12: 0 | L12: URO | M12: =IF(L12="GEN","GM",L12) -> URO
A13: SH-9000012 | B13: ST-71868 | C13: NURSE | D13: W-03 | E13: 45663 | F13: DAY | G13: 7.5 | H13: 7.5 | I13: N | J13: N | K13: 0 | L13: RS | M13: =IF(L13="GEN","GM",L13) -> RS
... A28: SH-9000027 | B28: ST-61297 | C28: SHO | D28: W-07 | E28: 45663 | F28: DAY | G28: 7.5 | H28: 7.5 | I28: N | J28: N | K28: 0 | L28: RHE | M28: =IF(L28="GEN","GM",L28) -> RHE
A29: SH-9000028 | C29: HCA | D29: W-07 | E29: 45663 | F29: DAY | G29: 7.5 | H29: 8.7 | I29: N | J29: N | K29: 1.2 | L29: URO | M29: =IF(L29="GEN","GM",L29) -> URO
A30: SH-9000029 | B30: ST-99939 | C30: NURSE | D30: W-01 | E30: 45664 | F30: LONG | G30: 12 | H30: 12 | I30: Y | J30: N | K30: 0 | L30: RHE | M30: =IF(L30="GEN","GM",L30) -> RHE
A31: SH-9000030 | B31: ST-52474 | C31: NURSE | D31: W-01 | E31: 45664 | F31: LONG | G31: 12 | H31: 12 | I31: N | J31: N | K31: 0 | L31: GYN | M31: =IF(L31="GEN","GM",L31) -> GYN
A32: SH-9000031 | B32: ST-69603 | C32: NURSE | D32: W-01 | E32: 45664 | F32: LONG | G32: 12 | H32: 12 | I32: N | J32: N | K32: 0 | L32: OR | M32: =IF(L32="GEN","GM",L32) -> OR
A33: SH-9000032 | B33: ST-80014 | C33: CONS | D33: W-01 | E33: 45664 | F33: LONG | G33: 12 | H33: 12 | I33: N | J33: N | K33: 0 | L33: EM | M33: =IF(L33="GEN","GM",L33) -> EM
A34: SH-9000033 | B34: ST-76694 | C34: NURSE | D34: W-02 | E34: 45664 | F34: LONG | G34: 12 | H34: 12 | I34: N | J34: N | K34: 0 | L34: GYN | M34: =IF(L34="GEN","GM",L34) -> GYN
A35: SH-9000034 | B35: ST-64354 | C35: REG | D35: W-02 | E35: 45664 | F35: LONG | G35: 12 | H35: 12 | I35: N | J35: N | K35: 0 | L35: URO | M35: =IF(L35="GEN","GM",L35) -> URO
A36: SH-9000035 | B36: ST-92788 | C36: HCA | D36: W-02 | E36: 45664 | F36: LONG | G36: 12 | H36: 12 | I36: N | J36: Y | K36: 0 | L36: RHE | M36: =IF(L36="GEN","GM",L36) -> RHE
A37: SH-9000036 | B37: ST-89261 | C37: NURSE | D37: W-02 | E37: 45664 | F37: NIGHT | G37: 11.5 | H37: 11.5 | I37: N | J37: N | K37: 0 | L37: GS | M37: =IF(L37="GEN","GM",L37) -> GS
A38: SH-9000037 | B38: ST-33554 | C38: HCA | D38: W-03 | E38: 45664 | F38: NIGHT | G38: 11.5 | H38: 11.5 | I38: N | J38: N | K38: 0 | L38: CS | M38: =IF(L38="GEN","GM",L38) -> CS
A39: SH-9000038 | B39: ST-67265 | C39: CONS | D39: W-03 | E39: 45664 | F39: DAY | G39: 7.5 | H39: 7.5 | I39: N | J39: N | K39: 0 | L39: URO | M39: =IF(L39="GEN","GM",L39) -> URO
A40: SH-9000039 | B40: ST-85365 | C40: HCA | D40: W-03 | E40: 45664 | F40: LONG | G40: 12 | H40: 12 | I40: N | J40: N | K40: 0 | L40: GYN | M40: =IF(L40="GEN","GM",L40) -> GYN
A41: SH-9000040 | B41: ST-77932 | C41: CONS | D41: W-03 | E41: 45664 | F41: NIGHT | G41: 11.5 | H41: 11.5 | I41: N | J41: N | K41: 0 | L41: EM | M41: =IF(L41="GEN","GM",L41) -> EM
... A61: SH-9000060 | B61: ST-65908 | C61: HCA | D61: W-01 | E61: 45665 | F61: LONG | G61: 12 | H61: 12 | I61: N | J61: Y | K61: 0 | L61: EM | M61: =IF(L61="GEN","GM",L61) -> EM
A62: SH-9000061 | C62: NURSE | D62: W-01 | E62: 45665 | F62: LONG | G62: 12 | H62: 12 | I62: N | J62: Y | K62: 0 | L62: GM | M62: =IF(L62="GEN","GM",L62) -> GM
A63: SH-9000062 | B63: ST-73372 | C63: SHO | D63: W-02 | E63: 45665 | F63: NIGHT | G63: 11.5 | H63: 11.5 | I63: N | J63: N | K63: 0 | L63: RS | M63: =IF(L63="GEN","GM",L63) -> RS
A64: SH-9000063 | B64: ST-52368 | C64: NURSE | D64: W-02 | E64: 45665 | F64: LONG | G64: 12 | H64: 12 | I64: N | J64: Y | K64: 0 | L64: RHE | M64: =IF(L64="GEN","GM",L64) -> RHE
A65: SH-9000064 | B65: ST-81763 | C65: NURSE | D65: W-02 | E65: 45665 | F65: LONG | G65: 12 | H65: 12 | I65: N | J65: N | K65: 0 | L65: EM | M65: =IF(L65="GEN","GM",L65) -> EM
A66: SH-9000065 | B66: ST-73576 | C66: NURSE | D66: W-02 | E66: 45665 | F66: DAY | G66: 7.5 | H66: 7.5 | I66: N | J66: N | K66: 0 | L66: GYN | M66: =IF(L66="GEN","GM",L66) -> GYN
A67: SH-9000066 | B67: ST-69341 | C67: NURSE | D67: W-03 | E67: 45665 | F67: NIGHT | G67: 11.5 | H67: 11.5 | I67: N | J67: N | K67: 0 | L67: RHE | M67: =IF(L67="GEN","GM",L67) -> RHE
A68: SH-9000067 | B68: ST-20776 | C68: CONS | D68: W-03 | E68: 45665 | F68: NIGHT | G68: 11.5 | H68: 10.5 | I68: N | J68: N | K68: 0 | L68: RHE | M68: =IF(L68="GEN","GM",L68) -> RHE
A69: SH-9000068 | B69: ST-55646 | C69: HCA | D69: W-03 | E69: 45665 | F69: NIGHT | G69: 11.5 | H69: 11.5 | I69: N | J69: N | K69: 0 | L69: EM | M69: =IF(L69="GEN","GM",L69) -> EM
A70: SH-9000069 | B70: ST-42105 | C70: NURSE | D70: W-03 | E70: 45665 | F70: DAY | G70: 7.5 | H70: 7.5 | I70: N | J70: N | K70: 0 | L70: EM | M70: =IF(L70="GEN","GM",L70) -> EM
A71: SH-9000070 | B71: ST-62501 | C71: REG | D71: W-04 | E71: 45665 | F71: LONG | G71: 12 | H71: 13.9 | I71: N | J71: N | K71: 1.9 | L71: GM | M71: =IF(L71="GEN","GM",L71) -> GM
A72: SH-9000071 | B72: ST-12115 | C72: REG | D72: W-04 | E72: 45665 | F72: LONG | G72: 12 | H72: 12 | I72: N | J72: N | K72: 0 | L72: CS | M72: =IF(L72="GEN","GM",L72) -> CS
A73: SH-9000072 | B73: ST-57562 | C73: NURSE | D73: W-04 | E73: 45665 | F73: DAY | G73: 7.5 | H73: 7.5 | I73: N | J73: N | K73: 0 | L73: URO | M73: =IF(L73="GEN","GM",L73) -> URO
A74: SH-9000073 | B74: ST-55230 | C74: NURSE | D74: W-04 | E74: 45665 | F74: LONG | G74: 12 | H74: 12 | I74: N | J74: N | K74: 0 | L74: GS | M74: =IF(L74="GEN","GM",L74) -> GS
... A78: SH-9000077 | B78: ST-17776 | C78: NURSE | D78: W-05 | E78: 45665 | F78: LONG | G78: 12 | H78: 12 | I78: N | J78: N | K78: 0 | L78: GS | M78: =IF(L78="GEN","GM",L78) -> GS
A79: SH-9000078 | C79: NURSE | D79: W-05 | E79: 45665 | F79: LONG | G79: 12 | H79: 12 | I79: N | J79: N | K79: 0 | L79: GS | M79: =IF(L79="GEN","GM",L79) -> GS
A80: SH-9000079 | B80: ST-79167 | C80: SHO | D80: W-05 | E80: 45665 | F80: NIGHT | G80: 11.5 | H80: 11.5 | I80: Y | J80: N | K80: 0 | L80: EM | M80: =IF(L80="GEN","GM",L80) -> EM
A81: SH-9000080 | B81: ST-69390 | C81: CONS | D81: W-06 | E81: 45665 | F81: NIGHT | G81: 11.5 | H81: 11.5 | I81: N | J81: N | K81: 0 | L81: EM | M81: =IF(L81="GEN","GM",L81) -> EM
A82: SH-9000081 | B82: ST-61951 | C82: SHO | D82: W-06 | E82: 45665 | F82: DAY | G82: 7.5 | H82: 8.5 | I82: N | J82: N | K82: 1 | L82: RS | M82: =IF(L82="GEN","GM",L82) -> RS
A83: SH-9000082 | B83: ST-34042 | C83: HCA | D83: W-06 | E83: 45665 | F83: NIGHT | G83: 11.5 | H83: 11.5 | I83: N | J83: N | K83: 0 | L83: URO | M83: =IF(L83="GEN","GM",L83) -> URO
A84: SH-9000083 | B84: ST-81358 | C84: NURSE | D84: W-07 | E84: 45665 | F84: DAY | G84: 7.5 | H84: 7.5 | I84: N | J84: N | K84: 0 | L84: OR | M84: =IF(L84="GEN","GM",L84) -> OR
A85: SH-9000084 | B85: ST-48923 | C85: HCA | D85: W-07 | E85: 45665 | F85: LONG | G85: 12 | H85: 12 | I85: Y | J85: N | K85: 0 | L85: GM | M85: =IF(L85="GEN","GM",L85) -> GM
A86: SH-9000085 | B86: ST-65404 | C86: REG | D86: W-07 | E86: 45665 | F86: LONG | G86: 12 | H86: 12 | I86: N | J86: Y | K86: 0 | L86: OR | M86: =IF(L86="GEN","GM",L86) -> OR
A87: SH-9000086 | B87: ST-20818 | C87: NURSE | D87: W-01 | E87: 45666 | F87: LONG | G87: 12 | H87: 12 | I87: N | J87: N | K87: 0 | L87: GM | M87: =IF(L87="GEN","GM",L87) -> GM
A88: SH-9000087 | B88: ST-74299 | C88: HCA | D88: W-01 | E88: 45666 | F88: LONG | G88: 12 | H88: 12 | I88: N | J88: N | K88: 0 | L88: OR | M88: =IF(L88="GEN","GM",L88) -> OR
A89: SH-9000088 | B89: ST-58335 | C89: CONS | D89: W-01 | E89: 45666 | F89: LONG | G89: 12 | H89: 12 | I89: N | J89: N | K89: 0 | L89: GS | M89: =IF(L89="GEN","GM",L89) -> GS
A90: SH-9000089 | B90: ST-23350 | C90: HCA | D90: W-01 | E90: 45666 | F90: NIGHT | G90: 11.5 | H90: 10.6 | I90: N | J90: N | K90: 0 | L90: GS | M90: =IF(L90="GEN","GM",L90) -> GS
A91: SH-9000090 | B91: ST-77479 | C91: HCA | D91: W-02 | E91: 45666 | F91: NIGHT | G91: 11.5 | H91: 11.5 | I91: N | J91: N | K91: 0 | L91: RS | M91: =IF(L91="GEN","GM",L91) -> RS
... A127: SH-9000126 | B127: ST-80237 | C127: REG | D127: W-04 | E127: 45667 | F127: LONG | G127: 12 | H127: 12 | I127: N | J127: N | K127: 0 | L127: URO | M127: =IF(L127="GEN","GM",L127) -> URO
A128: SH-9000127 | B128: ST-60916 | C128: HCA | D128: W-04 | E128: 45667 | F128: NIGHT | G128: 11.5 | H128: 11.5 | J128: N | K128: 0 | L128: GS | M128: =IF(L128="GEN","GM",L128) -> GS
A129: SH-9000128 | B129: ST-62049 | C129: NURSE | D129: W-04 | E129: 45667 | F129: LONG | G129: 12 | H129: 12 | I129: N | J129: N | K129: 0 | L129: URO | M129: =IF(L129="GEN","GM",L129) -> URO
A130: SH-9000129 | B130: ST-94209 | C130: REG | D130: W-05 | E130: 45667 | F130: NIGHT | G130: 11.5 | H130: 11.5 | I130: N | J130: N | K130: 0 | L130: CS | M130: =IF(L130="GEN","GM",L130) -> CS
A131: SH-9000130 | B131: ST-87616 | C131: NURSE | D131: W-05 | E131: 45667 | F131: LONG | G131: 0 | H131: 12 | I131: N | J131: N | K131: 0 | L131: GM | M131: =IF(L131="GEN","GM",L131) -> GM
A132: SH-9000131 | B132: ST-87159 | C132: NURSE | D132: W-05 | E132: 45667 | F132: NIGHT | G132: 11.5 | H132: 11.5 | I132: N | J132: N | K132: 0 | L132: OR | M132: =IF(L132="GEN","GM",L132) -> OR
A133: SH-9000132 | B133: ST-55848 | C133: SHO | D133: W-06 | E133: 45667 | F133: LONG | G133: 12 | H133: 12 | I133: N | J133: N | K133: 0 | L133: OR | M133: =IF(L133="GEN","GM",L133) -> OR
A134: SH-9000133 | B134: ST-21749 | C134: NURSE | D134: W-06 | E134: 45667 | F134: DAY | G134: 7.5 | H134: 7.5 | I134: Y | J134: N | K134: 0 | L134: EM | M134: =IF(L134="GEN","GM",L134) -> EM
A135: SH-9000134 | B135: ST-56196 | C135: HCA | D135: W-06 | E135: 45667 | F135: DAY | G135: 7.5 | H135: 7.5 | I135: N | J135: N | K135: 0 | L135: GYN | M135: =IF(L135="GEN","GM",L135) -> GYN
A136: SH-9000135 | B136: ST-53622 | C136: NURSE | D136: W-06 | E136: 45667 | F136: DAY | G136: 7.5 | H136: 7.5 | I136: N | J136: N | K136: 0 | L136: EM | M136: =IF(L136="GEN","GM",L136) -> EM
A137: SH-9000136 | B137: ST-74256 | C137: HCA | D137: W-07 | E137: 45667 | F137: DAY | G137: 7.5 | H137: 7.5 | I137: N | J137: N | K137: 0 | L137: RHE | M137: =IF(L137="GEN","GM",L137) -> RHE
A138: SH-9000137 | C138: SHO | D138: W-07 | E138: 45667 | F138: LONG | G138: 12 | H138: 12 | I138: N | J138: N | K138: 0 | L138: OR | M138: =IF(L138="GEN","GM",L138) -> OR
A139: SH-9000138 | B139: ST-78129 | C139: SHO | D139: W-07 | E139: 45667 | F139: DAY | G139: 7.5 | H139: 7.5 | I139: N | J139: N | K139: 0 | L139: EM | M139: =IF(L139="GEN","GM",L139) -> EM
A140: SH-9000139 | B140: ST-96994 | C140: REG | D140: W-07 | E140: 45667 | F140: DAY | G140: 7.5 | H140: 7.5 | I140: N | J140: N | K140: 0 | L140: GM | M140: =IF(L140="GEN","GM",L140) -> GM
A141: SH-9000140 | B141: ST-16760 | C141: NURSE | D141: W-01 | E141: 45668 | F141: NIGHT | G141: 11.5 | H141: 11.5 | I141: N | J141: N | K141: 0 | L141: EM | M141: =IF(L141="GEN","GM",L141) -> EM
A142: SH-9000141 | B142: ST-39460 | C142: SHO | D142: W-01 | E142: 45668 | F142: DAY | G142: 7.5 | H142: 7.5 | I142: N | J142: N | K142: 0 | L142: RS | M142: =IF(L142="GEN","GM",L142) -> RS
A143: SH-9000142 | B143: ST-27975 | C143: HCA | D143: W-01 | E143: 45668 | F143: LONG | G143: 12 | H143: 12 | I143: N | J143: N | K143: 0 | L143: GS | M143: =IF(L143="GEN","GM",L143) -> GS
A144: SH-9000143 | B144: ST-93205 | C144: HCA | D144: W-01 | E144: 45668 | F144: NIGHT | G144: 11.5 | H144: 11.5 | I144: N | J144: Y | K144: 0 | L144: CS | M144: =IF(L144="GEN","GM",L144) -> CS
A145: SH-9000144 | B145: ST-25069 | C145: REG | D145: W-01 | E145: 45668 | F145: NIGHT | G145: 11.5 | H145: 11.5 | I145: N | J145: N | K145: 0 | L145: GYN | M145: =IF(L145="GEN","GM",L145) -> GYN
A146: SH-9000145 | B146: ST-46347 | C146: CONS | D146: W-02 | E146: 45668 | F146: DAY | G146: 7.5 | H146: 7.5 | I146: N | J146: N | K146: 0 | L146: RS | M146: =IF(L146="GEN","GM",L146) -> RS
A147: SH-9000146 | C147: HCA | D147: W-02 | E147: 45668 | F147: NIGHT | G147: 11.5 | H147: 11.5 | I147: Y | J147: N | K147: 0 | L147: CS | M147: =IF(L147="GEN","GM",L147) -> CS
A148: SH-9000147 | B148: ST-32384 | C148: SHO | D148: W-02 | E148: 45668 | F148: DAY | G148: 7.5 | H148: 7.5 | I148: N | J148: N | K148: 0 | L148: URO | M148: =IF(L148="GEN","GM",L148) -> URO
A149: SH-9000148 | B149: ST-55182 | C149: CONS | D149: W-03 | E149: 45668 | F149: NIGHT | G149: 11.5 | H149: 11.5 | I149: N | J149: N | K149: 0 | L149: OR | M149: =IF(L149="GEN","GM",L149) -> OR
A150: SH-9000149 | B150: ST-71767 | C150: HCA | D150: W-03 | E150: 45668 | F150: NIGHT | G150: 11.5 | H150: 13.1 | I150: N | J150: N | K150: 1.6 | L150: GS | M150: =IF(L150="GEN","GM",L150) -> GS
A151: SH-9000150 | B151: ST-53433 | C151: REG | D151: W-03 | E151: 45668 | F151: LONG | G151: 12 | H151: 12 | I151: N | J151: N | K151: 0 | L151: GYN | M151: =IF(L151="GEN","GM",L151) -> GYN
A152: SH-9000151 | B152: ST-13325 | C152: NURSE | D152: W-03 | E152: 45668 | F152: NIGHT | G152: 11.5 | H152: 15.2 | I152: N | J152: Y | K152: 3.7 | L152: RS | M152: =IF(L152="GEN","GM",L152) -> RS
A153: SH-9000152 | B153: ST-93268 | C153: CONS | D153: W-08 | E153: 45668 | F153: NIGHT | G153: 11.5 | H153: 11.5 | I153: Y | J153: N | K153: 0 | L153: RS | M153: =IF(L153="GEN","GM",L153) -> RS
A154: SH-9000153 | B154: ST-90463 | C154: NURSE | D154: W-04 | E154: 45668 | F154: NIGHT | G154: 11.5 | H154: 11.5 | I154: N | J154: N | K154: 0 | L154: CS | M154: =IF(L154="GEN","GM",L154) -> CS
A155: SH-9000154 | B155: ST-36018 | C155: REG | D155: W-04 | E155: 45668 | F155: NIGHT | G155: 11.5 | H155: 11.5 | I155: N | J155: N | K155: 0 | L155: URO | M155: =IF(L155="GEN","GM",L155) -> URO
A156: SH-9000155 | B156: ST-58699 | C156: HCA | D156: W-04 | E156: 45668 | F156: DAY | G156: 7.5 | H156: 8.5 | I156: N | J156: N | K156: 1 | L156: CS | M156: =IF(L156="GEN","GM",L156) -> CS
A157: SH-9000156 | B157: ST-84718 | C157: REG | D157: W-04 | E157: 45668 | F157: NIGHT | G157: 11.5 | H157: 11.5 | I157: N | J157: N | K157: 0 | L157: GM | M157: =IF(L157="GEN","GM",L157) -> GM
A158: SH-9000157 | B158: ST-20292 | C158: NURSE | D158: W-05 | E158: 45668 | F158: DAY | G158: 7.5 | H158: 7.5 | I158: N | J158: N | K158: 0 | L158: RS | M158: =IF(L158="GEN","GM",L158) -> RS
A159: SH-9000158 | B159: ST-51140 | C159: CONS | D159: W-05 | E159: 45668 | F159: DAY | G159: 7.5 | H159: 7.5 | I159: Y | J159: N | K159: 0 | L159: GS | M159: =IF(L159="GEN","GM",L159) -> GS
... A185: SH-9000184 | B185: ST-56362 | C185: NURSE | D185: W-05 | E185: 45669 | F185: LONG | G185: 12 | H185: 12 | I185: N | J185: N | K185: 0 | L185: EM | M185: =IF(L185="GEN","GM",L185) -> EM
A186: SH-9000185 | B186: ST-47873 | C186: SHO | D186: W-05 | E186: 45669 | F186: DAY | G186: 7.5 | H186: 7.5 | J186: N | K186: 0 | L186: GM | M186: =IF(L186="GEN","GM",L186) -> GM
A187: SH-9000186 | B187: ST-65993 | C187: NURSE | D187: W-05 | E187: 45669 | F187: NIGHT | G187: 11.5 | H187: 11.5 | I187: N | J187: N | K187: 0 | L187: OR | M187: =IF(L187="GEN","GM",L187) -> OR
A188: SH-9000187 | B188: ST-89544 | C188: NURSE | D188: W-05 | E188: 45669 | F188: DAY | G188: 7.5 | H188: 7.5 | I188: N | J188: N | K188: 0 | L188: URO | M188: =IF(L188="GEN","GM",L188) -> URO
A189: SH-9000188 | B189: ST-31526 | C189: REG | D189: W-05 | E189: 45669 | F189: LONG | G189: 12 | H189: 12 | I189: Y | J189: Y | K189: 0 | L189: GS | M189: =IF(L189="GEN","GM",L189) -> GS
A190: SH-9000189 | B190: ST-91493 | C190: SHO | D190: W-06 | E190: 45669 | F190: DAY | G190: 7.5 | H190: 7.5 | I190: Y | J190: N | K190: 0 | L190: GS | M190: =IF(L190="GEN","GM",L190) -> GS
A191: SH-9000190 | B191: ST-74637 | C191: CONS | D191: W-06 | E191: 45669 | F191: DAY | G191: 7.5 | H191: 7.5 | I191: N | J191: N | K191: 0 | L191: GYN | M191: =IF(L191="GEN","GM",L191) -> GYN
A192: SH-9000191 | B192: ST-60888 | C192: HCA | D192: W-06 | E192: 45669 | F192: LONG | G192: 12 | H192: 12 | I192: N | J192: N | K192: 0 | L192: OR | M192: =IF(L192="GEN","GM",L192) -> OR
A193: SH-9000192 | B193: ST-74114 | C193: NURSE | D193: W-07 | E193: 45669 | F193: NIGHT | G193: 11.5 | H193: 11.5 | I193: N | J193: N | K193: 0 | L193: OR | M193: =IF(L193="GEN","GM",L193) -> OR
A194: SH-9000193 | B194: ST-73272 | C194: NURSE | D194: W-07 | E194: 45669 | F194: NIGHT | G194: 11.5 | H194: 11.5 | I194: Y | J194: N | K194: 0 | L194: GM | M194: =IF(L194="GEN","GM",L194) -> GM
A195: SH-9000194 | B195: ST-94518 | C195: REG | D195: W-07 | E195: 45669 | F195: DAY | G195: 7.5 | H195: 7.5 | I195: N | J195: N | K195: 0 | L195: GS | M195: =IF(L195="GEN","GM",L195) -> GS
A196: SH-9000195 | B196: ST-22785 | C196: NURSE | D196: W-07 | E196: 45669 | F196: NIGHT | G196: 11.5 | H196: 11.5 | J196: N | K196: 0 | L196: GEN | M196: =IF(L196="GEN","GM",L196) -> GM
...
