Workbook

Sheet README
A1: Bronings University Hospital Group — 18-KPI Research Pack
A2: Phase 2 deliverable · Prepared for Tom Nguyen (Director of Operations) · Input to the Phase 5 KPI Design Workshop and Phase 6 dashboards
A3: Prepared by: Lucky Ukeni, Advanced Healthcare Data Analyst · 17 January 2025 · Status: DRAFT for workshop
A5: Purpose
A6: Bronings has no agreed KPI framework — three departments produced three DNA rates (9.8%, 12.4%, 14.1%) from the same data. This pack fixes one definition per KPI so every stakeholder works from the same formula, source, standard, target and owner.
A8: How the 7 required fields map to KPI_Register (columns C–K, blue headers)
A9: 1. KPI name and abbreviation → columns C–D · 2. Formula → column E (numerator F, denominator G, rules H) · 3. Data source → columns I–J · 4. NHS England standard → column K
A10: 5. Bronings Trust target → column L · 6. Operational owner (department) → column M (named lead in N) · 7. Business decision supported → column O
A11: Columns P onwards (grey headers) add value for the workshop: numeric targets, current figure, gap, data confidence, action on breach and sources.
A13: Sheets
A14: KPI_Register — the 18 KPIs. Gap_Analysis — current vs Trust target vs NHS standard (formula-driven). DNA_Method — the three DNA figures explained, with a calculator. Financial_Exposure — the brief's £ risk rebuilt with formulas. Sources — references.
A16: Legend
... A24: NHS England sets constitutional standards (e.g. 95% ED 4-hour, 92% RTT) and lower annual interim planning targets (e.g. 78% ED 4-hour by March 2025). Both are shown. Simulation date is January 2025, so 2024/25 and 2025/26 planning guidance apply.

Sheet KPI_Register
A1: KPI_ID | B1: Domain | C1: 1. KPI name | D1: 1. Abbreviation | E1: 2. Formula (exact calculation) | F1: Numerator | G1: Denominator | H1: Inclusion / exclusion rules | I1: 3. Data source — system | J1: 3. Data source — sheet & column(s) | K1: 4. NHS England standard / benchmark | L1: 5. Bronings Trust target | M1: 6. Operational owner (department) | N1: Named lead | O1: 7. Business decision supported | P1: Unit | Q1: Better when | R1: Bronings current | S1: NHS standard (value) | T1: Trust target (value) | U1: Gap to NHS standard | V1: Status vs NHS standard | W1: Data confidence | X1: Why confidence is limited | Y1: Action on breach | Z1: Reporting frequency | AA1: Benchmark source
A2: K01 | B2: Emergency | C2: ED 4-hour target compliance | D2: 4HT | E2: (ED attendances with Departure_DateTime − Arrival_DateTime ≤ 4 hours) ÷ (all ED attendances) × 100 | F2: ED attendances admitted, transferred or discharged within 240 minutes of arrival | G2: All ED attendances in the period | H2: All departure types counted (ADM, DISC, LWBS, transfer). Remove duplicate ED-IDs. Reformat 14 Nov 2024 downtime entries (DD-MM-YYYY HH:MM) before calculating. | I2: EDIS | J2: ED_Attendances: ED_ID ✔ (ED-XXXXXXX), Arrival_DateTime [?], Departure_DateTime [?], Departure_Method [?] | K2: 95% (NHS Constitution). Interim: 78% by March 2025 (2024/25 planning guidance) | L2: 90% | M2: Urgent & Emergency Care (Operations) | N2: Tom Nguyen, Director of Operations | O2: ED staffing and flow investment; escalation (OPEL) decisions; the headline figure NHS England will test. | P2: % | Q2: Higher | R2: 0.813 | S2: 0.95 | T2: 0.9 | U2: =IF(OR(R2="",S2=""),"",IF(Q2="Higher",R2-S2,IF(Q2="Lower",S2-R2,""))) -> -0.137 | V2: =IF(R2="","No current figure",IF(S2="","No national target",IF(Q2="Higher",IF(R2>=S2,"Meeting","Breaching"),IF(Q2="Lower",IF(R2<=S2,"Meeting","Breaching"),"Context only")))) -> Breaching | W2: Amber | X2: Board figure is counted by eye in a filtered view — no audit trail. 14 Nov 2024 manual entries in non-standard date format. | Y2: Below 78%: daily breach review by cause (bed wait / clinical / assessment). Below Trust target 3 months running: recovery plan to Board. | Z2: Daily; monthly statutory | AA2: NHS Constitution; NHS England 2024/25 planning guidance
A3: K02 | B3: Emergency | C3: ED Left Without Being Seen rate | D3: LWBS | E3: (ED attendances with Departure_Method = 'LWBS') ÷ (all ED attendances) × 100 | F3: Attendances coded LWBS | G3: All ED attendances in the period | H3: Glossary code LWBS only. Same cleaning rules as 4HT. | I3: EDIS | J3: ED_Attendances: Departure_Method [?] (code LWBS ✔), ED_ID ✔ | K3: ≤5% (A&E clinical quality indicators, DH 2010/11). No current national target | L3: Proposed: <5% | M3: Urgent & Emergency Care (ED) | N3: ED Clinical Lead (reports to Tom Nguyen) | O3: Triage and streaming capacity; front-door staffing at peak arrival times. | P3: % | Q3: Lower | S3: 0.05 | T3: 0.05 | U3: =IF(OR(R3="",S3=""),"",IF(Q3="Higher",R3-S3,IF(Q3="Lower",S3-R3,""))) | V3: =IF(R3="","No current figure",IF(S3="","No national target",IF(Q3="Higher",IF(R3>=S3,"Meeting","Breaching"),IF(Q3="Lower",IF(R3<=S3,"Meeting","Breaching"),"Context only")))) -> No current figure | W3: Amber | X3: Depends on correct departure coding in EDIS; not yet profiled. | Y3: Above 5%: review by hour/day; check triage-to-clinician times; re-roster to peaks. | Z3: Weekly / monthly | AA3: A&E Clinical Quality Indicators (DH)
A4: K03 | B4: Outpatients | C4: DNA (Did Not Attend) rate | D4: DNA | E4: COUNTIF(ATT_STATUS,"DNA") ÷ (COUNTIF(ATT_STATUS,"ATT") + COUNTIF(ATT_STATUS,"DNA") + COUNTIF(ATT_STATUS,"REF")) × 100 | F4: Appointments with ATT_STATUS = DNA | G4: All booked appointments excluding cancellations (ATT + DNA + REF) | H4: Exclude CAN (Trust cancellations) and blank status. Fixed period = financial quarter. Exclude CL-OLD / CL-DEP clinics and 5-digit (truncated) APT-IDs pending validation. Workshop to confirm REF treatment. | I4: PAS | J4: Outpatient_Appointments: ATT_STATUS ✔ (column F), APT_ID ✔, clinic_code ✔, Appointment_Date [?] | K4: No constitutional standard. National average 7.6% (2021/22, NHS England). NHS England definition: denominator excludes cancelled appointments. Brief cites NHS <10% | L4: <8% | M4: Outpatients (Performance team) | N4: Sarah Okafor, Performance Manager | O4: Where to target SMS reminders, overbooking and clinic redesign; frees clinic capacity for RTT recovery. | P4: % | Q4: Lower | S4: 0.1 | T4: 0.08 | U4: =IF(OR(R4="",S4=""),"",IF(Q4="Higher",R4-S4,IF(Q4="Lower",S4-R4,""))) | V4: =IF(R4="","No current figure",IF(S4="","No national target",IF(Q4="Higher",IF(R4>=S4,"Meeting","Breaching"),IF(Q4="Lower",IF(R4<=S4,"Meeting","Breaching"),"Context only")))) -> No current figure | W4: Red | X4: Three competing figures (9.8% / 12.4% / 14.1%) — none valid. See DNA_Method sheet. | Y4: Above 8%: drill down by specialty and clinic; check reminder coverage; review repeat non-attenders for safeguarding ('was not brought'). | Z4: Monthly | AA4: NHS England: Reducing DNAs in outpatient services
A5: K04 | B5: Elective | C5: RTT 18-week compliance | D5: RTT18 | E5: (Open RTT pathways with clock-start-to-month-end ≤ 18 weeks) ÷ (all open RTT pathways) × 100 | F5: Incomplete pathways waiting 18 weeks or less | G5: All incomplete (open) RTT pathways at month end | H5: Incomplete pathways only. Remove pathways that have stopped but are still marked OPEN (suspected cause of the 12–18 patient PAS vs Unify2 gap). | I5: PAS | J5: RTT_Compliance (rebuild — pivot stale since Aug 2024); Outpatient_Appointments: Referral_Date [?], Waiting_Days ✔, Pathway_Status [?] | K5: 92% (NHS Constitution). Interim: 65% nationally by March 2026, every trust +5 points (2025/26 guidance) | L5: 88% | M5: Elective Care / Planned Care (Operations) | N5: Tom Nguyen, Director of Operations | O5: Which specialties need extra capacity, outsourcing or validation; statutory monthly RTT submission. | P5: % | Q5: Higher | R5: 0.748 | S5: 0.92 | T5: 0.88 | U5: =IF(OR(R5="",S5=""),"",IF(Q5="Higher",R5-S5,IF(Q5="Lower",S5-R5,""))) -> -0.172 | V5: =IF(R5="","No current figure",IF(S5="","No national target",IF(Q5="Higher",IF(R5>=S5,"Meeting","Breaching"),IF(Q5="Lower",IF(R5<=S5,"Meeting","Breaching"),"Context only")))) -> Breaching | W5: Red | X5: RTT_Compliance pivot on manual refresh since August 2024 — 74.8% may be an August figure. v13 VLOOKUP error. PAS vs Unify2 gap unresolved. | Y5: Specialty breakdown monthly; any specialty below target gets a recovery trajectory; validate open pathways before each submission. | Z5: Monthly statutory | AA5: NHS Constitution; NHS England 2025/26 planning guidance
A6: K05 | B6: Elective | C6: Waiting list size (open RTT pathways) | D6: RTT-WL | E6: COUNT of open RTT pathways at month-end snapshot (= denominator of RTT18) | F6: Open RTT pathways at month end | G6: n/a — count (trend vs previous month and vs plan trajectory) | H6: Validated open pathways only; de-duplicate on valid 10-digit NHS Number + pathway ID. | I6: PAS | J6: Outpatient_Appointments / RTT_Compliance: Pathway_ID [?], Pathway_Status [?], NHS_Number ✔ | K6: No fixed national size target. NHS England tracks list size monthly; 2025/26 guidance sets 18-week and 52-week ratios rather than list size | L6: Proposed: month-on-month reduction against agreed trajectory | M6: Elective Care (Operations / Performance) | N6: Sarah Okafor, Performance Manager | O6: Capacity-vs-demand planning; validation programme; outsourcing and insourcing decisions. | P6: Count | Q6: Lower | U6: =IF(OR(R6="",S6=""),"",IF(Q6="Higher",R6-S6,IF(Q6="Lower",S6-R6,""))) | V6: =IF(R6="","No current figure",IF(S6="","No national target",IF(Q6="Higher",IF(R6>=S6,"Meeting","Breaching"),IF(Q6="Lower",IF(R6<=S6,"Meeting","Breaching"),"Context only")))) -> No current figure | W6: Amber | X6: Includes pathways that have stopped but remain OPEN; truncated NHS Numbers may create duplicates. | Y6: List growing for 2+ months: demand/capacity review by specialty; prioritise validation. | Z6: Weekly / monthly | AA6: NHS England RTT waiting times statistics
A7: K06 | B7: Elective | C7: Patients waiting more than 52 weeks | D7: RTT52 | E7: COUNTIFS(Pathway_Status,"OPEN", Waiting_Weeks,">52") — also report >104 weeks separately | F7: Open RTT pathways waiting over 52 weeks | G7: n/a — count (also as % of waiting list) | H7: Same validation as RTT18. Report >104-week patients (currently 47) as a sub-count. | I7: PAS | J7: RTT_Compliance; Outpatient_Appointments: Waiting_Days ✔ (÷7), Pathway_Status [?] | K7: Zero; 2025/26 interim: fewer than 1% of the waiting list by March 2026 | L7: 0 | M7: Elective Care (Operations) | N7: Tom Nguyen, Director of Operations | O7: Prioritising long-waiters; mutual aid and outsourcing; financial exposure (£14,000 per breach per brief). | P7: Count | Q7: Lower | R7: 312 | S7: 0 | T7: 0 | U7: =IF(OR(R7="",S7=""),"",IF(Q7="Higher",R7-S7,IF(Q7="Lower",S7-R7,""))) -> -312 | V7: =IF(R7="","No current figure",IF(S7="","No national target",IF(Q7="Higher",IF(R7>=S7,"Meeting","Breaching"),IF(Q7="Lower",IF(R7<=S7,"Meeting","Breaching"),"Context only")))) -> Breaching | W7: Amber | X7: Count depends on unvalidated open pathways (PAS vs Unify2 differ by 12–18 patients). | Y7: Weekly patient-level list with a treatment date for each; clinical harm review for every patient over 52 weeks. | Z7: Weekly / monthly | AA7: NHS England 2025/26 planning guidance
A8: K07 | B8: Elective | C8: Theatre utilisation rate | D8: TU | E8: Recommended (GIRFT capped): SUM(touch-time within planned session, capped at session end) ÷ SUM(planned session time) × 100. Current Trust method: Sessions_Used ÷ Sessions_Available | F8: Capped operating (touch) time in elective sessions | G8: Planned elective session time (T1–T3) | H8: Exclude T4 (emergency & trauma). Weeks where Sessions_Used > Sessions_Available are entry errors — fix at source; stop the silent 'fudge' rule. | I8: TMS | J8: Theatre_Utilisation: Sessions_Used ✔, Sessions_Available ✔, Theatre_ID ✔ (T1–T4), Planned_Hours [?], Touch_Time_Hours [?] | K8: 85% capped touch-time utilisation (GIRFT, 2024/25) | L8: 85% | M8: Theatres & Anaesthetics (Surgical division) | N8: Theatres Manager (accountable: Tom Nguyen) | O8: Session planning and reallocation; list scheduling; whether to cancel or repurpose under-used sessions (~£180k/month unused). | P8: % | Q8: Higher | R8: 0.63 | S8: 0.85 | T8: 0.85 | U8: =IF(OR(R8="",S8=""),"",IF(Q8="Higher",R8-S8,IF(Q8="Lower",S8-R8,""))) -> -0.22 | V8: =IF(R8="","No current figure",IF(S8="","No national target",IF(Q8="Higher",IF(R8>=S8,"Meeting","Breaching"),IF(Q8="Lower",IF(R8<=S8,"Meeting","Breaching"),"Context only")))) -> Breaching | W8: Amber | X8: No agreed definition: 63% (sessions) vs 71% (hours) vs a third TMS method. | Y8: Below 85%: session-level review of late starts, early finishes, on-the-day cancellations; reallocate persistently unused sessions. | Z8: Weekly / monthly | AA8: GIRFT Theatre Productivity programme
A9: K08 | B9: Elective | C9: Cancelled operations rate | D9: CANOP | E9: (Elective operations cancelled at the last minute for non-clinical reasons) ÷ (elective admissions) × 100; plus % of those patients not treated within 28 days | F9: Last-minute non-clinical cancellations (on the day or after arrival) | G9: All elective (ELEC) admissions in the period | H9: Last minute = on the day of surgery or after admission. Non-clinical reasons only (e.g. no bed, list over-run, staff). Exclude patient-initiated cancellations. | I9: TMS + EHR | J9: Theatre_Utilisation: Cancellation_Reason [?], Cancellation_Date [?]; Inpatient_Admissions: Admission_Type = ELEC ✔ | K9: National ≈0.9% of elective activity (Q2 2025/26). NHS Constitution: every patient offered a binding new date within 28 days | L9: Proposed: <0.8%; 100% rebooked within 28 days | M9: Theatres & Surgical division (with Patient Flow) | N9: Theatres Manager / Tom Nguyen | O9: Protecting elective beds; list planning; statutory Cancelled Operations return. | P9: % | Q9: Lower | T9: 0.008 | U9: =IF(OR(R9="",S9=""),"",IF(Q9="Higher",R9-S9,IF(Q9="Lower",S9-R9,""))) | V9: =IF(R9="","No current figure",IF(S9="","No national target",IF(Q9="Higher",IF(R9>=S9,"Meeting","Breaching"),IF(Q9="Lower",IF(R9<=S9,"Meeting","Breaching"),"Context only")))) -> No current figure | W9: Unknown | X9: Cancellation fields not yet profiled in the TMS export; TMS does not always update cancelled sessions (pipeline issue 5). | Y9: Any breach of 28-day rule escalated to Tom; weekly review of cancellation reasons (bed availability vs theatre). | Z9: Monthly statutory (quarterly national publication) | AA9: NHS England Cancelled Elective Operations statistics
A10: K09 | B10: Flow & Quality | C10: Bed occupancy rate | D10: BOR | E10: (Occupied general & acute beds at midnight census, averaged over period) ÷ (available G&A beds) × 100 | F10: Occupied beds at midnight (from admissions spanning midnight) | G10: Available beds (380; exclude W-08) | H10: Exclude W-08 (decommissioned Feb 2024). Midnight census averaged over the period. | I10: EHR | J10: Inpatient_Admissions: Admission_Date [?], Discharge_Date [?], Ward_Code ✔ (W-01–W-08); bed base = 380 (brief) | K10: ≤92% (2023/24 planning guidance) | L10: <85% | M10: Patient Flow / Site Management (Operations) | N10: Tom Nguyen, Director of Operations | O10: Escalation beds, discharge focus, elective bed protection; the root driver of ED breaches. | P10: % | Q10: Lower | S10: 0.92 | T10: 0.85 | U10: =IF(OR(R10="",S10=""),"",IF(Q10="Higher",R10-S10,IF(Q10="Lower",S10-R10,""))) | V10: =IF(R10="","No current figure",IF(S10="","No national target",IF(Q10="Higher",IF(R10>=S10,"Meeting","Breaching"),IF(Q10="Lower",IF(R10<=S10,"Meeting","Breaching"),"Context only")))) -> No current figure | W10: Unknown | X10: Bed_Occupancy sheet disappeared in workbook v11; method undocumented. | Y10: Above 92%: daily discharge huddles, long-stayer (>21 days) review, protect elective beds. | Z10: Daily / monthly | AA10: NHS England 2023/24 planning guidance
A11: K10 | B11: Flow & Quality | C11: Average length of stay | D11: ALOS | E11: SUM(Discharge_Date − Admission_Date) ÷ COUNT(discharged spells) | F11: Total bed days for spells discharged in the period | G11: Number of spells discharged in the period | H11: Discharged spells only. Report elective and emergency separately; exclude day cases (LOS = 0). | I11: EHR | J11: Inpatient_Admissions: Admission_Date [?], Discharge_Date [?], Admission_Type ✔ (ELEC/EMER), Discharge_Method ✔ (HOME/TRANSFER) | K11: No national target — benchmark vs peers (Model Health System). Brief cites <4.5 days | L11: <4.5 days | M11: Medical & Surgical divisions (Patient Flow) | N11: Medical Director (with Director of Operations) | O11: Discharge process improvement; community capacity; specialty bed allocation. | P11: Days | Q11: Lower | S11: 4.5 | T11: 4.5 | U11: =IF(OR(R11="",S11=""),"",IF(Q11="Higher",R11-S11,IF(Q11="Lower",S11-R11,""))) | V11: =IF(R11="","No current figure",IF(S11="","No national target",IF(Q11="Higher",IF(R11>=S11,"Meeting","Breaching"),IF(Q11="Lower",IF(R11<=S11,"Meeting","Breaching"),"Context only")))) -> No current figure | W11: Unknown | X11: Not currently calculated; admission/discharge dates not yet profiled. | Y11: Above target: ward and specialty drill-down; review delayed discharges and patients with no criteria to reside. | Z11: Monthly | AA11: Model Health System; company brief
A12: K11 | B12: Flow & Quality | C12: 30-day readmission rate | D12: RA30 | E12: (Emergency readmissions within 30 days of a previous discharge) ÷ (all discharges in the period) × 100 | F12: Discharges followed by an EMER admission within 30 days | G12: All discharges in the period | H12: Emergency readmissions only. Back-fill blank Readmission_Flag using admission-date logic (Nov 2024 governance decision). | I12: EHR | J12: Inpatient_Admissions: Readmission_Flag ✔ (41 rows blank), Admission_Type ✔, Admission_Date [?], Discharge_Date [?], NHS_Number ✔ | K12: No national target; monitored in NHS Oversight Framework. Brief cites <10% | L12: <10% | M12: Clinical Governance (Medical Director's office) | N12: Medical Director | O12: Discharge quality, follow-up and community support decisions. | P12: % | Q12: Lower | S12: 0.1 | T12: 0.1 | U12: =IF(OR(R12="",S12=""),"",IF(Q12="Higher",R12-S12,IF(Q12="Lower",S12-R12,""))) | V12: =IF(R12="","No current figure",IF(S12="","No national target",IF(Q12="Higher",IF(R12>=S12,"Meeting","Breaching"),IF(Q12="Lower",IF(R12<=S12,"Meeting","Breaching"),"Context only")))) -> No current figure | W12: Red | X12: Readmission_Flag not populated by EHR — 41 rows blank; ownership disputed. | Y12: Above 10%: specialty case review of readmissions; check discharge-planning compliance. | Z12: Monthly | AA12: NHS Oversight Framework; company brief
A13: K12 | B13: Finance | C13: HRG coding completeness | D13: HRG% | E13: COUNTIFS(HRG_Code,"<>") ÷ COUNTA(Episode_ID) × 100; £ at risk = blank episodes × £1,850 | F13: Finished inpatient episodes with a valid HRG code | G13: All finished inpatient episodes in the period | H13: Finished episodes only (allow for coding lag in the current month). | I13: EHR → SUS | J13: Inpatient_Admissions: HRG_Code ✔, Episode_ID ✔ (EP-XXXXXXXX) | K13: 98% (brief); complete coding required for monthly SUS submission | L13: 98% | M13: Clinical Coding (Finance impact) | N13: Marcus Reid, Clinical Coding Manager (with Priya Chakrabarti) | O13: Coding resource allocation; income recovery before the SUS deadline (~£51,800/month at risk). | P13: % | Q13: Higher | S13: 0.98 | T13: 0.98 | U13: =IF(OR(R13="",S13=""),"",IF(Q13="Higher",R13-S13,IF(Q13="Lower",S13-R13,""))) | V13: =IF(R13="","No current figure",IF(S13="","No national target",IF(Q13="Higher",IF(R13>=S13,"Meeting","Breaching"),IF(Q13="Lower",IF(R13<=S13,"Meeting","Breaching"),"Context only")))) -> No current figure | W13: Amber | X13: ~28 blank episodes/month estimated; exact count to confirm in Phase 3. | Y13: Below 98%: send uncoded-episode list to Clinical Coding before SUS submission; report £ at risk to Priya. | Z13: Monthly | AA13: Company brief; SUS submission requirements
A14: K13 | B14: Finance | C14: Agency spend as % of total staff cost | D14: AGY% | E14: SUM(cost of shifts where Agency_Flag = 'Y') ÷ SUM(total staff cost) × 100 — report best/worst case until blank flags are resolved | F14: Agency staff cost (£) | G14: Total staff cost / pay bill (£) | H14: Exclude WRS training records (Staff_ID starting ST-99). Classify blank Agency_Flag shifts (bank vs agency) before calculating; reconcile to the Finance ledger. | I14: WRS + Finance System | J14: Workforce_Staffing: Agency_Flag ✔, Staff_ID ✔, Shift_ID ✔, Grade ✔, Shift_Cost [?]; Finance ledger agency cost centres | K14: Max 3.2% of total pay bill (2024/25 guidance); minimum 30% reduction in agency spend (2025/26) | L14: <8% (brief) — above the national cap; recommend review | M14: Finance (with Workforce) | N14: Priya Chakrabarti, Finance Business Partner | O14: Agency approval controls; recruitment business cases; workforce spend reporting to the Board. | P14: % | Q14: Lower | S14: 0.032 | T14: 0.08 | U14: =IF(OR(R14="",S14=""),"",IF(Q14="Higher",R14-S14,IF(Q14="Lower",S14-R14,""))) | V14: =IF(R14="","No current figure",IF(S14="","No national target",IF(Q14="Higher",IF(R14>=S14,"Meeting","Breaching"),IF(Q14="Lower",IF(R14<=S14,"Meeting","Breaching"),"Context only")))) -> No current figure | W14: Red | X14: Blank Agency_Flag for bank shifts booked outside the agency module — never quantified. Spend estimated £2.3m/yr. | Y14: Above cap: executive sign-off for agency shifts; ward-level review of blank-flag shifts; monthly ledger reconciliation with documented assumptions. | Z14: Monthly | AA14: NHS England 2024/25 & 2025/26 planning guidance
A15: K14 | B15: Finance | C15: Cost per patient episode | D15: CPE | E15: Total operating cost (£) ÷ number of finished patient episodes; also by HRG / specialty | F15: Total operating expenditure in the period (£) | G15: Finished patient episodes in the period | H15: Use the same period and scope for cost and activity (e.g. inpatients only, or all points of delivery). Uncoded episodes understate activity — fix HRG% first. | I15: Finance System + EHR | J15: Finance ledger (actuals by cost centre); Inpatient_Admissions: Episode_ID ✔, HRG_Code ✔, Specialty_Code ✔ | K15: No national target. Benchmark vs peers using National Cost Collection / Model Health System | L15: Proposed: at or below peer median | M15: Finance (Service Line Reporting) | N15: Priya Chakrabarti, Finance Business Partner | O15: Service-line efficiency and cost-improvement plans; pricing and contract negotiations. | P15: £ | Q15: Lower | U15: =IF(OR(R15="",S15=""),"",IF(Q15="Higher",R15-S15,IF(Q15="Lower",S15-R15,""))) | V15: =IF(R15="","No current figure",IF(S15="","No national target",IF(Q15="Higher",IF(R15>=S15,"Meeting","Breaching"),IF(Q15="Lower",IF(R15<=S15,"Meeting","Breaching"),"Context only")))) -> No current figure | W15: Unknown | X15: Finance_Reconciliation sheet undocumented; episode counts affected by blank HRG codes. | Y15: Above peer median: specialty cost drill-down (pay, drugs, theatre time); feed into cost-improvement plan. | Z15: Monthly / quarterly | AA15: National Cost Collection; Model Health System
A16: K15 | B16: Quality & Safety | C16: Patient safety incident rate | D16: PSIR | E16: (Patient safety incidents reported) ÷ (occupied bed days) × 1,000; plus % causing moderate or severe harm | F16: Patient safety incidents reported in the period | G16: Occupied bed days in the period (÷ 1,000) | H16: All reported incidents (LFPSE). Report harm level separately — a high reporting rate with low harm indicates a good reporting culture. | I16: Incident system (LFPSE / Datix) + EHR | J16: Not in master workbook — incident export required; bed days from Inpatient_Admissions: Admission_Date [?], Discharge_Date [?] | K16: No national target. NHS England publishes LFPSE patient safety event statistics quarterly for comparison | L16: Proposed: reporting rate at or above peer median; moderate+ harm reducing | M16: Patient Safety / Clinical Governance | N16: Medical Director and Chief Nurse | O16: Safety improvement priorities under PSIRF; learning and assurance to the Board and CQC. | P16: Per 1,000 | Q16: Context | U16: =IF(OR(R16="",S16=""),"",IF(Q16="Higher",R16-S16,IF(Q16="Lower",S16-R16,""))) | V16: =IF(R16="","No current figure",IF(S16="","No national target",IF(Q16="Higher",IF(R16>=S16,"Meeting","Breaching"),IF(Q16="Lower",IF(R16<=S16,"Meeting","Breaching"),"Context only")))) -> No current figure | W16: Unknown | X16: Incident data not in the workbook; needs a new feed (flag to Daniel Walsh). | Y16: Falling reporting or rising moderate+ harm: Patient Safety team review; themes to Quality Committee. | Z16: Monthly | AA16: NHS England patient safety data (LFPSE)
A17: K16 | B17: Workforce | C17: Staff vacancy rate | D17: VAC | E17: (Funded establishment WTE − staff in post WTE) ÷ funded establishment WTE × 100 | F17: Vacant funded WTE | G17: Funded establishment WTE | H17: Use the finance-funded establishment; report by staff group (CONS, REG, SHO, NURSE, HCA) and ward. | I17: Finance System + ESR/WRS | J17: Finance establishment ledger; Workforce_Staffing: Staff_ID ✔, Grade ✔ (staff in post) | K17: No national target. Benchmark vs NHS England quarterly NHS Vacancy Statistics | L17: Proposed: at or below national rate for each staff group | M17: Workforce / HR | N17: Adaeze Obi, Workforce Planning Manager | O17: Recruitment priorities and business cases; root cause of agency spend (AGY%). | P17: % | Q17: Lower | U17: =IF(OR(R17="",S17=""),"",IF(Q17="Higher",R17-S17,IF(Q17="Lower",S17-R17,""))) | V17: =IF(R17="","No current figure",IF(S17="","No national target",IF(Q17="Higher",IF(R17>=S17,"Meeting","Breaching"),IF(Q17="Lower",IF(R17<=S17,"Meeting","Breaching"),"Context only")))) -> No current figure | W17: Unknown | X17: Establishment data not in the workbook. | Y17: Above benchmark: targeted recruitment plan for hot-spot wards; skill-mix review. | Z17: Quarterly | AA17: NHS England Digital: NHS Vacancy Statistics
A18: K17 | B18: Data Quality | C18: DSP Toolkit DQMI score | D18: DQMI | E18: NHS England DQMI: average across national datasets (e.g. SUS) of the % of data items that are complete and valid. Internal proxy = valid & complete key fields ÷ total key fields × 100 | F18: Valid and complete data items submitted | G18: All data items submitted | H18: Internal proxy uses Phase 3 field rules (e.g. NHS Number = 10 digits + Modulus 11; Specialty_Code in mapping table; valid dates). | I18: NHS England DQMI publication; internal DQ_Issue_Log | J18: DQ_Issue_Log (incomplete); all five export sheets | K18: 75 / 100 = acceptable threshold (brief) | L18: ≥75 by DSP Toolkit submission (March); internal DQ score >95% | M18: Analytics / Information (with Information Governance) | N18: Head of Analytics (vacant — interim analyst); Fiona Lawson, IG Lead | O18: Which data fixes to prioritise; evidence for the DSP Toolkit submission and £380k CQUIN. | P18: Score | Q18: Higher | R18: 52 | S18: 75 | T18: 75 | U18: =IF(OR(R18="",S18=""),"",IF(Q18="Higher",R18-S18,IF(Q18="Lower",S18-R18,""))) -> -23 | V18: =IF(R18="","No current figure",IF(S18="","No national target",IF(Q18="Higher",IF(R18>=S18,"Meeting","Breaching"),IF(Q18="Lower",IF(R18<=S18,"Meeting","Breaching"),"Context only")))) -> Breaching | W18: Green | X18: Published score — defensible as a figure. The underlying data quality is the problem. | Y18: Below 75: prioritised fix list via Daniel Walsh's pipeline queue; monthly DQ report to Tom. | Z18: Monthly | AA18: NHS Data Quality Maturity Index; company brief
A19: K18 | B19: Data Quality | C19: RTT clock start to stop accuracy | D19: RTT-CSA | E19: (Validated RTT pathways with correct clock start and clock stop per the RTT rules) ÷ (RTT pathways validated) × 100; plus count of negative waits and PAS-vs-Unify2 difference | F19: Sampled pathways whose clock start (referral date) and clock stop (treatment / decision) are correctly recorded | G19: Pathways validated in the period (sample or full) | H19: Apply national RTT rules suite. Negative Waiting_Days (4 rows) = automatic fail. Include transferred-in patients with original clock start. | I19: PAS (vs Unify2 portal) | J19: Outpatient_Appointments: Referral_Date [?], Appointment_Date [?], Waiting_Days ✔, RTT_Status / outcome code [?]; Unify2 submission totals | K19: NHS England RTT rules suite: every pathway must have a recorded clock start and clock stop; Trust boards must assure waiting-time data quality | L19: Proposed: ≥98% of validated pathways correct; 0 negative waits; PAS = Unify2 | M19: Elective Access / Performance team | N19: Sarah Okafor, Performance Manager | O19: Whether the RTT submission can be defended to NHS England; how much validation resource is needed. | P19: % | Q19: Higher | T19: 0.98 | U19: =IF(OR(R19="",S19=""),"",IF(Q19="Higher",R19-S19,IF(Q19="Lower",S19-R19,""))) | V19: =IF(R19="","No current figure",IF(S19="","No national target",IF(Q19="Higher",IF(R19>=S19,"Meeting","Breaching"),IF(Q19="Lower",IF(R19<=S19,"Meeting","Breaching"),"Context only")))) -> No current figure | W19: Red | X19: 4 negative Waiting_Days rows; PAS and Unify2 differ by 12–18 patients every month; closed pathways left OPEN. | Y19: Below 98% or any negative wait: correct before submission; root-cause with PAS team; report to Tom. | Z19: Monthly (before each RTT submission) | AA19: NHS England: Recording and reporting RTT waiting times guidance
C21: Summary
C22: KPIs in framework | D22: =COUNTA(A2:A19) -> 18
C23: Breaching NHS standard | D23: =COUNTIF(V2:V19,"Breaching") -> 5
C24: No current figure | D24: =COUNTIF(V2:V19,"No current figure") -> 13
C25: Confidence: Green | D25: =COUNTIF(W2:W19,"Green") -> 1
C26: Confidence: Amber | D26: =COUNTIF(W2:W19,"Amber") -> 6
C27: Confidence: Red | D27: =COUNTIF(W2:W19,"Red") -> 5
C28: Confidence: Unknown | D28: =COUNTIF(W2:W19,"Unknown") -> 6
C29: Trust targets still to be agreed (Proposed) | D29: =COUNTIF(L2:L19,"Proposed*") -> 7

Sheet Gap_Analysis
A1: KPI_ID | B1: KPI | C1: Abbr. | D1: Unit | E1: Better when | F1: Bronings current | G1: Trust target | H1: NHS standard | I1: NHS interim target | J1: Gap to Trust target | K1: Gap to NHS standard | L1: Gap to interim | M1: Status vs NHS standard
A2: =KPI_Register!A2 -> K01 | B2: =KPI_Register!C2 -> ED 4-hour target compliance | C2: =KPI_Register!D2 -> 4HT | D2: =KPI_Register!P2 -> % | E2: =KPI_Register!Q2 -> Higher | F2: =KPI_Register!R2 -> 0.813 | G2: =KPI_Register!T2 -> 0.9 | H2: =KPI_Register!S2 -> 0.95 | I2: 0.78 | J2: =IF(G2="","",IF(E2="Higher",F2-G2,G2-F2)) -> -0.087 | K2: =IF(H2="","",IF(E2="Higher",F2-H2,H2-F2)) -> -0.137 | L2: =IF(I2="","",IF(E2="Higher",F2-I2,I2-F2)) -> 0.033 | M2: =IF(K2="","",IF(K2>=0,"Meeting","Breaching")) -> Breaching
A3: =KPI_Register!A5 -> K04 | B3: =KPI_Register!C5 -> RTT 18-week compliance | C3: =KPI_Register!D5 -> RTT18 | D3: =KPI_Register!P5 -> % | E3: =KPI_Register!Q5 -> Higher | F3: =KPI_Register!R5 -> 0.748 | G3: =KPI_Register!T5 -> 0.88 | H3: =KPI_Register!S5 -> 0.92 | I3: 0.65 | J3: =IF(G3="","",IF(E3="Higher",F3-G3,G3-F3)) -> -0.132 | K3: =IF(H3="","",IF(E3="Higher",F3-H3,H3-F3)) -> -0.172 | L3: =IF(I3="","",IF(E3="Higher",F3-I3,I3-F3)) -> 0.098 | M3: =IF(K3="","",IF(K3>=0,"Meeting","Breaching")) -> Breaching
A4: =KPI_Register!A7 -> K06 | B4: =KPI_Register!C7 -> Patients waiting more than 52 weeks | C4: =KPI_Register!D7 -> RTT52 | D4: =KPI_Register!P7 -> Count | E4: =KPI_Register!Q7 -> Lower | F4: =KPI_Register!R7 -> 312 | G4: =KPI_Register!T7 -> 0 | H4: =KPI_Register!S7 -> 0 | J4: =IF(G4="","",IF(E4="Higher",F4-G4,G4-F4)) -> -312 | K4: =IF(H4="","",IF(E4="Higher",F4-H4,H4-F4)) -> -312 | L4: =IF(I4="","",IF(E4="Higher",F4-I4,I4-F4)) | M4: =IF(K4="","",IF(K4>=0,"Meeting","Breaching")) -> Breaching
A5: =KPI_Register!A8 -> K07 | B5: =KPI_Register!C8 -> Theatre utilisation rate | C5: =KPI_Register!D8 -> TU | D5: =KPI_Register!P8 -> % | E5: =KPI_Register!Q8 -> Higher | F5: =KPI_Register!R8 -> 0.63 | G5: =KPI_Register!T8 -> 0.85 | H5: =KPI_Register!S8 -> 0.85 | I5: 0.85 | J5: =IF(G5="","",IF(E5="Higher",F5-G5,G5-F5)) -> -0.22 | K5: =IF(H5="","",IF(E5="Higher",F5-H5,H5-F5)) -> -0.22 | L5: =IF(I5="","",IF(E5="Higher",F5-I5,I5-F5)) -> -0.22 | M5: =IF(K5="","",IF(K5>=0,"Meeting","Breaching")) -> Breaching
A6: =KPI_Register!A18 -> K17 | B6: =KPI_Register!C18 -> DSP Toolkit DQMI score | C6: =KPI_Register!D18 -> DQMI | D6: =KPI_Register!P18 -> Score | E6: =KPI_Register!Q18 -> Higher | F6: =KPI_Register!R18 -> 52 | G6: =KPI_Register!T18 -> 75 | H6: =KPI_Register!S18 -> 75 | J6: =IF(G6="","",IF(E6="Higher",F6-G6,G6-F6)) -> -23 | K6: =IF(H6="","",IF(E6="Higher",F6-H6,H6-F6)) -> -23 | L6: =IF(I6="","",IF(E6="Higher",F6-I6,I6-F6)) | M6: =IF(K6="","",IF(K6>=0,"Meeting","Breaching")) -> Breaching
A9: Notes
A10: Green text = linked from KPI_Register. Blue = input. Negative gap = shortfall.
A11: Interim targets: ED 4-hour 78% (March 2025, 2024/25 guidance); RTT 65% (March 2026, 2025/26 guidance); theatre 85% (GIRFT).
A12: ED 4-hour (81.3%) is already above the 78% national interim target — a positive point for the review, while still 13.7 points below the constitutional standard.
A13: Caution: RTT 74.8% may be stale (pivot not refreshed since Aug 2024). Theatre 63% is sessions-based; hours-based is 71%.
A14: Only 5 of 18 KPIs have a current figure. The DNA rate is disputed; the other 12 cannot yet be calculated reliably.

Sheet DNA_Method
A1: DNA rate — why three figures exist and the recommended method
A3: Version | B3: Reported value | C3: Where it lives | D3: Method | E3: Why it is wrong
A4: A — KPI_Summary (Operations) | B4: 0.098 | C4: KPI_Summary!D14 | D4: =COUNTIF(F:F,"DNA")/COUNTA(F:F) | E4: COUNTA counts the header row; CAN (Trust cancellations) included in denominator — understates the rate.
A5: B — Finance | B5: 0.124 | C5: Finance_Reconciliation!B7 | D5: Hardcoded value, last updated September 2024 | E5: Not linked to live data. This is the figure currently sent to the Board.
A6: C — PAS report | B6: 0.141 | C6: PAS reporting module | D6: PAS standard report, calendar-month filter | E6: Different period (calendar month vs financial quarter); method not documented.
A7: Recommended (NHS-aligned) | B7: =B22 -> 0.090607735 | C7: New DNA_Rate sheet (Phase 3) | D7: DNA ÷ (ATT + DNA + REF) | E7: Matches NHS England definition: denominator = all appointments excluding cancellations. Fixed period = financial quarter.
A10: Calculator — enter appointment counts by ATT_STATUS for one period
A11: Yellow cells are inputs. The values shown are ILLUSTRATIVE ONLY (not Bronings data) — replace with real counts in Phase 3.
A12: ATT — attended | B12: 8200
A13: DNA — did not attend | B13: 820
A14: CAN — cancelled by Trust | B14: 950
A15: REF — refused on the day | B15: 30
A16: Blank status rows | B16: 0
A17: Total rows incl. header (what COUNTA sees) | B17: =SUM(B12:B16)+1 -> 10001
A19: Method | B19: Result | C19: Formula logic
A20: Version A logic (broken) | B20: =B13/(B17-B16) -> 0.081991801 | C20: DNA ÷ (all non-blank rows incl. header and CAN)
A21: All booked incl. CAN, no header | B21: =B13/SUM(B12:B15) -> 0.082 | C21: DNA ÷ (ATT+DNA+CAN+REF)
A22: RECOMMENDED — NHS-aligned | B22: =B13/(B12+B13+B15) -> 0.090607735 | C22: DNA ÷ (ATT+DNA+REF) — cancellations and blanks excluded
A23: Alternative — DNA vs attended only | B23: =B13/(B12+B13) -> 0.090909091 | C23: DNA ÷ (ATT+DNA) — if workshop decides REF is excluded
A25: Spread between broken and recommended method (percentage points) | B25: =B22-B20 -> 0.008615934
A27: Decisions for the Phase 5 workshop
A28: 1. Adopt DNA ÷ (ATT + DNA + REF) as the single Trust definition (NHS England: denominator = appointments excluding cancellations).
A29: 2. Confirm whether REF (refused on the day) is treated as attended-equivalent (in denominator) or excluded entirely.
A30: 3. Fix the reporting period: financial quarter for Board, calendar month for operational review — always labelled.
A31: 4. Retire Version A (KPI_Summary D14) and Version B (hardcoded B7). One live formula, one owner (Performance Manager).
A32: 5. Apply DQ exclusions first: truncated 5-digit APT-IDs, CL-OLD / CL-DEP clinics, duplicate appointments.

Sheet Financial_Exposure
A1: Financial stakes from the company brief — rebuilt with formulas
A3: Issue | B3: Unit value (£) | C3: Volume | D3: Periods / yr | E3: Annual exposure (£) | F3: Basis / assumption
A4: Unused theatre capacity (63% vs 85%) | B4: 180000 | C4: 1 | D4: 12 | E4: =B4*C4*D4 -> 2160000 | F4: £180,000 per month (brief)
A5: Blank HRG codes — unpaid episodes | B5: 1850 | C5: 28 | D5: 12 | E5: =B5*C5*D5 -> 621600 | F5: £1,850 per episode × ~28 episodes per month (brief)
A6: Agency spend (untracked, estimate) | B6: 2300000 | C6: 1 | D6: 1 | E6: =B6*C6*D6 -> 2300000 | F6: £2.3m per year estimate — actual unknown (brief). This is total spend, not all of it is avoidable.
A7: RTT 52-week breach fines | B7: 14000 | C7: 312 | D7: 1 | E7: =B7*C7*D7 -> 4368000 | F7: £14,000 per breach per patient × 312 patients (brief). Treated as a one-off annual exposure.
A8: CQUIN income at risk | B8: 380000 | C8: 1 | D8: 1 | E8: =B8*C8*D8 -> 380000 | F8: £380,000 quality payments tied to data quality (brief)
A10: Sum of line items | E10: =SUM(E4:E8) -> 9829600
A11: Total stated in company brief | E11: 4200000
A12: Difference (to reconcile with Priya Chakrabarti) | E12: =E10-E11 -> 5629600
A14: Finding: the line items do not add up to the £4.2m stated in the brief. The basis of the £4.2m is undocumented (e.g. it may exclude agency spend or treat RTT fines differently). Agree the method and assumptions with Priya before any £ figure goes to the Board.

Sheet Sources
A1: Source | B1: Used for | C1: URL
A2: NHS Constitution for England | B2: ED 95% 4-hour; RTT 92% 18-week; 28-day cancelled operations pledge | C2: https://www.gov.uk/government/publications/the-nhs-constitution-for-england
A3: NHS England — 2024/25 priorities and operational planning guidance | B3: ED 78% (Mar 2025); agency cap 3.2% of pay bill | C3: https://www.england.nhs.uk/long-read/2024-25-priorities-and-operational-planning-guidance/
A4: NHS England — 2025/26 priorities and operational planning guidance | B4: RTT 65% by Mar 2026 (+5 pts per trust); 52-week <1%; ED 78% (Mar 2026); agency −30% | C4: https://www.england.nhs.uk/long-read/2025-26-priorities-and-operational-planning-guidance/
A5: NHS England — 2023/24 priorities and operational planning guidance | B5: G&A bed occupancy ≤92% | C5: https://www.england.nhs.uk/wp-content/uploads/2022/12/PRN00021-23-24-priorities-and-operational-planning-guidance-v1.1.pdf
A6: NHS England — Reducing did not attends (DNAs) in outpatient services | B6: DNA definition (denominator excludes cancellations); national 7.6% (2021/22) | C6: https://www.england.nhs.uk/long-read/reducing-did-not-attends-dnas-in-outpatient-services/
A7: GIRFT — Theatre productivity programme | B7: 85% capped touch-time theatre utilisation | C7: https://gettingitrightfirsttime.co.uk/hvlc/theatre-productivity/
A8: NHS England — Cancelled Elective Operations statistics (QMCO) | B8: Last-minute cancellation definition; national ≈0.9% of elective activity; 28-day standard | C8: https://www.england.nhs.uk/statistics/wp-content/uploads/sites/2/2025/11/QMCO-Statistical-Commentary-Q2-2025-26.pdf
A9: NHS England — Recording and reporting RTT waiting times guidance | B9: RTT clock start/stop rules; board assurance of waiting-time data quality | C9: https://www.england.nhs.uk/statistics/wp-content/uploads/sites/2/2025/10/Recording-and-reporting-RTT-waiting-times-guidance-v5.2-Feb25.pdf
A10: NHS England — Patient safety data (LFPSE statistics) | B10: Patient safety incident benchmarking | C10: https://www.england.nhs.uk/statistics/statistical-work-areas/patient-safety-data/
A11: NHS England Digital — NHS Vacancy Statistics | B11: Vacancy rate benchmark | C11: https://digital.nhs.uk/data-and-information/publications/statistical/nhs-vacancies-survey
A12: NHS England — National Cost Collection / Model Health System | B12: Cost per episode and length-of-stay peer benchmarks | C12: https://www.england.nhs.uk/costing-in-the-nhs/national-cost-collection/
... A15: Analytics Process Notes & Handover (J. Whitfield / D. Walsh) | B15: Column names, pipeline issues, DNA versions, open questions | C15: Internal — 02_process_notes
